Workbook
Name DistinctIssues: #REF!

Sheet Plan
A1: Name | B1: Date | C1: Process | D1: Est Hours | F1: Project Plan | G1: % | H1: Hours
A2: nachiket.kulawade | B2: 45204 | C2: Testing | D2: 4 | F2: Testing & Report Writing | G2: 0.65 | H2: {=Project[Budgetted Hours by Sales]*G2} -> 212.1535
A3: harshada.morje | B3: 45204 | C3: Testing | D3: 4 | F3: QA | G3: 0.25 | H3: {=Project[Budgetted Hours by Sales]*G3} -> 81.5975
A4: naveen.lagishetty | B4: 45204 | C4: Testing | D4: 4 | F4: PM | G4: 0.1 | H4: {=Project[Budgetted Hours by Sales]*G4} -> 32.639
A5: nachiket.kulawade | B5: 45205 | C5: Testing | D5: 4
A6: harshada.morje | B6: 45205 | C6: Testing | D6: 4
A7: naveen.lagishetty | B7: 45205 | C7: Testing | D7: 4
A8: nachiket.kulawade | B8: 45205 | C8: Report | D8: 4
A9: harshada.morje | B9: 45205 | C9: Report | D9: 4
A10: naveen.lagishetty | B10: 45205 | C10: Report | D10: 4
A11: nachiket.kulawade | B11: 45208 | C11: Testing | D11: 4
A12: harshada.morje | B12: 45208 | C12: Testing | D12: 4
A13: naveen.lagishetty | B13: 45208 | C13: Testing | D13: 4
A14: nachiket.kulawade | B14: 45208 | C14: Report | D14: 4
A15: harshada.morje | B15: 45208 | C15: Report | D15: 4
A16: naveen.lagishetty | B16: 45208 | C16: Report | D16: 4
... A70: manasi.varma | B70: 45219 | C70: QA | D70: 3

Sheet Project
A1: Name of Project | B1: Client | C1: Type of Report | D1: VPAT Needed | E1: What are we Testing | F1: What is the Unit of Testing | G1: No. of Units Being Tested as per project scope | H1: No. of Units in URL Sheet | I1: Initial Stage Units | J1: Project Status | K1: Estimated Start Date | L1: Estimated Delivery Date | M1: Delivered Date | N1: Delivered Time | O1: Budgetted Hours by Sales | P1: Additional Hours | Q1: New Members | R1: Total Team | S1: Mentor | T1: APM | U1: Captain | V1: No. of Working Days | W1: Planned Hours | X1: Actual Hours | Y1: Est VPAT | Z1: Total Issues | AA1: Total Issues Delivered | AB1: Total Perfect Issues
A2: MyLab Marketing VPAT Audit | B2: Pearson | C2: Bug - Every Bug on Every Page | D2: WCAG 2.1 | E2: Web | F2: Page/URL | G2: 70 | H2: 35 | I2: 4 | J2: Delivered | K2: 45204 | L2: 45219 | M2: 45219 | N2: Before 9 pm | O2: 326.39 | P2: =Project[[#This Row],[New Members]]*(Project[[#This Row],[Budgetted Hours by Sales]]*0.7%) -> 0 | Q2: 0 | R2: =ROWS(Team[]) -> 11 | S2: jayshree.sharma | T2: chhayanka.amberkar | U2: manasi.varma | V2: =NETWORKDAYS(Project[[#This Row],[Estimated Start Date]],Project[[#This Row],[Estimated Delivery Date]],HolidayList[]) -> 12 | W2: =SUM(Plan!D:D) -> 250 | X2: =Production!H3 -> 68.25 | Y2: =IF(Project[[#This Row],[VPAT Needed]]=0,0,IF(Project[[#This Row],[VPAT Needed]]="WCAG 2.0",Variables!E55,Variables!E56)) -> 24 | Z2: =(COUNTA('Final Report'!BC:BC)-1) -> 998 | AA2: =(COUNTIFS('Final Report'!AX:AX,"*Approved after Fixing*"))+(COUNTIFS('Final Report'!AX:AX,"*Yes Perfect Issue*"))+(COUNTIFS('Final Report'!AX:AX,"*New Issue - QA*"))+(COUNTIFS('Final Report'!AX:AX,"*New Issue*")) -> 14 | AB2: =COUNTIF('Final Report'!BK:BK,"*Perfect*") -> 0
G3: =IF(I2=B11,"Units are correct",IF(I2>B11,"Check why we testing LESS than needed","Check why we testing MORE than needed")) -> Check why we testing MORE than needed
A8: Automated tools | B8: Assistive Technologies | C8: Web Browsers | D8: How much Testing in % or Numbers
A9: Mark up validators | B9: JAWS 2022 | C9: Chrome
A10: Accessibility toolbars | B10: NVDA 2022 | C10: FF
A11: Color Contrast Analyzer | B11: VoiceOver | C11: Safari-Mac
A12: ZoomText | B12: VoiceOver | C12: iOS - Safari / iOS App
A13: Dragon | B13: TalkBack | C13: Android - Chrome / Android App
A15: Note: Please put all the team members including Associates, APM, TL
A17: Name | B17: Role
A18: nachiket.kulawade | B18: FT Tester
A19: harshada.morje | B19: FT Tester
A20: naveen.lagishetty | B20: FT Tester
A21: irfan.shaikh | B21: FT Tester
A22: kumar.reddy | B22: FT Tester
A23: manasi.varma | B23: Captain
A24: jayshree.sharma | B24: Mentor
A25: chhayanka.amberkar | B25: APM
A26: prerna.rane | B26: FT QA
A27: dilip.dharia | B27: AT Tester
A28: manisha.prakash
A35: Steps to Reproduce Start for Web | B35: Steps to Reproduce Start for App | D35: Component Keyword | F35: Login | H35: Labels
D36: Accessibility, Audit, Marketing, MLM-XL, MLVISION, MyLab, US, VPAT | H36: Accessibility, Audit, Marketing, MLM-XL, MLVISION, MyLab, US, VPAT
D42: Tested on
D43: Windows: 11 MAC OS: 12 iOS: 15 Android OS: 10

Sheet Production
A1: Employee | B1: Date | C1: Process | D1: No. of Hours | E1: No. of Units | G1: Timelines | H1: Numbers | K1: Row Labels | L1: No. of Issues | M1: Self QC Score | N1: BB Self QC Score | O1: QC Percentage | Q1: Row Labels | R1: No. of Issues | S1: Self QC QA Score | T1: BB Self QC QA Score | U1: QA Percentage | W1: Count of Finalized | X1: Column Labels | AL1: Status | AM1: (All) | AO1: Status | AP1: (All) | AS1: Count of Issue Name | AT1: Column Labels | AZ1: Issue Tested By | BA1: Count of Writing Score
A2: kumar.reddy | B2: 45208 | C2: Testing | D2: 3 | E2: 3 | G2: Project Est Hours | H2: =Project[[#This Row],[Budgetted Hours by Sales]]+Project[[#This Row],[Additional Hours]] -> 326.39 | K2: (blank) | L2: 59 | O2: 0 | Q2: (blank) | R2: 66 | U2: 0 | W2: Row Labels | X2: (blank) | Y2: To Be Approved | Z2: Delete - QA | AA2: Yes Perfect Issue | AB2: Approved after Fixing | AC2: Grand Total | AS2: Row Labels | AT2: (blank) | AU2: Grand Total | AZ2: (blank)
A3: naveen.lagishetty | B3: 45208 | C3: Testing | D3: 6 | E3: 6 | G3: Actual Production Hours | H3: =(SUM(D:D)-(SUMIF(C:C,"PM",D:D)+SUMIF(C:C,"Meeting",D:D))) -> 68.25 | K3: naveen.lagishetty | L3: 13 | M3: 50 | N3: 50 | O3: 100 | Q3: manasi.varma | R3: 3 | S3: 15 | U3: 0 | W3: (blank) | AL3: Row Labels | AM3: Wastage | AO3: Row Labels | AP3: New Issues | AS3: (blank) | AT3: 59 | AU3: 59 | AZ3: naveen.lagishetty | BA3: 8
A4: naveen.lagishetty | B4: 45208 | C4: Testing | D4: 1 | E4: 1 | G4: Total Units to be produced | H4: {=Project[No. of Units in URL Sheet]} -> 35 | K4: kumar.reddy | L4: 15 | M4: 75 | N4: 70 | O4: 93.333333 | Q4: manisha.prakash | R4: 22 | S4: 85 | U4: 0 | W4: naveen.lagishetty | Z4: 8 | AA4: 1 | AB4: 1 | AC4: 10 | AL4: (blank) | AO4: (blank) | AS4: naveen.lagishetty | AT4: 13 | AU4: 13 | AZ4: irfan shaikh | BA4: 1
A5: harshada.morje | B5: 45208 | C5: Meeting | D5: 0.5 | E5: 0 | G5: Delivery | H5: {=Project[Estimated Delivery Date]} -> 45219 | K5: irfan.shaikh | L5: 1 | M5: 5 | O5: 0 | Q5: Grand Total | R5: 91 | S5: 100 | U5: 0 | W5: irfan shaikh | AL5: naveen.lagishetty | AM5: 45 | AO5: naveen.lagishetty | AP5: 45 | AS5: kumar.reddy | AT5: 15 | AU5: 15 | AZ5: Kumar.reddy | BA5: 6
A6: harshada.morje | B6: 45208 | C6: Support | D6: 0.5 | E6: 10 | G6: Testing - To Be Approved | H6: =COUNTIF(Final_Report[Status],"To Be Approved") -> 0 | K6: nachiket.kulawade | L6: 2 | M6: 10 | O6: 0 | W6: Kumar.reddy | Y6: 2 | Z6: 3 | AA6: 5 | AB6: 5 | AC6: 15 | AL6: irfan shaikh | AM6: 8 | AO6: irfan shaikh | AP6: 8 | AS6: irfan.shaikh | AT6: 1 | AU6: 1 | AZ6: harshada.morje
A7: kumar.reddy | B7: 45209 | C7: Testing | D7: 5 | E7: 5 | G7: Reporting - To Be Approved | H7: =COUNTIF(Final_Report[Finalized],"To Be Approved") -> 2 | K7: harshada.morje | L7: 1 | M7: 5 | O7: 0 | W7: harshada.morje | AA7: 2 | AC7: 2 | AL7: Kumar.reddy | AM7: 21 | AO7: Kumar.reddy | AP7: 21 | AS7: nachiket.kulawade | AT7: 2 | AU7: 2 | AZ7: nachiket.kulawade
A8: kumar.reddy | B8: 45210 | C8: Testing | D8: 3 | E8: 3 | K8: Grand Total | L8: 91 | M8: 145 | N8: 120 | O8: 82.758621 | W8: nachiket.kulawade | AL8: harshada.morje | AM8: 14 | AO8: harshada.morje | AP8: 15 | AS8: harshada.morje | AT8: 1 | AU8: 1 | AZ8: Grand Total | BA8: 15
A9: irfan.shaikh | B9: 45210 | C9: Testing | D9: 3 | E9: 2 | W9: Grand Total | Y9: 2 | Z9: 11 | AA9: 8 | AB9: 6 | AC9: 27 | AL9: nachiket.kulawade | AM9: 3 | AO9: nachiket.kulawade | AP9: 3 | AS9: Grand Total | AT9: 91 | AU9: 91
A10: naveen.lagishetty | B10: 45209 | C10: Meeting | D10: 0.5 | E10: 1 | AL10: Grand Total | AM10: 91 | AO10: Grand Total | AP10: 92
A11: naveen.lagishetty | B11: 45209 | C11: Testing | D11: 4 | E11: 6
A12: naveen.lagishetty | B12: 45210 | C12: Meeting | D12: 0.5 | E12: 1
A13: naveen.lagishetty | B13: 45210 | C13: Report | D13: 2 | E13: 4 | AM13: Issue Complexity
A14: harshada.morje | B14: 45210 | C14: Meeting | D14: 0.5 | E14: 0 | AM14: #N/A | AN14: (blank) | AO14: Grand Total
A15: naveen.lagishetty | B15: 45211 | C15: Report | D15: 3 | E15: 5 | AL15: Count of Issue Name | AM15: 91 | AO15: 91
A16: kumar.reddy | B16: 45211 | C16: Report | D16: 2 | E16: 6 | G16: Units | H16: Column Labels
A17: prerna.rane | B17: 45212 | C17: Testing | D17: 2 | E17: 2 | G17: Row Labels | H17: 45208 | I17: 45209 | J17: 45210 | K17: 45211 | L17: 45212 | M17: 45215 | N17: 45216 | O17: 45218 | P17: Grand Total
A18: prerna.rane | B18: 45212 | C18: Testing | D18: 1 | E18: 0 | G18: Testing | H18: 10 | I18: 11 | J18: 5 | K18: 3 | L18: 2 | M18: 5 | N18: 2 | O18: 4 | P18: 42
A19: manasi.varma | B19: 45212 | C19: Testing | D19: 0.5 | E19: 0 | G19: kumar.reddy | H19: 3 | I19: 5 | J19: 3 | M19: 1 | P19: 12
A20: harshada.morje | B20: 45211 | C20: Testing | D20: 3 | E20: 3 | G20: naveen.lagishetty | H20: 7 | I20: 6 | P20: 13
A21: kumar.reddy | B21: 45215 | C21: Testing | D21: 1 | E21: 1 | G21: harshada.morje | K21: 3 | M21: 4 | P21: 7
A22: kumar.reddy | B22: 45215 | C22: Report | D22: 2.5 | E22: 8 | G22: irfan.shaikh | J22: 2 | P22: 2
A23: manasi.varma | B23: 45215 | C23: Support | D23: 0.5 | E23: 2 | G23: prerna.rane | L23: 2 | P23: 2
A24: manasi.varma | B24: 45215 | C24: Testing | D24: 2 | E24: 0 | G24: manasi.varma | L24: 0 | M24: 0 | O24: 0 | P24: 0
A25: harshada.morje | B25: 45215 | C25: Testing | D25: 4 | E25: 4 | G25: dilip.dharia | N25: 2 | O25: 4 | P25: 6
A26: manasi.varma | B26: 45216 | C26: QA | D26: 1 | E26: 3 | G26: Meeting | H26: 0 | I26: 1 | J26: 1 | O26: 0 | P26: 2
A27: dilip.dharia | B27: 45216 | C27: Testing | D27: 2 | E27: 2 | G27: naveen.lagishetty | I27: 1 | J27: 1 | P27: 2
A28: dilip.dharia | B28: 45216 | C28: Testing | D28: 1 | E28: 0 | G28: harshada.morje | H28: 0 | J28: 0 | P28: 0
A29: kumar.reddy | B29: 45218 | C29: Support | D29: 0.5 | G29: manisha.prakash | O29: 0 | P29: 0
A30: dilip.dharia | B30: 45218 | C30: Support | D30: 3 | E30: 35 | G30: Support | H30: 10 | M30: 2 | O30: 37 | P30: 49
A31: dilip.dharia | B31: 45218 | C31: Testing | D31: 4.75 | E31: 4 | G31: kumar.reddy
A32: manasi.varma | B32: 45218 | C32: Testing | D32: 3.5 | E32: 0 | G32: harshada.morje | H32: 10 | P32: 10
A33: manasi.varma | B33: 45218 | C33: Support | D33: 0.75 | E33: 2 | G33: manasi.varma | M33: 2 | O33: 2 | P33: 4
A34: manisha.prakash | B34: 45218 | C34: QA | D34: 2.75 | E34: 10 | G34: dilip.dharia | O34: 35 | P34: 35
A35: manisha.prakash | B35: 45218 | C35: Meeting | D35: 0.5 | E35: 0 | G35: Report | J35: 4 | K35: 11 | M35: 8 | P35: 23
G36: kumar.reddy | K36: 6 | M36: 8 | P36: 14
G37: naveen.lagishetty | J37: 4 | K37: 5 | P37: 9
G38: QA | N38: 3 | O38: 10 | P38: 13
G39: manasi.varma | N39: 3 | P39: 3
G40: manisha.prakash | O40: 10 | P40: 10
G41: Grand Total | H41: 20 | I41: 12 | J41: 10 | K41: 14 | L41: 2 | M41: 15 | N41: 5 | O41: 51 | P41: 129
G76: Hours | H76: Column Labels
G77: Row Labels | H77: 45208 | I77: 45209 | J77: 45210 | K77: 45211 | L77: 45212 | M77: 45215 | N77: 45216 | O77: 45218 | P77: Grand Total
G78: Testing | H78: 10 | I78: 9 | J78: 6 | K78: 3 | L78: 3.5 | M78: 7 | N78: 3 | O78: 8.25 | P78: 49.75
G79: kumar.reddy | H79: 3 | I79: 5 | J79: 3 | M79: 1 | P79: 12
G80: naveen.lagishetty | H80: 7 | I80: 4 | P80: 11
G81: harshada.morje | K81: 3 | M81: 4 | P81: 7
G82: irfan.shaikh | J82: 3 | P82: 3
G83: prerna.rane | L83: 3 | P83: 3
G84: manasi.varma | L84: 0.5 | M84: 2 | O84: 3.5 | P84: 6
G85: dilip.dharia | N85: 3 | O85: 4.75 | P85: 7.75
G86: Meeting | H86: 0.5 | I86: 0.5 | J86: 1 | O86: 0.5 | P86: 2.5
G87: naveen.lagishetty | I87: 0.5 | J87: 0.5 | P87: 1
G88: harshada.morje | H88: 0.5 | J88: 0.5 | P88: 1
G89: manisha.prakash | O89: 0.5 | P89: 0.5
G90: Support | H90: 0.5 | M90: 0.5 | O90: 4.25 | P90: 5.25
G91: kumar.reddy | O91: 0.5 | P91: 0.5
G92: harshada.morje | H92: 0.5 | P92: 0.5
G93: manasi.varma | M93: 0.5 | O93: 0.75 | P93: 1.25
G94: dilip.dharia | O94: 3 | P94: 3
G95: Report | J95: 2 | K95: 5 | M95: 2.5 | P95: 9.5
G96: kumar.reddy | K96: 2 | M96: 2.5 | P96: 4.5
G97: naveen.lagishetty | J97: 2 | K97: 3 | P97: 5
G98: QA | N98: 1 | O98: 2.75 | P98: 3.75
G99: manasi.varma | N99: 1 | P99: 1
G100: manisha.prakash | O100: 2.75 | P100: 2.75
G101: Grand Total | H101: 11 | I101: 9.5 | J101: 9 | K101: 8 | L101: 3.5 | M101: 10 | N101: 4 | O101: 15.75 | P101: 70.75

Sheet URL
A1: Sr. No. | B1: Page Name | C1: URL | D1: Type | E1: Notes | F1: Browser | G1: Screen Reader | H1: Magnification | I1: Speech Recognition | J1: Accessibility Settings | K1: Mobile Tablet | L1: FT Tester | M1: AT Tester | N1: FT QA | O1: AT QA | P1: QA | Q1: QA2
A2: P1 | B2: Left Navigation | D2: Component | E2: Instructor account with Student View | F2: Chrome | G2: JAWS 2022 | K2: Android Tablet (Nachiket) | L2: Naveen | P2: Manasi
A3: P2 | B3: Course Home - Calendar | D3: Page | E3: Instructor account with Student View | F3: Chrome | G3: JAWS 2022 | H3: Yes | K3: Android Tablet (Nachiket) | L3: Naveen | P3: Manasi
A4: P3 | B4: Student Success Hub | D4: Component | E4: Instructor account with Student View | F4: Chrome | G4: JAWS 2022 | K4: Android Tablet (Nachiket) | L4: Naveen | P4: Manasi
A5: P4 | B5: MyLab Tour for students | D5: Page | E5: Instructor account with Student View | F5: Chrome | G5: JAWS 2022 | H5: Yes | K5: Android Tablet (Nachiket) | L5: Naveen | P5: Manasi
A6: P5 | B6: Dynamic Study Modules | D6: Component | E6: Instructor account with Student View | F6: Chrome | G6: JAWS 2022 | K6: Android Tablet (Nachiket) | L6: Naveen | P6: Manasi
A7: P6 | B7: Multimedia Library Mainpage | D7: Page | E7: Instructor account with Student View | F7: Chrome | G7: JAWS 2022 | K7: Android Tablet (Nachiket) | L7: Naveen | P7: Manasi
A8: P7 | B8: Print Offers | D8: Component | E8: Instructor account with Student View | F8: Chrome | G8: JAWS 2022 | K8: Android Tablet (Nachiket) | L8: Naveen | P8: Manasi
A9: P8 | B9: eTextbook | D9: Page | E9: Instructor account with Student View | F9: Chrome | G9: JAWS 2022 | K9: Android Tablet (Nachiket) | L9: Naveen | P9: Manasi
A10: P9 | B10: Course Home - Document Sharing | C10: https://mylabmastering.pearson.com/?courseId=12530108&key=1540223697657138739132023#/DocSharing/813763a3-21c6-41d5-8e84-98acc6a32e05 | D10: Component | E10: Instructor account with Student View | F10: Chrome | G10: JAWS 2022 | K10: Android Tablet (Nachiket) | L10: Irfan | M10: Dilip | P10: Manasi
A11: P10 | B11: Accessibility Information | C11: https://mylabmastering.pearson.com/?courseId=12530108&key=1540223697657138739132023#/ | D11: Page | E11: Instructor account with Student View | F11: Chrome | G11: JAWS 2022 | K11: Android Tablet (Nachiket) | L11: Irfan | M11: Dilip | P11: Manasi
A12: P11 | B12: Student To-do list | C12: https://mylabmastering.pearson.com/?courseId=12530108&key=620406497315419132023#/ | D12: Page | E12: Student Account | F12: Chrome | G12: JAWS 2022 | K12: Android Tablet (Nachiket) | L12: Irfan | M12: Dilip | P12: Manasi
A13: P12 | B13: Chapter 9 Homework: Question 1 | D13: Component | E13: Student Account | F13: Chrome | G13: JAWS 2022 | K13: Android Tablet (Nachiket) | L13: Irfan | M13: Dilip | P13: Manasi
A14: P13 | B14: Chapter 9 Homework: Question 5 | D14: Component | E14: Student Account | F14: FF | G14: NVDA | K14: Android Tablet (Nachiket) | L14: Naveen | P14: Manasi
A15: P14 | B15: Video Assignment Page | D15: Page | E15: Student Account | F15: FF | G15: NVDA | K15: Android Tablet (Nachiket) | L15: Kumar | P15: Manasi
A16: P15 | B16: Video: Question 1 | D16: Component | E16: Student Account | F16: FF | G16: NVDA | K16: Android Tablet (Nachiket) | L16: Kumar | P16: Manasi
A17: P16 | B17: Video Quiz Summary | D17: Component | F17: FF | G17: NVDA | K17: iPad (Harshada) | L17: Kumar | P17: Manasi
A18: P17 | B18: Question 1 | D18: Page | F18: FF | G18: NVDA | K18: Android Tablet (Nachiket) | L18: Kumar | P18: Manasi
A19: P18 | B19: Question 1 | D19: Component | F19: FF | G19: NVDA | L19: Kumar | P19: Manasi
A20: P19 | B20: Case Study Library Mainpage | D20: Page | F20: FF | G20: NVDA | K20: Android Tablet (Nachiket) | L20: Kumar | P20: Manasi
A21: P20 | B21: Case Study - Brief | D21: Page | F21: FF | G21: NVDA | K21: iPad (Harshada) | L21: Kumar | P21: Manasi
A22: P21 | B22: Case Study - Questions | D22: Page | F22: FF | G22: NVDA | K22: iPad (Harshada) | L22: Kumar | P22: Manasi
A23: P22 | B23: Podcast Assignment Mainpage | D23: Page | F23: FF | G23: NVDA | K23: iPad (Harshada) | L23: Kumar | P23: Manasi
A24: P23 | B24: Question 1 | D24: Component | F24: FF | G24: NVDA | K24: iPad (Harshada) | L24: Kumar | P24: Manasi
A25: P24 | B25: Podcast Quiz Summary | D25: Component | F25: FF | G25: NVDA | K25: iPad (Harshada) | L25: Kumar | P25: Manasi
A26: P25 | B26: Take a Quiz test | D26: Page | F26: Mac | G26: VoiceOver | K26: iPad (Harshada) | L26: Harshada | P26: Manasi
A27: P26 | B27: Start Quiz Page | D27: Component | F27: Mac | G27: VoiceOver | K27: iPad (Harshada) | L27: Harshada | P27: Manasi
A28: P27 | B28: Question 1 | D28: Component | F28: Mac | G28: VoiceOver | K28: iPad (Harshada) | L28: Harshada | P28: Manasi
A29: P28 | B29: Quiz Summary | D29: Page | F29: Mac | G29: VoiceOver | K29: iPad (Harshada) | L29: Harshada | P29: Manasi
A30: P29 | B30: Study Plan Recommendations | D30: Page | F30: Mac | G30: VoiceOver | K30: iPad (Harshada) | L30: Harshada | P30: Manasi
A31: P30 | B31: Practice Define marketing and outline the steps in the marketing process: Question 1 | D31: Component | F31: Mac | G31: VoiceOver | K31: iPad (Harshada) | L31: Harshada | P31: Manasi
... A35: P34 | B35: Study Plan All Chapters | D35: Page | F35: Mac | G35: VoiceOver | K35: iPad (Harshada) | L35: Harshada | P35: Manasi
A36: P35 | B36: Student Gradebook Results Page | D36: Page | E36: Student Account | F36: Mac | G36: VoiceOver | K36: iPad (Harshada) | L36: Harshada | P36: Manasi
B37: Column Labels
B38: (blank) | C38: No QA Needed | D38: Delete | E38: approved | F38: Grand Total
A39: Sum of Issue Name | C39: 0 | D39: 0 | E39: 0 | F39: 0

Sheet Final Report
A1: Page | B1: Page Name | C1: URL Link | D1: Type of Issue | E1: Issue Name | F1: Comments | G1: Chrome/JAWS | H1: FF/NVDA | I1: Chrome/NVDA | J1: Mac/Safari/VO | K1: Mac/Chrome/VO | L1: iOS/VO | M1: Android/Talkback | N1: ZoomText | O1: Dragon | P1: Issue Tested By | Q1: Status | R1: Testing - Reviewed By | S1: Move to Report | T1: Summary | U1: Issue Description | V1: FinaIized - Issue Description | W1: Code Snippet | X1: FinaIized - Code Snippet | Y1: Expected Result | Z1: FinaIized - Expected Result | AA1: Rationale | AB1: Recommendation | AC1: FinaIized - Recommendation | AD1: Steps to Reproduce Start | AE1: Steps to Reproduce | AF1: FinaIized - Steps to Reproduce | AG1: WCAG 2.1 Conformance Level | AH1: WCAG 2.1 Success Criteria | AI1: ScreenShot Name | AJ1: Priority | AK1: Tested On | AL1: Components | AM1: Labels | AN1: Severity | AO1: Issue Written By | AP1: Self QC | AQ1: Writing Score | AR1: Tester's Comment | AS1: BB Self QC | AT1: Reporting - Reviewed By | AU1: Reviewers comment | AV1: Issue Level | AW1: Self QC QA | AX1: Finalized | AY1: BB Self QC QA | AZ1: Regression Status | BA1: Uploading Status | BB1: Uploading comment | BC1: Issue Complexity | BD1: Client Feedback | BE1: Client Feedback Level
A2: P1 | B2: =VLOOKUP(A2,URL[],2,0) -> Left Navigation | C2: =VLOOKUP(A2,URL[],3,0) -> 0 | D2: ARIA | E2: ARIA attribute defined inappropriately | F2: Left navigation buttons aria-expand/collapse functionality is unclear - Known issue - ACDS-265656, ACDS-262925 known check done valid- dilip | G2: Applicable | H2: Applicable | I2: Applicable | P2: naveen.lagishetty | Q2: No QA Needed | R2: 0 | S2: No | T2: =IF(Final_Report[[#This Row],[Move to Report]]="Yes",VLOOKUP(E2,IssueVariable[],3,0),"N/A") -> N/A | U2: =IF(Final_Report[[#This Row],[Move to Report]]="Yes",VLOOKUP(E2,IssueVariable[],4,0),"N/A") -> N/A | V2: =Final_Report[[#This Row],[Issue Description]] -> N/A | X2: =Final_Report[[#This Row],[Code Snippet]] -> 0 | Y2: =IF(Final_Report[[#This Row],[Move to Report]]="Yes",VLOOKUP(E2,IssueVariable[],5,0),"N/A") -> N/A | Z2: =Final_Report[[#This Row],[Expected Result]] -> N/A | AA2: =IF(Final_Report[[#This Row],[Move to Report]]="Yes",VLOOKUP(E2,IssueVariable[],6,0),"N/A") -> N/A | AB2: =IF(Final_Report[[#This Row],[Move to Report]]="Yes",VLOOKUP(E2,IssueVariable[],7,0),"N/A") -> N/A | AC2: =Final_Report[[#This Row],[Recommendation]] -> N/A | AE2: =IF(Final_Report[[#This Row],[Move to Report]]="Yes",VLOOKUP(E2,IssueVariable[],8,0),"N/A") -> N/A | AF2: =Final_Report[[#This Row],[Steps to Reproduce]] -> N/A | AG2: =IF(Final_Report[[#This Row],[Move to Report]]="Yes",VLOOKUP(E2,IssueVariable[],9,0),"N/A") -> N/A | AH2: =IF(Final_Report[[#This Row],[Move to Report]]="Yes",VLOOKUP(E2,IssueVariable[],10,0),"N/A") -> N/A | AK2: {=Table95[Tested on]} -> Windows: 11 MAC OS: 12 iOS: 15 Android OS: 10 | AL2: {=_xlfn.TEXTJOIN(", ",TRUE,_xlfn.UNIQUE(TRIM(MID(SUBSTITUTE((Final_Report[[#This Row],[WCAG 2.1 Success Criteria]] &_xlfn.CONCAT(" (Level ") &Final_Report[[#This Row],[WCAG 2.1 Conformance Level]] &_xlfn.CONCAT("), ") &IF(Final_Report[[#This Row],[Chrome/JAWS]]="Applicable","Windows_11, Chrome, JAWS, ", " ") &IF(Final_Report[[#This Row],[FF/NVDA]]="Applicable", "Windows_11, Firefox, NVDA, ", " ") &IF(Final_Report[[#This Row],[Chrome/NVDA]]="Applicable", "Windows_11, Chrome, NVDA, ", " ") &IF(Final_Report[[#This Row],[iOS/VO]]="Applicable", "iOS Tablet, VoiceOver, ", " ") &IF(Final_Report[[#This Row],[Mac/Safari/VO]]="Applicable", "macOS_12, Safari, VoiceOver, ", " ") &IF(Final_Report[[#This Row],[Mac/Chrome/VO]]="Applicable", "macOS_12, Chrome, VoiceOver, ", " ") &IF(Final_Report[[#This Row],[Android/Talkback]]="Applicable", "TalkBack, Android Tablet", " ") ) &", " &IF(ISERROR(FIND("iOS 13",INDEX(Keyword[Component Keyword],MATCH(TRUE,INDEX((Keyword[Component Keyword]<>0),0),0)))=FALSE),INDEX(Keyword[Component Keyword],MATCH(TRUE,INDEX((Keyword[Component Keyword]<>0),0),0)),SUBSTITUTE(INDEX(Keyword[Component Keyword],MATCH(TRUE,INDEX((Keyword[Component Keyword]<>0),0),0)),"iOS 13","iOS")),",",REPT(" ",999)),(ROW($AAN$1:INDEX($AAX:$AAX,LEN((Final_Report[[#This Row],[WCAG 2.1 Success Criteria]] &_xlfn.CONCAT(" (Level ") &Final_Report[[#This Row],[WCAG 2.1 Conformance Level]] &_xlfn.CONCAT("), ") &IF(Final_Report[[#This Row],[Chrome/JAWS]]="Applicable","Windows_11, Chrome, JAWS, ", " ") &IF(Final_Report[[#This Row],[FF/NVDA]]="Applicable", "Windows_11, Firefox, NVDA, ", " ") &IF(Final_Report[[#This Row],[Chrome/NVDA]]="Applicable", "Windows_11, Chrome, NVDA, ", " ") &IF(Final_Report[[#This Row],[iOS/VO]]="Applicable", "iOS Tablet, VoiceOver, ", " ") &IF(Final_Report[[#This Row],[Mac/Safari/VO]]="Applicable", "macOS_12, Safari, VoiceOver, ", " ") &IF(Final_Report[[#This Row],[Mac/Chrome/VO]]="Applicable", "macOS_12, Chrome, VoiceOver, ", " ") &IF(Final_Report[[#This Row],[Android/Talkback]]="Applicable", "TalkBack, Android Tablet", " ") ) &", " &IF(ISERROR(FIND("iOS 13",INDEX(Keyword[Component Keyword],MATCH(TRUE,INDEX((Keyword[Component Keyword]<>0),0),0)))=FALSE),INDEX(Keyword[Component Keyword],MATCH(TRUE,INDEX((Keyword[Component Keyword]<>0),0),0)),SUBSTITUTE(INDEX(Keyword[Component Keyword],MATCH(TRUE,INDEX((Keyword[Component Keyword]<>0),0),0)),"iOS 13","iOS")))-LEN(SUBSTITUTE((Final_Report[[#This Row],[WCAG 2.1 Success Criteria]] &_xlfn.CONCAT(" (Level ") &Final_Report[[#This Row],[WCAG 2.1 Conformance Level]] &_xlfn.CONCAT("), ") &IF(Final_Report[[#This Row],[Chrome/JAWS]]="Applicable","Windows_11, Chrome, JAWS, ", " ") &IF(Final_Report[[#This Row],[FF/NVDA]]="Applicable", "Windows_11, Firefox, NVDA, ", " ") &IF(Final_Report[[#This Row],[Chrome/NVDA]]="Applicable", "Windows_11, Chrome, NVDA, ", " ") &IF(Final_Report[[#This Row],[iOS/VO]]="Applicable", "iOS Tablet, VoiceOver, ", " ") &IF(Final_Report[[#This Row],[Mac/Safari/VO]]="Applicable", "macOS_12, Safari, VoiceOver, ", " ") &IF(Final_Report[[#This Row],[Mac/Chrome/VO]]="Applicable", "macOS_12, Chrome, VoiceOver, ", " ") &IF(Final_Report[[#This Row],[Android/Talkback]]="Applicable", "TalkBack, Android Tablet", " ") ) &", " &IF(ISERROR(FIND("iOS 13",INDEX(Keyword[Component Keyword],MATCH(TRUE,INDEX((Keyword[Component Keyword]<>0),0),0)))=FALSE),INDEX(Keyword[Component Keyword],MATCH(TRUE,INDEX((Keyword[Component Keyword]<>0),0),0)),SUBSTITUTE(INDEX(Keyword[Component Keyword],MATCH(TRUE,INDEX((Keyword[Component Keyword]<>0),0),0)),"iOS 13","iOS")),",",""))+1))-1)*999+1,999))))} -> N/A (Level N/A), Windows_11, Chrome, JAWS, Firefox, NVDA, Accessibility, Audit, Marketing, MLM-XL, MLVISION, MyLab, US, VPAT | AM2: {=CONCATENATE(LEFT(AH2, SEARCH(" ", AH2) -1),", ",Labels[Labels])} -> #VALUE! | AN2: =IF(AJ2="Blocker","1 - Critical - showstopper",IF(AJ2="Critical","1 - Critical - showstopper",IF(AJ2="Major","1 - Critical - showstopper",IF(AJ2="Minor","3 - Medium - minor functionality broken",IF(AJ2="Trivial","4 - Low - cosmetic or usability"))))) -> FALSE | BC2: =VLOOKUP('Final Report'!D2,'Issue Variable'!A:N,11,FALSE) -> #N/A
A3: P1 | B3: =VLOOKUP(A3,URL[],2,0) -> Left Navigation | C3: =VLOOKUP(A3,URL[],3,0) -> 0 | D3: Images | E3: No text equivalent for SVG image | F3: Left navigation "Educator Hub->Instructor Resources" when user acitvate it opens a page in new tab - Known issue - ACDS-251421 known check done valid- dilip | G3: Applicable | H3: Applicable | I3: Applicable | P3: naveen.lagishetty | Q3: No QA Needed | S3: No | T3: =IF(Final_Report[[#This Row],[Move to Report]]="Yes",VLOOKUP(E3,IssueVariable[],3,0),"N/A") -> N/A | U3: =IF(Final_Report[[#This Row],[Move to Report]]="Yes",VLOOKUP(E3,IssueVariable[],4,0),"N/A") -> N/A | V3: =Final_Report[[#This Row],[Issue Description]] -> N/A | X3: =Final_Report[[#This Row],[Code Snippet]] -> 0 | Y3: =IF(Final_Report[[#This Row],[Move to Report]]="Yes",VLOOKUP(E3,IssueVariable[],5,0),"N/A") -> N/A | Z3: =Final_Report[[#This Row],[Expected Result]] -> N/A | AA3: =IF(Final_Report[[#This Row],[Move to Report]]="Yes",VLOOKUP(E3,IssueVariable[],6,0),"N/A") -> N/A | AB3: =IF(Final_Report[[#This Row],[Move to Report]]="Yes",VLOOKUP(E3,IssueVariable[],7,0),"N/A") -> N/A | AC3: =Final_Report[[#This Row],[Recommendation]] -> N/A | AE3: =IF(Final_Report[[#This Row],[Move to Report]]="Yes",VLOOKUP(E3,IssueVariable[],8,0),"N/A") -> N/A | AF3: =Final_Report[[#This Row],[Steps to Reproduce]] -> N/A | AG3: =IF(Final_Report[[#This Row],[Move to Report]]="Yes",VLOOKUP(E3,IssueVariable[],9,0),"N/A") -> N/A | AH3: =IF(Final_Report[[#This Row],[Move to Report]]="Yes",VLOOKUP(E3,IssueVariable[],10,0),"N/A") -> N/A | AK3: {=Table95[Tested on]} -> Windows: 11 MAC OS: 12 iOS: 15 Android OS: 10 | AL3: {=_xlfn.TEXTJOIN(", ",TRUE,_xlfn.UNIQUE(TRIM(MID(SUBSTITUTE((Final_Report[[#This Row],[WCAG 2.1 Success Criteria]] &_xlfn.CONCAT(" (Level ") &Final_Report[[#This Row],[WCAG 2.1 Conformance Level]] &_xlfn.CONCAT("), ") &IF(Final_Report[[#This Row],[Chrome/JAWS]]="Applicable","Windows_11, Chrome, JAWS, ", " ") &IF(Final_Report[[#This Row],[FF/NVDA]]="Applicable", "Windows_11, Firefox, NVDA, ", " ") &IF(Final_Report[[#This Row],[Chrome/NVDA]]="Applicable", "Windows_11, Chrome, NVDA, ", " ") &IF(Final_Report[[#This Row],[iOS/VO]]="Applicable", "iOS Tablet, VoiceOver, ", " ") &IF(Final_Report[[#This Row],[Mac/Safari/VO]]="Applicable", "macOS_12, Safari, VoiceOver, ", " ") &IF(Final_Report[[#This Row],[Mac/Chrome/VO]]="Applicable", "macOS_12, Chrome, VoiceOver, ", " ") &IF(Final_Report[[#This Row],[Android/Talkback]]="Applicable", "TalkBack, Android Tablet", " ") ) &", " &IF(ISERROR(FIND("iOS 13",INDEX(Keyword[Component Keyword],MATCH(TRUE,INDEX((Keyword[Component Keyword]<>0),0),0)))=FALSE),INDEX(Keyword[Component Keyword],MATCH(TRUE,INDEX((Keyword[Component Keyword]<>0),0),0)),SUBSTITUTE(INDEX(Keyword[Component Keyword],MATCH(TRUE,INDEX((Keyword[Component Keyword]<>0),0),0)),"iOS 13","iOS")),",",REPT(" ",999)),(ROW($AAN$1:INDEX($AAX:$AAX,LEN((Final_Report[[#This Row],[WCAG 2.1 Success Criteria]] &_xlfn.CONCAT(" (Level ") &Final_Report[[#This Row],[WCAG 2.1 Conformance Level]] &_xlfn.CONCAT("), ") &IF(Final_Report[[#This Row],[Chrome/JAWS]]="Applicable","Windows_11, Chrome, JAWS, ", " ") &IF(Final_Report[[#This Row],[FF/NVDA]]="Applicable", "Windows_11, Firefox, NVDA, ", " ") &IF(Final_Report[[#This Row],[Chrome/NVDA]]="Applicable", "Windows_11, Chrome, NVDA, ", " ") &IF(Final_Report[[#This Row],[iOS/VO]]="Applicable", "iOS Tablet, VoiceOver, ", " ") &IF(Final_Report[[#This Row],[Mac/Safari/VO]]="Applicable", "macOS_12, Safari, VoiceOver, ", " ") &IF(Final_Report[[#This Row],[Mac/Chrome/VO]]="Applicable", "macOS_12, Chrome, VoiceOver, ", " ") &IF(Final_Report[[#This Row],[Android/Talkback]]="Applicable", "TalkBack, Android Tablet", " ") ) &", " &IF(ISERROR(FIND("iOS 13",INDEX(Keyword[Component Keyword],MATCH(TRUE,INDEX((Keyword[Component Keyword]<>0),0),0)))=FALSE),INDEX(Keyword[Component Keyword],MATCH(TRUE,INDEX((Keyword[Component Keyword]<>0),0),0)),SUBSTITUTE(INDEX(Keyword[Component Keyword],MATCH(TRUE,INDEX((Keyword[Component Keyword]<>0),0),0)),"iOS 13","iOS")))-LEN(SUBSTITUTE((Final_Report[[#This Row],[WCAG 2.1 Success Criteria]] &_xlfn.CONCAT(" (Level ") &Final_Report[[#This Row],[WCAG 2.1 Conformance Level]] &_xlfn.CONCAT("), ") &IF(Final_Report[[#This Row],[Chrome/JAWS]]="Applicable","Windows_11, Chrome, JAWS, ", " ") &IF(Final_Report[[#This Row],[FF/NVDA]]="Applicable", "Windows_11, Firefox, NVDA, ", " ") &IF(Final_Report[[#This Row],[Chrome/NVDA]]="Applicable", "Windows_11, Chrome, NVDA, ", " ") &IF(Final_Report[[#This Row],[iOS/VO]]="Applicable", "iOS Tablet, VoiceOver, ", " ") &IF(Final_Report[[#This Row],[Mac/Safari/VO]]="Applicable", "macOS_12, Safari, VoiceOver, ", " ") &IF(Final_Report[[#This Row],[Mac/Chrome/VO]]="Applicable", "macOS_12, Chrome, VoiceOver, ", " ") &IF(Final_Report[[#This Row],[Android/Talkback]]="Applicable", "TalkBack, Android Tablet", " ") ) &", " &IF(ISERROR(FIND("iOS 13",INDEX(Keyword[Component Keyword],MATCH(TRUE,INDEX((Keyword[Component Keyword]<>0),0),0)))=FALSE),INDEX(Keyword[Component Keyword],MATCH(TRUE,INDEX((Keyword[Component Keyword]<>0),0),0)),SUBSTITUTE(INDEX(Keyword[Component Keyword],MATCH(TRUE,INDEX((Keyword[Component Keyword]<>0),0),0)),"iOS 13","iOS")),",",""))+1))-1)*999+1,999))))} -> N/A (Level N/A), Windows_11, Chrome, JAWS, Firefox, NVDA, Accessibility, Audit, Marketing, MLM-XL, MLVISION, MyLab, US, VPAT | AM3: {=CONCATENATE(LEFT(AH3, SEARCH(" ", AH3) -1),", ",Labels[Labels])} -> #VALUE! | AN3: =IF(AJ3="Blocker","1 - Critical - showstopper",IF(AJ3="Critical","1 - Critical - showstopper",IF(AJ3="Major","1 - Critical - showstopper",IF(AJ3="Minor","3 - Medium - minor functionality broken",IF(AJ3="Trivial","4 - Low - cosmetic or usability"))))) -> FALSE | BC3: =VLOOKUP('Final Report'!D3,'Issue Variable'!A:N,11,FALSE) -> #N/A
A4: P1 | B4: =VLOOKUP(A4,URL[],2,0) -> Left Navigation | C4: =VLOOKUP(A4,URL[],3,0) -> 0 | D4: Keyboard | E4: Missing Keyboard Support for Button | F4: Left navigation elements has role="button" so it should work with space and enter key but it works with only enter key. | G4: Applicable | I4: Applicable | P4: naveen.lagishetty | Q4: No QA Needed | S4: No | T4: =IF(Final_Report[[#This Row],[Move to Report]]="Yes",VLOOKUP(E4,IssueVariable[],3,0),"N/A") -> N/A | U4: =IF(Final_Report[[#This Row],[Move to Report]]="Yes",VLOOKUP(E4,IssueVariable[],4,0),"N/A") -> N/A | V4: =Final_Report[[#This Row],[Issue Description]] -> N/A | X4: =Final_Report[[#This Row],[Code Snippet]] -> 0 | Y4: =IF(Final_Report[[#This Row],[Move to Report]]="Yes",VLOOKUP(E4,IssueVariable[],5,0),"N/A") -> N/A | Z4: =Final_Report[[#This Row],[Expected Result]] -> N/A | AA4: =IF(Final_Report[[#This Row],[Move to Report]]="Yes",VLOOKUP(E4,IssueVariable[],6,0),"N/A") -> N/A | AB4: =IF(Final_Report[[#This Row],[Move to Report]]="Yes",VLOOKUP(E4,IssueVariable[],7,0),"N/A") -> N/A | AC4: =Final_Report[[#This Row],[Recommendation]] -> N/A | AE4: =IF(Final_Report[[#This Row],[Move to Report]]="Yes",VLOOKUP(E4,IssueVariable[],8,0),"N/A") -> N/A | AF4: =Final_Report[[#This Row],[Steps to Reproduce]] -> N/A | AG4: =IF(Final_Report[[#This Row],[Move to Report]]="Yes",VLOOKUP(E4,IssueVariable[],9,0),"N/A") -> N/A | AH4: =IF(Final_Report[[#This Row],[Move to Report]]="Yes",VLOOKUP(E4,IssueVariable[],10,0),"N/A") -> N/A | AK4: {=Table95[Tested on]} -> Windows: 11 MAC OS: 12 iOS: 15 Android OS: 10 | AL4: {=_xlfn.TEXTJOIN(", ",TRUE,_xlfn.UNIQUE(TRIM(MID(SUBSTITUTE((Final_Report[[#This Row],[WCAG 2.1 Success Criteria]] &_xlfn.CONCAT(" (Level ") &Final_Report[[#This Row],[WCAG 2.1 Conformance Level]] &_xlfn.CONCAT("), ") &IF(Final_Report[[#This Row],[Chrome/JAWS]]="Applicable","Windows_11, Chrome, JAWS, ", " ") &IF(Final_Report[[#This Row],[FF/NVDA]]="Applicable", "Windows_11, Firefox, NVDA, ", " ") &IF(Final_Report[[#This Row],[Chrome/NVDA]]="Applicable", "Windows_11, Chrome, NVDA, ", " ") &IF(Final_Report[[#This Row],[iOS/VO]]="Applicable", "iOS Tablet, VoiceOver, ", " ") &IF(Final_Report[[#This Row],[Mac/Safari/VO]]="Applicable", "macOS_12, Safari, VoiceOver, ", " ") &IF(Final_Report[[#This Row],[Mac/Chrome/VO]]="Applicable", "macOS_12, Chrome, VoiceOver, ", " ") &IF(Final_Report[[#This Row],[Android/Talkback]]="Applicable", "TalkBack, Android Tablet", " ") ) &", " &IF(ISERROR(FIND("iOS 13",INDEX(Keyword[Component Keyword],MATCH(TRUE,INDEX((Keyword[Component Keyword]<>0),0),0)))=FALSE),INDEX(Keyword[Component Keyword],MATCH(TRUE,INDEX((Keyword[Component Keyword]<>0),0),0)),SUBSTITUTE(INDEX(Keyword[Component Keyword],MATCH(TRUE,INDEX((Keyword[Component Keyword]<>0),0),0)),"iOS 13","iOS")),",",REPT(" ",999)),(ROW($AAN$1:INDEX($AAX:$AAX,LEN((Final_Report[[#This Row],[WCAG 2.1 Success Criteria]] &_xlfn.CONCAT(" (Level ") &Final_Report[[#This Row],[WCAG 2.1 Conformance Level]] &_xlfn.CONCAT("), ") &IF(Final_Report[[#This Row],[Chrome/JAWS]]="Applicable","Windows_11, Chrome, JAWS, ", " ") &IF(Final_Report[[#This Row],[FF/NVDA]]="Applicable", "Windows_11, Firefox, NVDA, ", " ") &IF(Final_Report[[#This Row],[Chrome/NVDA]]="Applicable", "Windows_11, Chrome, NVDA, ", " ") &IF(Final_Report[[#This Row],[iOS/VO]]="Applicable", "iOS Tablet, VoiceOver, ", " ") &IF(Final_Report[[#This Row],[Mac/Safari/VO]]="Applicable", "macOS_12, Safari, VoiceOver, ", " ") &IF(Final_Report[[#This Row],[Mac/Chrome/VO]]="Applicable", "macOS_12, Chrome, VoiceOver, ", " ") &IF(Final_Report[[#This Row],[Android/Talkback]]="Applicable", "TalkBack, Android Tablet", " ") ) &", " &IF(ISERROR(FIND("iOS 13",INDEX(Keyword[Component Keyword],MATCH(TRUE,INDEX((Keyword[Component Keyword]<>0),0),0)))=FALSE),INDEX(Keyword[Component Keyword],MATCH(TRUE,INDEX((Keyword[Component Keyword]<>0),0),0)),SUBSTITUTE(INDEX(Keyword[Component Keyword],MATCH(TRUE,INDEX((Keyword[Component Keyword]<>0),0),0)),"iOS 13","iOS")))-LEN(SUBSTITUTE((Final_Report[[#This Row],[WCAG 2.1 Success Criteria]] &_xlfn.CONCAT(" (Level ") &Final_Report[[#This Row],[WCAG 2.1 Conformance Level]] &_xlfn.CONCAT("), ") &IF(Final_Report[[#This Row],[Chrome/JAWS]]="Applicable","Windows_11, Chrome, JAWS, ", " ") &IF(Final_Report[[#This Row],[FF/NVDA]]="Applicable", "Windows_11, Firefox, NVDA, ", " ") &IF(Final_Report[[#This Row],[Chrome/NVDA]]="Applicable", "Windows_11, Chrome, NVDA, ", " ") &IF(Final_Report[[#This Row],[iOS/VO]]="Applicable", "iOS Tablet, VoiceOver, ", " ") &IF(Final_Report[[#This Row],[Mac/Safari/VO]]="Applicable", "macOS_12, Safari, VoiceOver, ", " ") &IF(Final_Report[[#This Row],[Mac/Chrome/VO]]="Applicable", "macOS_12, Chrome, VoiceOver, ", " ") &IF(Final_Report[[#This Row],[Android/Talkback]]="Applicable", "TalkBack, Android Tablet", " ") ) &", " &IF(ISERROR(FIND("iOS 13",INDEX(Keyword[Component Keyword],MATCH(TRUE,INDEX((Keyword[Component Keyword]<>0),0),0)))=FALSE),INDEX(Keyword[Component Keyword],MATCH(TRUE,INDEX((Keyword[Component Keyword]<>0),0),0)),SUBSTITUTE(INDEX(Keyword[Component Keyword],MATCH(TRUE,INDEX((Keyword[Component Keyword]<>0),0),0)),"iOS 13","iOS")),",",""))+1))-1)*999+1,999))))} -> N/A (Level N/A), Windows_11, Chrome, JAWS, NVDA, Accessibility, Audit, Marketing, MLM-XL, MLVISION, MyLab, US, VPAT | AM4: {=CONCATENATE(LEFT(AH4, SEARCH(" ", AH4) -1),", ",Labels[Labels])} -> #VALUE! | AN4: =IF(AJ4="Blocker","1 - Critical - showstopper",IF(AJ4="Critical","1 - Critical - showstopper",IF(AJ4="Major","1 - Critical - showstopper",IF(AJ4="Minor","3 - Medium - minor functionality broken",IF(AJ4="Trivial","4 - Low - cosmetic or usability"))))) -> FALSE | BC4: =VLOOKUP('Final Report'!D4,'Issue Variable'!A:N,11,FALSE) -> #N/A
A5: P2 | B5: =VLOOKUP(A5,URL[],2,0) -> Course Home - Calendar | C5: =VLOOKUP(A5,URL[],3,0) -> 0 | D5: Colour | E5: Color alone used to convey information | F5: Colour (#C0C0C0) alone is used to indicate the "Gray text" information on the table - Known issue - ACDS-248696 known check done valid- dilip | G5: Applicable | I5: Applicable | P5: naveen.lagishetty | Q5: No QA Needed | S5: No | T5: =IF(Final_Report[[#This Row],[Move to Report]]="Yes",VLOOKUP(E5,IssueVariable[],3,0),"N/A") -> N/A | U5: =IF(Final_Report[[#This Row],[Move to Report]]="Yes",VLOOKUP(E5,IssueVariable[],4,0),"N/A") -> N/A | V5: =Final_Report[[#This Row],[Issue Description]] -> N/A | X5: =Final_Report[[#This Row],[Code Snippet]] -> 0 | Y5: =IF(Final_Report[[#This Row],[Move to Report]]="Yes",VLOOKUP(E5,IssueVariable[],5,0),"N/A") -> N/A | Z5: =Final_Report[[#This Row],[Expected Result]] -> N/A | AA5: =IF(Final_Report[[#This Row],[Move to Report]]="Yes",VLOOKUP(E5,IssueVariable[],6,0),"N/A") -> N/A | AB5: =IF(Final_Report[[#This Row],[Move to Report]]="Yes",VLOOKUP(E5,IssueVariable[],7,0),"N/A") -> N/A | AC5: =Final_Report[[#This Row],[Recommendation]] -> N/A | AE5: =IF(Final_Report[[#This Row],[Move to Report]]="Yes",VLOOKUP(E5,IssueVariable[],8,0),"N/A") -> N/A | AF5: =Final_Report[[#This Row],[Steps to Reproduce]] -> N/A | AG5: =IF(Final_Report[[#This Row],[Move to Report]]="Yes",VLOOKUP(E5,IssueVariable[],9,0),"N/A") -> N/A | AH5: =IF(Final_Report[[#This Row],[Move to Report]]="Yes",VLOOKUP(E5,IssueVariable[],10,0),"N/A") -> N/A | AK5: {=Table95[Tested on]} -> Windows: 11 MAC OS: 12 iOS: 15 Android OS: 10 | AL5: {=_xlfn.TEXTJOIN(", ",TRUE,_xlfn.UNIQUE(TRIM(MID(SUBSTITUTE((Final_Report[[#This Row],[WCAG 2.1 Success Criteria]] &_xlfn.CONCAT(" (Level ") &Final_Report[[#This Row],[WCAG 2.1 Conformance Level]] &_xlfn.CONCAT("), ") &IF(Final_Report[[#This Row],[Chrome/JAWS]]="Applicable","Windows_11, Chrome, JAWS, ", " ") &IF(Final_Report[[#This Row],[FF/NVDA]]="Applicable", "Windows_11, Firefox, NVDA, ", " ") &IF(Final_Report[[#This Row],[Chrome/NVDA]]="Applicable", "Windows_11, Chrome, NVDA, ", " ") &IF(Final_Report[[#This Row],[iOS/VO]]="Applicable", "iOS Tablet, VoiceOver, ", " ") &IF(Final_Report[[#This Row],[Mac/Safari/VO]]="Applicable", "macOS_12, Safari, VoiceOver, ", " ") &IF(Final_Report[[#This Row],[Mac/Chrome/VO]]="Applicable", "macOS_12, Chrome, VoiceOver, ", " ") &IF(Final_Report[[#This Row],[Android/Talkback]]="Applicable", "TalkBack, Android Tablet", " ") ) &", " &IF(ISERROR(FIND("iOS 13",INDEX(Keyword[Component Keyword],MATCH(TRUE,INDEX((Keyword[Component Keyword]<>0),0),0)))=FALSE),INDEX(Keyword[Component Keyword],MATCH(TRUE,INDEX((Keyword[Component Keyword]<>0),0),0)),SUBSTITUTE(INDEX(Keyword[Component Keyword],MATCH(TRUE,INDEX((Keyword[Component Keyword]<>0),0),0)),"iOS 13","iOS")),",",REPT(" ",999)),(ROW($AAN$1:INDEX($AAX:$AAX,LEN((Final_Report[[#This Row],[WCAG 2.1 Success Criteria]] &_xlfn.CONCAT(" (Level ") &Final_Report[[#This Row],[WCAG 2.1 Conformance Level]] &_xlfn.CONCAT("), ") &IF(Final_Report[[#This Row],[Chrome/JAWS]]="Applicable","Windows_11, Chrome, JAWS, ", " ") &IF(Final_Report[[#This Row],[FF/NVDA]]="Applicable", "Windows_11, Firefox, NVDA, ", " ") &IF(Final_Report[[#This Row],[Chrome/NVDA]]="Applicable", "Windows_11, Chrome, NVDA, ", " ") &IF(Final_Report[[#This Row],[iOS/VO]]="Applicable", "iOS Tablet, VoiceOver, ", " ") &IF(Final_Report[[#This Row],[Mac/Safari/VO]]="Applicable", "macOS_12, Safari, VoiceOver, ", " ") &IF(Final_Report[[#This Row],[Mac/Chrome/VO]]="Applicable", "macOS_12, Chrome, VoiceOver, ", " ") &IF(Final_Report[[#This Row],[Android/Talkback]]="Applicable", "TalkBack, Android Tablet", " ") ) &", " &IF(ISERROR(FIND("iOS 13",INDEX(Keyword[Component Keyword],MATCH(TRUE,INDEX((Keyword[Component Keyword]<>0),0),0)))=FALSE),INDEX(Keyword[Component Keyword],MATCH(TRUE,INDEX((Keyword[Component Keyword]<>0),0),0)),SUBSTITUTE(INDEX(Keyword[Component Keyword],MATCH(TRUE,INDEX((Keyword[Component Keyword]<>0),0),0)),"iOS 13","iOS")))-LEN(SUBSTITUTE((Final_Report[[#This Row],[WCAG 2.1 Success Criteria]] &_xlfn.CONCAT(" (Level ") &Final_Report[[#This Row],[WCAG 2.1 Conformance Level]] &_xlfn.CONCAT("), ") &IF(Final_Report[[#This Row],[Chrome/JAWS]]="Applicable","Windows_11, Chrome, JAWS, ", " ") &IF(Final_Report[[#This Row],[FF/NVDA]]="Applicable", "Windows_11, Firefox, NVDA, ", " ") &IF(Final_Report[[#This Row],[Chrome/NVDA]]="Applicable", "Windows_11, Chrome, NVDA, ", " ") &IF(Final_Report[[#This Row],[iOS/VO]]="Applicable", "iOS Tablet, VoiceOver, ", " ") &IF(Final_Report[[#This Row],[Mac/Safari/VO]]="Applicable", "macOS_12, Safari, VoiceOver, ", " ") &IF(Final_Report[[#This Row],[Mac/Chrome/VO]]="Applicable", "macOS_12, Chrome, VoiceOver, ", " ") &IF(Final_Report[[#This Row],[Android/Talkback]]="Applicable", "TalkBack, Android Tablet", " ") ) &", " &IF(ISERROR(FIND("iOS 13",INDEX(Keyword[Component Keyword],MATCH(TRUE,INDEX((Keyword[Component Keyword]<>0),0),0)))=FALSE),INDEX(Keyword[Component Keyword],MATCH(TRUE,INDEX((Keyword[Component Keyword]<>0),0),0)),SUBSTITUTE(INDEX(Keyword[Component Keyword],MATCH(TRUE,INDEX((Keyword[Component Keyword]<>0),0),0)),"iOS 13","iOS")),",",""))+1))-1)*999+1,999))))} -> N/A (Level N/A), Windows_11, Chrome, JAWS, NVDA, Accessibility, Audit, Marketing, MLM-XL, MLVISION, MyLab, US, VPAT | AM5: {=CONCATENATE(LEFT(AH5, SEARCH(" ", AH5) -1),", ",Labels[Labels])} -> #VALUE! | AN5: =IF(AJ5="Blocker","1 - Critical - showstopper",IF(AJ5="Critical","1 - Critical - showstopper",IF(AJ5="Major","1 - Critical - showstopper",IF(AJ5="Minor","3 - Medium - minor functionality broken",IF(AJ5="Trivial","4 - Low - cosmetic or usability"))))) -> FALSE | AR5: Known issue - ACDS-248696 | BC5: =VLOOKUP('Final Report'!D5,'Issue Variable'!A:N,11,FALSE) -> #N/A
A6: P2 | B6: =VLOOKUP(A6,URL[],2,0) -> Course Home - Calendar | C6: =VLOOKUP(A6,URL[],3,0) -> 0 | D6: Content | E6: Element type defined inappropriately | F6: The <article> element was incorrectly defined on the tested page which resulted in a confusing experience for screen reader users - Known issue - ACDS-248691 known check done valid- dilip | G6: Applicable | H6: Applicable | I6: Applicable | P6: naveen.lagishetty | Q6: No QA Needed | S6: No | T6: =IF(Final_Report[[#This Row],[Move to Report]]="Yes",VLOOKUP(E6,IssueVariable[],3,0),"N/A") -> N/A | U6: =IF(Final_Report[[#This Row],[Move to Report]]="Yes",VLOOKUP(E6,IssueVariable[],4,0),"N/A") -> N/A | V6: =Final_Report[[#This Row],[Issue Description]] -> N/A | X6: =Final_Report[[#This Row],[Code Snippet]] -> 0 | Y6: =IF(Final_Report[[#This Row],[Move to Report]]="Yes",VLOOKUP(E6,IssueVariable[],5,0),"N/A") -> N/A | Z6: =Final_Report[[#This Row],[Expected Result]] -> N/A | AA6: =IF(Final_Report[[#This Row],[Move to Report]]="Yes",VLOOKUP(E6,IssueVariable[],6,0),"N/A") -> N/A | AB6: =IF(Final_Report[[#This Row],[Move to Report]]="Yes",VLOOKUP(E6,IssueVariable[],7,0),"N/A") -> N/A | AC6: =Final_Report[[#This Row],[Recommendation]] -> N/A | AE6: =IF(Final_Report[[#This Row],[Move to Report]]="Yes",VLOOKUP(E6,IssueVariable[],8,0),"N/A") -> N/A | AF6: =Final_Report[[#This Row],[Steps to Reproduce]] -> N/A | AG6: =IF(Final_Report[[#This Row],[Move to Report]]="Yes",VLOOKUP(E6,IssueVariable[],9,0),"N/A") -> N/A | AH6: =IF(Final_Report[[#This Row],[Move to Report]]="Yes",VLOOKUP(E6,IssueVariable[],10,0),"N/A") -> N/A | AK6: {=Table95[Tested on]} -> Windows: 11 MAC OS: 12 iOS: 15 Android OS: 10 | AL6: {=_xlfn.TEXTJOIN(", ",TRUE,_xlfn.UNIQUE(TRIM(MID(SUBSTITUTE((Final_Report[[#This Row],[WCAG 2.1 Success Criteria]] &_xlfn.CONCAT(" (Level ") &Final_Report[[#This Row],[WCAG 2.1 Conformance Level]] &_xlfn.CONCAT("), ") &IF(Final_Report[[#This Row],[Chrome/JAWS]]="Applicable","Windows_11, Chrome, JAWS, ", " ") &IF(Final_Report[[#This Row],[FF/NVDA]]="Applicable", "Windows_11, Firefox, NVDA, ", " ") &IF(Final_Report[[#This Row],[Chrome/NVDA]]="Applicable", "Windows_11, Chrome, NVDA, ", " ") &IF(Final_Report[[#This Row],[iOS/VO]]="Applicable", "iOS Tablet, VoiceOver, ", " ") &IF(Final_Report[[#This Row],[Mac/Safari/VO]]="Applicable", "macOS_12, Safari, VoiceOver, ", " ") &IF(Final_Report[[#This Row],[Mac/Chrome/VO]]="Applicable", "macOS_12, Chrome, VoiceOver, ", " ") &IF(Final_Report[[#This Row],[Android/Talkback]]="Applicable", "TalkBack, Android Tablet", " ") ) &", " &IF(ISERROR(FIND("iOS 13",INDEX(Keyword[Component Keyword],MATCH(TRUE,INDEX((Keyword[Component Keyword]<>0),0),0)))=FALSE),INDEX(Keyword[Component Keyword],MATCH(TRUE,INDEX((Keyword[Component Keyword]<>0),0),0)),SUBSTITUTE(INDEX(Keyword[Component Keyword],MATCH(TRUE,INDEX((Keyword[Component Keyword]<>0),0),0)),"iOS 13","iOS")),",",REPT(" ",999)),(ROW($AAN$1:INDEX($AAX:$AAX,LEN((Final_Report[[#This Row],[WCAG 2.1 Success Criteria]] &_xlfn.CONCAT(" (Level ") &Final_Report[[#This Row],[WCAG 2.1 Conformance Level]] &_xlfn.CONCAT("), ") &IF(Final_Report[[#This Row],[Chrome/JAWS]]="Applicable","Windows_11, Chrome, JAWS, ", " ") &IF(Final_Report[[#This Row],[FF/NVDA]]="Applicable", "Windows_11, Firefox, NVDA, ", " ") &IF(Final_Report[[#This Row],[Chrome/NVDA]]="Applicable", "Windows_11, Chrome, NVDA, ", " ") &IF(Final_Report[[#This Row],[iOS/VO]]="Applicable", "iOS Tablet, VoiceOver, ", " ") &IF(Final_Report[[#This Row],[Mac/Safari/VO]]="Applicable", "macOS_12, Safari, VoiceOver, ", " ") &IF(Final_Report[[#This Row],[Mac/Chrome/VO]]="Applicable", "macOS_12, Chrome, VoiceOver, ", " ") &IF(Final_Report[[#This Row],[Android/Talkback]]="Applicable", "TalkBack, Android Tablet", " ") ) &", " &IF(ISERROR(FIND("iOS 13",INDEX(Keyword[Component Keyword],MATCH(TRUE,INDEX((Keyword[Component Keyword]<>0),0),0)))=FALSE),INDEX(Keyword[Component Keyword],MATCH(TRUE,INDEX((Keyword[Component Keyword]<>0),0),0)),SUBSTITUTE(INDEX(Keyword[Component Keyword],MATCH(TRUE,INDEX((Keyword[Component Keyword]<>0),0),0)),"iOS 13","iOS")))-LEN(SUBSTITUTE((Final_Report[[#This Row],[WCAG 2.1 Success Criteria]] &_xlfn.CONCAT(" (Level ") &Final_Report[[#This Row],[WCAG 2.1 Conformance Level]] &_xlfn.CONCAT("), ") &IF(Final_Report[[#This Row],[Chrome/JAWS]]="Applicable","Windows_11, Chrome, JAWS, ", " ") &IF(Final_Report[[#This Row],[FF/NVDA]]="Applicable", "Windows_11, Firefox, NVDA, ", " ") &IF(Final_Report[[#This Row],[Chrome/NVDA]]="Applicable", "Windows_11, Chrome, NVDA, ", " ") &IF(Final_Report[[#This Row],[iOS/VO]]="Applicable", "iOS Tablet, VoiceOver, ", " ") &IF(Final_Report[[#This Row],[Mac/Safari/VO]]="Applicable", "macOS_12, Safari, VoiceOver, ", " ") &IF(Final_Report[[#This Row],[Mac/Chrome/VO]]="Applicable", "macOS_12, Chrome, VoiceOver, ", " ") &IF(Final_Report[[#This Row],[Android/Talkback]]="Applicable", "TalkBack, Android Tablet", " ") ) &", " &IF(ISERROR(FIND("iOS 13",INDEX(Keyword[Component Keyword],MATCH(TRUE,INDEX((Keyword[Component Keyword]<>0),0),0)))=FALSE),INDEX(Keyword[Component Keyword],MATCH(TRUE,INDEX((Keyword[Component Keyword]<>0),0),0)),SUBSTITUTE(INDEX(Keyword[Component Keyword],MATCH(TRUE,INDEX((Keyword[Component Keyword]<>0),0),0)),"iOS 13","iOS")),",",""))+1))-1)*999+1,999))))} -> N/A (Level N/A), Windows_11, Chrome, JAWS, Firefox, NVDA, Accessibility, Audit, Marketing, MLM-XL, MLVISION, MyLab, US, VPAT | AM6: {=CONCATENATE(LEFT(AH6, SEARCH(" ", AH6) -1),", ",Labels[Labels])} -> #VALUE! | AN6: =IF(AJ6="Blocker","1 - Critical - showstopper",IF(AJ6="Critical","1 - Critical - showstopper",IF(AJ6="Major","1 - Critical - showstopper",IF(AJ6="Minor","3 - Medium - minor functionality broken",IF(AJ6="Trivial","4 - Low - cosmetic or usability"))))) -> FALSE | AR6: Known issue - ACDS-248691 | BC6: =VLOOKUP('Final Report'!D6,'Issue Variable'!A:N,11,FALSE) -> #N/A
A7: P2 | B7: =VLOOKUP(A7,URL[],2,0) -> Course Home - Calendar | C7: =VLOOKUP(A7,URL[],3,0) -> 0 | D7: Focus | E7: Focus not clearly visible | F7: When user activate "0%, Overall Score" button it shows "Show progress and scores" toggle button where focus outline is not clearly visible. | G7: Applicable | I7: Applicable | M7: Applicable | P7: naveen.lagishetty | Q7: No QA Needed | S7: Yes | T7: Web: Course Home - Calendar: Focus not clearly visible | U7: When accessing the page through the keyboard, it is not possible to visually identify user’s current location on the menu items such as "Show progress and scores" toggle button (that becomes available on activating "0%, Overall Score" button). Focus indicator is not clearly visible as the user tabs through using a keyboard. | V7: =Final_Report[[#This Row],[Issue Description]] -> When accessing the page through the keyboard, it is not possible to visually identify user’s current location on the menu items such as "Show progress and scores" toggle button (that becomes available on activating "0%, Overall Score" button). Focus indicator is not clearly visible as the user tabs through using a keyboard. | X7: =Final_Report[[#This Row],[Code Snippet]] -> 0 | Y7: =IF(Final_Report[[#This Row],[Move to Report]]="Yes",VLOOKUP(E7,IssueVariable[],5,0),"N/A") -> When the keyboard-only users navigate through the above-discussed content, there should be a clear visual indication to user when their focus moves from one interactive element to another. | Z7: =Final_Report[[#This Row],[Expected Result]] -> When the keyboard-only users navigate through the above-discussed content, there should be a clear visual indication to user when their focus moves from one interactive element to another. | AA7: =IF(Final_Report[[#This Row],[Move to Report]]="Yes",VLOOKUP(E7,IssueVariable[],6,0),"N/A") -> On screen, visual focus indication helps users find out about their location on the page. This is found very helpful by users with low vision, elderly users, keyboard-only users and users with mobility impairments. In the absence of clear focus indication, users would find it difficult to access the page information. | AB7: =IF(Final_Report[[#This Row],[Move to Report]]="Yes",VLOOKUP(E7,IssueVariable[],7,0),"N/A") -> Provide clear visual indication to user when their focus moves from one interactive element to another. This will help all users while accessing the page content especially users with visual, mobility and learning impairments. | AC7: =Final_Report[[#This Row],[Recommendation]] -> Provide clear visual indication to user when their focus moves from one interactive element to another. This will help all users while accessing the page content especially users with visual, mobility and learning impairments. | AD7: URL: https://www.pearsonmylabandmastering.com/northamerica Username: Aqavpat-edu1 Password: AuditPa559338 Course Title: AQA_VPAT_Kotler_Principles of Marketing 19e Course Id: auditor49388 1. Launch the above URL with the given credentials and navigate to the mentioned course | AE7: 2. Navigate to Course Home > Calendar interactive element and activate it. 3. Navigate to "0%, Overall Score" button and activate. 4. Navigate with tab key and oberve focus on "Show progress and scores" toggle button. | AF7: =Final_Report[[#This Row],[Steps to Reproduce]] -> 2. Navigate to Course Home > Calendar interactive element and activate it. 3. Navigate to "0%, Overall Score" button and activate. 4. Navigate with tab key and oberve focus on "Show progress and scores" toggle button. | AG7: =IF(Final_Report[[#This Row],[Move to Report]]="Yes",VLOOKUP(E7,IssueVariable[],9,0),"N/A") -> AA | AH7: =IF(Final_Report[[#This Row],[Move to Report]]="Yes",VLOOKUP(E7,IssueVariable[],10,0),"N/A") -> 2.4.7 Focus Visible | AI7: Marketing_7 | AJ7: Minor | AK7: {=Table95[Tested on]} -> Windows: 11 MAC OS: 12 iOS: 15 Android OS: 10 | AL7: {=_xlfn.TEXTJOIN(", ",TRUE,_xlfn.UNIQUE(TRIM(MID(SUBSTITUTE((Final_Report[[#This Row],[WCAG 2.1 Success Criteria]] &_xlfn.CONCAT(" (Level ") &Final_Report[[#This Row],[WCAG 2.1 Conformance Level]] &_xlfn.CONCAT("), ") &IF(Final_Report[[#This Row],[Chrome/JAWS]]="Applicable","Windows_11, Chrome, JAWS, ", " ") &IF(Final_Report[[#This Row],[FF/NVDA]]="Applicable", "Windows_11, Firefox, NVDA, ", " ") &IF(Final_Report[[#This Row],[Chrome/NVDA]]="Applicable", "Windows_11, Chrome, NVDA, ", " ") &IF(Final_Report[[#This Row],[iOS/VO]]="Applicable", "iOS Tablet, VoiceOver, ", " ") &IF(Final_Report[[#This Row],[Mac/Safari/VO]]="Applicable", "macOS_12, Safari, VoiceOver, ", " ") &IF(Final_Report[[#This Row],[Mac/Chrome/VO]]="Applicable", "macOS_12, Chrome, VoiceOver, ", " ") &IF(Final_Report[[#This Row],[Android/Talkback]]="Applicable", "TalkBack, Android Tablet", " ") ) &", " &IF(ISERROR(FIND("iOS 13",INDEX(Keyword[Component Keyword],MATCH(TRUE,INDEX((Keyword[Component Keyword]<>0),0),0)))=FALSE),INDEX(Keyword[Component Keyword],MATCH(TRUE,INDEX((Keyword[Component Keyword]<>0),0),0)),SUBSTITUTE(INDEX(Keyword[Component Keyword],MATCH(TRUE,INDEX((Keyword[Component Keyword]<>0),0),0)),"iOS 13","iOS")),",",REPT(" ",999)),(ROW($AAN$1:INDEX($AAX:$AAX,LEN((Final_Report[[#This Row],[WCAG 2.1 Success Criteria]] &_xlfn.CONCAT(" (Level ") &Final_Report[[#This Row],[WCAG 2.1 Conformance Level]] &_xlfn.CONCAT("), ") &IF(Final_Report[[#This Row],[Chrome/JAWS]]="Applicable","Windows_11, Chrome, JAWS, ", " ") &IF(Final_Report[[#This Row],[FF/NVDA]]="Applicable", "Windows_11, Firefox, NVDA, ", " ") &IF(Final_Report[[#This Row],[Chrome/NVDA]]="Applicable", "Windows_11, Chrome, NVDA, ", " ") &IF(Final_Report[[#This Row],[iOS/VO]]="Applicable", "iOS Tablet, VoiceOver, ", " ") &IF(Final_Report[[#This Row],[Mac/Safari/VO]]="Applicable", "macOS_12, Safari, VoiceOver, ", " ") &IF(Final_Report[[#This Row],[Mac/Chrome/VO]]="Applicable", "macOS_12, Chrome, VoiceOver, ", " ") &IF(Final_Report[[#This Row],[Android/Talkback]]="Applicable", "TalkBack, Android Tablet", " ") ) &", " &IF(ISERROR(FIND("iOS 13",INDEX(Keyword[Component Keyword],MATCH(TRUE,INDEX((Keyword[Component Keyword]<>0),0),0)))=FALSE),INDEX(Keyword[Component Keyword],MATCH(TRUE,INDEX((Keyword[Component Keyword]<>0),0),0)),SUBSTITUTE(INDEX(Keyword[Component Keyword],MATCH(TRUE,INDEX((Keyword[Component Keyword]<>0),0),0)),"iOS 13","iOS")))-LEN(SUBSTITUTE((Final_Report[[#This Row],[WCAG 2.1 Success Criteria]] &_xlfn.CONCAT(" (Level ") &Final_Report[[#This Row],[WCAG 2.1 Conformance Level]] &_xlfn.CONCAT("), ") &IF(Final_Report[[#This Row],[Chrome/JAWS]]="Applicable","Windows_11, Chrome, JAWS, ", " ") &IF(Final_Report[[#This Row],[FF/NVDA]]="Applicable", "Windows_11, Firefox, NVDA, ", " ") &IF(Final_Report[[#This Row],[Chrome/NVDA]]="Applicable", "Windows_11, Chrome, NVDA, ", " ") &IF(Final_Report[[#This Row],[iOS/VO]]="Applicable", "iOS Tablet, VoiceOver, ", " ") &IF(Final_Report[[#This Row],[Mac/Safari/VO]]="Applicable", "macOS_12, Safari, VoiceOver, ", " ") &IF(Final_Report[[#This Row],[Mac/Chrome/VO]]="Applicable", "macOS_12, Chrome, VoiceOver, ", " ") &IF(Final_Report[[#This Row],[Android/Talkback]]="Applicable", "TalkBack, Android Tablet", " ") ) &", " &IF(ISERROR(FIND("iOS 13",INDEX(Keyword[Component Keyword],MATCH(TRUE,INDEX((Keyword[Component Keyword]<>0),0),0)))=FALSE),INDEX(Keyword[Component Keyword],MATCH(TRUE,INDEX((Keyword[Component Keyword]<>0),0),0)),SUBSTITUTE(INDEX(Keyword[Component Keyword],MATCH(TRUE,INDEX((Keyword[Component Keyword]<>0),0),0)),"iOS 13","iOS")),",",""))+1))-1)*999+1,999))))} -> 2.4.7 Focus Visible (Level AA), Windows_11, Chrome, JAWS, NVDA, TalkBack, Android Tablet, Accessibility, Audit, Marketing, MLM-XL, MLVISION, MyLab, US, VPAT | AM7: {=CONCATENATE(LEFT(AH7, SEARCH(" ", AH7) -1),", ",Labels[Labels])} -> 2.4.7, Accessibility, Audit, Marketing, MLM-XL, MLVISION, MyLab, US, VPAT | AN7: =IF(AJ7="Blocker","1 - Critical - showstopper",IF(AJ7="Critical","1 - Critical - showstopper",IF(AJ7="Major","1 - Critical - showstopper",IF(AJ7="Minor","3 - Medium - minor functionality broken",IF(AJ7="Trivial","4 - Low - cosmetic or usability"))))) -> 3 - Medium - minor functionality broken | AO7: naveen.lagishetty | AP7: 5 | AS7: 5 | AT7: manasi.varma | AU7: issue is correct but we have flagged color issue it will solve focus problem also | AV7: Technical Issues | AW7: 5 | AX7: Delete - QA | BC7: =VLOOKUP('Final Report'!D7,'Issue Variable'!A:N,11,FALSE) -> #N/A
A8: P2 | B8: =VLOOKUP(A8,URL[],2,0) -> Course Home - Calendar | C8: =VLOOKUP(A8,URL[],3,0) -> 0 | D8: Keyboard | E8: Missing Keyboard Support for Button | F8: Calendar elements provided role="button" where it works with only enter key not with space key. | G8: Applicable | I8: Applicable | P8: naveen.lagishetty | Q8: No QA Needed | S8: No | T8: =IF(Final_Report[[#This Row],[Move to Report]]="Yes",VLOOKUP(E8,IssueVariable[],3,0),"N/A") -> N/A | U8: =IF(Final_Report[[#This Row],[Move to Report]]="Yes",VLOOKUP(E8,IssueVariable[],4,0),"N/A") -> N/A | V8: =Final_Report[[#This Row],[Issue Description]] -> N/A | X8: =Final_Report[[#This Row],[Code Snippet]] -> 0 | Y8: =IF(Final_Report[[#This Row],[Move to Report]]="Yes",VLOOKUP(E8,IssueVariable[],5,0),"N/A") -> N/A | Z8: =Final_Report[[#This Row],[Expected Result]] -> N/A | AA8: =IF(Final_Report[[#This Row],[Move to Report]]="Yes",VLOOKUP(E8,IssueVariable[],6,0),"N/A") -> N/A | AB8: =IF(Final_Report[[#This Row],[Move to Report]]="Yes",VLOOKUP(E8,IssueVariable[],7,0),"N/A") -> N/A | AC8: =Final_Report[[#This Row],[Recommendation]] -> N/A | AE8: =IF(Final_Report[[#This Row],[Move to Report]]="Yes",VLOOKUP(E8,IssueVariable[],8,0),"N/A") -> N/A | AF8: =Final_Report[[#This Row],[Steps to Reproduce]] -> N/A | AG8: =IF(Final_Report[[#This Row],[Move to Report]]="Yes",VLOOKUP(E8,IssueVariable[],9,0),"N/A") -> N/A | AH8: =IF(Final_Report[[#This Row],[Move to Report]]="Yes",VLOOKUP(E8,IssueVariable[],10,0),"N/A") -> N/A | AK8: {=Table95[Tested on]} -> Windows: 11 MAC OS: 12 iOS: 15 Android OS: 10 | AL8: {=_xlfn.TEXTJOIN(", ",TRUE,_xlfn.UNIQUE(TRIM(MID(SUBSTITUTE((Final_Report[[#This Row],[WCAG 2.1 Success Criteria]] &_xlfn.CONCAT(" (Level ") &Final_Report[[#This Row],[WCAG 2.1 Conformance Level]] &_xlfn.CONCAT("), ") &IF(Final_Report[[#This Row],[Chrome/JAWS]]="Applicable","Windows_11, Chrome, JAWS, ", " ") &IF(Final_Report[[#This Row],[FF/NVDA]]="Applicable", "Windows_11, Firefox, NVDA, ", " ") &IF(Final_Report[[#This Row],[Chrome/NVDA]]="Applicable", "Windows_11, Chrome, NVDA, ", " ") &IF(Final_Report[[#This Row],[iOS/VO]]="Applicable", "iOS Tablet, VoiceOver, ", " ") &IF(Final_Report[[#This Row],[Mac/Safari/VO]]="Applicable", "macOS_12, Safari, VoiceOver, ", " ") &IF(Final_Report[[#This Row],[Mac/Chrome/VO]]="Applicable", "macOS_12, Chrome, VoiceOver, ", " ") &IF(Final_Report[[#This Row],[Android/Talkback]]="Applicable", "TalkBack, Android Tablet", " ") ) &", " &IF(ISERROR(FIND("iOS 13",INDEX(Keyword[Component Keyword],MATCH(TRUE,INDEX((Keyword[Component Keyword]<>0),0),0)))=FALSE),INDEX(Keyword[Component Keyword],MATCH(TRUE,INDEX((Keyword[Component Keyword]<>0),0),0)),SUBSTITUTE(INDEX(Keyword[Component Keyword],MATCH(TRUE,INDEX((Keyword[Component Keyword]<>0),0),0)),"iOS 13","iOS")),",",REPT(" ",999)),(ROW($AAN$1:INDEX($AAX:$AAX,LEN((Final_Report[[#This Row],[WCAG 2.1 Success Criteria]] &_xlfn.CONCAT(" (Level ") &Final_Report[[#This Row],[WCAG 2.1 Conformance Level]] &_xlfn.CONCAT("), ") &IF(Final_Report[[#This Row],[Chrome/JAWS]]="Applicable","Windows_11, Chrome, JAWS, ", " ") &IF(Final_Report[[#This Row],[FF/NVDA]]="Applicable", "Windows_11, Firefox, NVDA, ", " ") &IF(Final_Report[[#This Row],[Chrome/NVDA]]="Applicable", "Windows_11, Chrome, NVDA, ", " ") &IF(Final_Report[[#This Row],[iOS/VO]]="Applicable", "iOS Tablet, VoiceOver, ", " ") &IF(Final_Report[[#This Row],[Mac/Safari/VO]]="Applicable", "macOS_12, Safari, VoiceOver, ", " ") &IF(Final_Report[[#This Row],[Mac/Chrome/VO]]="Applicable", "macOS_12, Chrome, VoiceOver, ", " ") &IF(Final_Report[[#This Row],[Android/Talkback]]="Applicable", "TalkBack, Android Tablet", " ") ) &", " &IF(ISERROR(FIND("iOS 13",INDEX(Keyword[Component Keyword],MATCH(TRUE,INDEX((Keyword[Component Keyword]<>0),0),0)))=FALSE),INDEX(Keyword[Component Keyword],MATCH(TRUE,INDEX((Keyword[Component Keyword]<>0),0),0)),SUBSTITUTE(INDEX(Keyword[Component Keyword],MATCH(TRUE,INDEX((Keyword[Component Keyword]<>0),0),0)),"iOS 13","iOS")))-LEN(SUBSTITUTE((Final_Report[[#This Row],[WCAG 2.1 Success Criteria]] &_xlfn.CONCAT(" (Level ") &Final_Report[[#This Row],[WCAG 2.1 Conformance Level]] &_xlfn.CONCAT("), ") &IF(Final_Report[[#This Row],[Chrome/JAWS]]="Applicable","Windows_11, Chrome, JAWS, ", " ") &IF(Final_Report[[#This Row],[FF/NVDA]]="Applicable", "Windows_11, Firefox, NVDA, ", " ") &IF(Final_Report[[#This Row],[Chrome/NVDA]]="Applicable", "Windows_11, Chrome, NVDA, ", " ") &IF(Final_Report[[#This Row],[iOS/VO]]="Applicable", "iOS Tablet, VoiceOver, ", " ") &IF(Final_Report[[#This Row],[Mac/Safari/VO]]="Applicable", "macOS_12, Safari, VoiceOver, ", " ") &IF(Final_Report[[#This Row],[Mac/Chrome/VO]]="Applicable", "macOS_12, Chrome, VoiceOver, ", " ") &IF(Final_Report[[#This Row],[Android/Talkback]]="Applicable", "TalkBack, Android Tablet", " ") ) &", " &IF(ISERROR(FIND("iOS 13",INDEX(Keyword[Component Keyword],MATCH(TRUE,INDEX((Keyword[Component Keyword]<>0),0),0)))=FALSE),INDEX(Keyword[Component Keyword],MATCH(TRUE,INDEX((Keyword[Component Keyword]<>0),0),0)),SUBSTITUTE(INDEX(Keyword[Component Keyword],MATCH(TRUE,INDEX((Keyword[Component Keyword]<>0),0),0)),"iOS 13","iOS")),",",""))+1))-1)*999+1,999))))} -> N/A (Level N/A), Windows_11, Chrome, JAWS, NVDA, Accessibility, Audit, Marketing, MLM-XL, MLVISION, MyLab, US, VPAT | AM8: {=CONCATENATE(LEFT(AH8, SEARCH(" ", AH8) -1),", ",Labels[Labels])} -> #VALUE! | AN8: =IF(AJ8="Blocker","1 - Critical - showstopper",IF(AJ8="Critical","1 - Critical - showstopper",IF(AJ8="Major","1 - Critical - showstopper",IF(AJ8="Minor","3 - Medium - minor functionality broken",IF(AJ8="Trivial","4 - Low - cosmetic or usability"))))) -> FALSE | BC8: =VLOOKUP('Final Report'!D8,'Issue Variable'!A:N,11,FALSE) -> #N/A
A9: P2 | B9: =VLOOKUP(A9,URL[],2,0) -> Course Home - Calendar | C9: =VLOOKUP(A9,URL[],3,0) -> 0 | D9: Content | E9: Element type defined inappropriately | F9: "Skip to main content" difiend wrong place it creates a confusion to screen reader users - known issue - ACDS-149317, ACDS-161894 | G9: Applicable | H9: Applicable | I9: Applicable | P9: naveen.lagishetty | Q9: No QA Needed | S9: No | T9: =IF(Final_Report[[#This Row],[Move to Report]]="Yes",VLOOKUP(E9,IssueVariable[],3,0),"N/A") -> N/A | U9: =IF(Final_Report[[#This Row],[Move to Report]]="Yes",VLOOKUP(E9,IssueVariable[],4,0),"N/A") -> N/A | V9: =Final_Report[[#This Row],[Issue Description]] -> N/A | X9: =Final_Report[[#This Row],[Code Snippet]] -> 0 | Y9: =IF(Final_Report[[#This Row],[Move to Report]]="Yes",VLOOKUP(E9,IssueVariable[],5,0),"N/A") -> N/A | Z9: =Final_Report[[#This Row],[Expected Result]] -> N/A | AA9: =IF(Final_Report[[#This Row],[Move to Report]]="Yes",VLOOKUP(E9,IssueVariable[],6,0),"N/A") -> N/A | AB9: =IF(Final_Report[[#This Row],[Move to Report]]="Yes",VLOOKUP(E9,IssueVariable[],7,0),"N/A") -> N/A | AC9: =Final_Report[[#This Row],[Recommendation]] -> N/A | AE9: =IF(Final_Report[[#This Row],[Move to Report]]="Yes",VLOOKUP(E9,IssueVariable[],8,0),"N/A") -> N/A | AF9: =Final_Report[[#This Row],[Steps to Reproduce]] -> N/A | AG9: =IF(Final_Report[[#This Row],[Move to Report]]="Yes",VLOOKUP(E9,IssueVariable[],9,0),"N/A") -> N/A | AH9: =IF(Final_Report[[#This Row],[Move to Report]]="Yes",VLOOKUP(E9,IssueVariable[],10,0),"N/A") -> N/A | AK9: {=Table95[Tested on]} -> Windows: 11 MAC OS: 12 iOS: 15 Android OS: 10 | AL9: {=_xlfn.TEXTJOIN(", ",TRUE,_xlfn.UNIQUE(TRIM(MID(SUBSTITUTE((Final_Report[[#This Row],[WCAG 2.1 Success Criteria]] &_xlfn.CONCAT(" (Level ") &Final_Report[[#This Row],[WCAG 2.1 Conformance Level]] &_xlfn.CONCAT("), ") &IF(Final_Report[[#This Row],[Chrome/JAWS]]="Applicable","Windows_11, Chrome, JAWS, ", " ") &IF(Final_Report[[#This Row],[FF/NVDA]]="Applicable", "Windows_11, Firefox, NVDA, ", " ") &IF(Final_Report[[#This Row],[Chrome/NVDA]]="Applicable", "Windows_11, Chrome, NVDA, ", " ") &IF(Final_Report[[#This Row],[iOS/VO]]="Applicable", "iOS Tablet, VoiceOver, ", " ") &IF(Final_Report[[#This Row],[Mac/Safari/VO]]="Applicable", "macOS_12, Safari, VoiceOver, ", " ") &IF(Final_Report[[#This Row],[Mac/Chrome/VO]]="Applicable", "macOS_12, Chrome, VoiceOver, ", " ") &IF(Final_Report[[#This Row],[Android/Talkback]]="Applicable", "TalkBack, Android Tablet", " ") ) &", " &IF(ISERROR(FIND("iOS 13",INDEX(Keyword[Component Keyword],MATCH(TRUE,INDEX((Keyword[Component Keyword]<>0),0),0)))=FALSE),INDEX(Keyword[Component Keyword],MATCH(TRUE,INDEX((Keyword[Component Keyword]<>0),0),0)),SUBSTITUTE(INDEX(Keyword[Component Keyword],MATCH(TRUE,INDEX((Keyword[Component Keyword]<>0),0),0)),"iOS 13","iOS")),",",REPT(" ",999)),(ROW($AAN$1:INDEX($AAX:$AAX,LEN((Final_Report[[#This Row],[WCAG 2.1 Success Criteria]] &_xlfn.CONCAT(" (Level ") &Final_Report[[#This Row],[WCAG 2.1 Conformance Level]] &_xlfn.CONCAT("), ") &IF(Final_Report[[#This Row],[Chrome/JAWS]]="Applicable","Windows_11, Chrome, JAWS, ", " ") &IF(Final_Report[[#This Row],[FF/NVDA]]="Applicable", "Windows_11, Firefox, NVDA, ", " ") &IF(Final_Report[[#This Row],[Chrome/NVDA]]="Applicable", "Windows_11, Chrome, NVDA, ", " ") &IF(Final_Report[[#This Row],[iOS/VO]]="Applicable", "iOS Tablet, VoiceOver, ", " ") &IF(Final_Report[[#This Row],[Mac/Safari/VO]]="Applicable", "macOS_12, Safari, VoiceOver, ", " ") &IF(Final_Report[[#This Row],[Mac/Chrome/VO]]="Applicable", "macOS_12, Chrome, VoiceOver, ", " ") &IF(Final_Report[[#This Row],[Android/Talkback]]="Applicable", "TalkBack, Android Tablet", " ") ) &", " &IF(ISERROR(FIND("iOS 13",INDEX(Keyword[Component Keyword],MATCH(TRUE,INDEX((Keyword[Component Keyword]<>0),0),0)))=FALSE),INDEX(Keyword[Component Keyword],MATCH(TRUE,INDEX((Keyword[Component Keyword]<>0),0),0)),SUBSTITUTE(INDEX(Keyword[Component Keyword],MATCH(TRUE,INDEX((Keyword[Component Keyword]<>0),0),0)),"iOS 13","iOS")))-LEN(SUBSTITUTE((Final_Report[[#This Row],[WCAG 2.1 Success Criteria]] &_xlfn.CONCAT(" (Level ") &Final_Report[[#This Row],[WCAG 2.1 Conformance Level]] &_xlfn.CONCAT("), ") &IF(Final_Report[[#This Row],[Chrome/JAWS]]="Applicable","Windows_11, Chrome, JAWS, ", " ") &IF(Final_Report[[#This Row],[FF/NVDA]]="Applicable", "Windows_11, Firefox, NVDA, ", " ") &IF(Final_Report[[#This Row],[Chrome/NVDA]]="Applicable", "Windows_11, Chrome, NVDA, ", " ") &IF(Final_Report[[#This Row],[iOS/VO]]="Applicable", "iOS Tablet, VoiceOver, ", " ") &IF(Final_Report[[#This Row],[Mac/Safari/VO]]="Applicable", "macOS_12, Safari, VoiceOver, ", " ") &IF(Final_Report[[#This Row],[Mac/Chrome/VO]]="Applicable", "macOS_12, Chrome, VoiceOver, ", " ") &IF(Final_Report[[#This Row],[Android/Talkback]]="Applicable", "TalkBack, Android Tablet", " ") ) &", " &IF(ISERROR(FIND("iOS 13",INDEX(Keyword[Component Keyword],MATCH(TRUE,INDEX((Keyword[Component Keyword]<>0),0),0)))=FALSE),INDEX(Keyword[Component Keyword],MATCH(TRUE,INDEX((Keyword[Component Keyword]<>0),0),0)),SUBSTITUTE(INDEX(Keyword[Component Keyword],MATCH(TRUE,INDEX((Keyword[Component Keyword]<>0),0),0)),"iOS 13","iOS")),",",""))+1))-1)*999+1,999))))} -> N/A (Level N/A), Windows_11, Chrome, JAWS, Firefox, NVDA, Accessibility, Audit, Marketing, MLM-XL, MLVISION, MyLab, US, VPAT | AM9: {=CONCATENATE(LEFT(AH9, SEARCH(" ", AH9) -1),", ",Labels[Labels])} -> #VALUE! | AN9: =IF(AJ9="Blocker","1 - Critical - showstopper",IF(AJ9="Critical","1 - Critical - showstopper",IF(AJ9="Major","1 - Critical - showstopper",IF(AJ9="Minor","3 - Medium - minor functionality broken",IF(AJ9="Trivial","4 - Low - cosmetic or usability"))))) -> FALSE | AR9: known issue - ACDS-149317, ACDS-161894 | BC9: =VLOOKUP('Final Report'!D9,'Issue Variable'!A:N,11,FALSE) -> #N/A
A10: P2 | B10: =VLOOKUP(A10,URL[],2,0) -> Course Home - Calendar | C10: =VLOOKUP(A10,URL[],3,0) -> 0 | D10: Focus | E10: Focus moves inappropriately | F10: When user activate "0%, Overall Score" button it shows a popup menu where focus does not moves to the menu | G10: Applicable | I10: Applicable | P10: naveen.lagishetty | Q10: Delete | S10: No | T10: =IF(Final_Report[[#This Row],[Move to Report]]="Yes",VLOOKUP(E10,IssueVariable[],3,0),"N/A") -> N/A | U10: =IF(Final_Report[[#This Row],[Move to Report]]="Yes",VLOOKUP(E10,IssueVariable[],4,0),"N/A") -> N/A | V10: =Final_Report[[#This Row],[Issue Description]] -> N/A | X10: =Final_Report[[#This Row],[Code Snippet]] -> 0 | Y10: =IF(Final_Report[[#This Row],[Move to Report]]="Yes",VLOOKUP(E10,IssueVariable[],5,0),"N/A") -> N/A | Z10: =Final_Report[[#This Row],[Expected Result]] -> N/A | AA10: =IF(Final_Report[[#This Row],[Move to Report]]="Yes",VLOOKUP(E10,IssueVariable[],6,0),"N/A") -> N/A | AB10: =IF(Final_Report[[#This Row],[Move to Report]]="Yes",VLOOKUP(E10,IssueVariable[],7,0),"N/A") -> N/A | AC10: =Final_Report[[#This Row],[Recommendation]] -> N/A | AE10: =IF(Final_Report[[#This Row],[Move to Report]]="Yes",VLOOKUP(E10,IssueVariable[],8,0),"N/A") -> N/A | AF10: =Final_Report[[#This Row],[Steps to Reproduce]] -> N/A | AG10: =IF(Final_Report[[#This Row],[Move to Report]]="Yes",VLOOKUP(E10,IssueVariable[],9,0),"N/A") -> N/A | AH10: =IF(Final_Report[[#This Row],[Move to Report]]="Yes",VLOOKUP(E10,IssueVariable[],10,0),"N/A") -> N/A | AK10: {=Table95[Tested on]} -> Windows: 11 MAC OS: 12 iOS: 15 Android OS: 10 | AL10: {=_xlfn.TEXTJOIN(", ",TRUE,_xlfn.UNIQUE(TRIM(MID(SUBSTITUTE((Final_Report[[#This Row],[WCAG 2.1 Success Criteria]] &_xlfn.CONCAT(" (Level ") &Final_Report[[#This Row],[WCAG 2.1 Conformance Level]] &_xlfn.CONCAT("), ") &IF(Final_Report[[#This Row],[Chrome/JAWS]]="Applicable","Windows_11, Chrome, JAWS, ", " ") &IF(Final_Report[[#This Row],[FF/NVDA]]="Applicable", "Windows_11, Firefox, NVDA, ", " ") &IF(Final_Report[[#This Row],[Chrome/NVDA]]="Applicable", "Windows_11, Chrome, NVDA, ", " ") &IF(Final_Report[[#This Row],[iOS/VO]]="Applicable", "iOS Tablet, VoiceOver, ", " ") &IF(Final_Report[[#This Row],[Mac/Safari/VO]]="Applicable", "macOS_12, Safari, VoiceOver, ", " ") &IF(Final_Report[[#This Row],[Mac/Chrome/VO]]="Applicable", "macOS_12, Chrome, VoiceOver, ", " ") &IF(Final_Report[[#This Row],[Android/Talkback]]="Applicable", "TalkBack, Android Tablet", " ") ) &", " &IF(ISERROR(FIND("iOS 13",INDEX(Keyword[Component Keyword],MATCH(TRUE,INDEX((Keyword[Component Keyword]<>0),0),0)))=FALSE),INDEX(Keyword[Component Keyword],MATCH(TRUE,INDEX((Keyword[Component Keyword]<>0),0),0)),SUBSTITUTE(INDEX(Keyword[Component Keyword],MATCH(TRUE,INDEX((Keyword[Component Keyword]<>0),0),0)),"iOS 13","iOS")),",",REPT(" ",999)),(ROW($AAN$1:INDEX($AAX:$AAX,LEN((Final_Report[[#This Row],[WCAG 2.1 Success Criteria]] &_xlfn.CONCAT(" (Level ") &Final_Report[[#This Row],[WCAG 2.1 Conformance Level]] &_xlfn.CONCAT("), ") &IF(Final_Report[[#This Row],[Chrome/JAWS]]="Applicable","Windows_11, Chrome, JAWS, ", " ") &IF(Final_Report[[#This Row],[FF/NVDA]]="Applicable", "Windows_11, Firefox, NVDA, ", " ") &IF(Final_Report[[#This Row],[Chrome/NVDA]]="Applicable", "Windows_11, Chrome, NVDA, ", " ") &IF(Final_Report[[#This Row],[iOS/VO]]="Applicable", "iOS Tablet, VoiceOver, ", " ") &IF(Final_Report[[#This Row],[Mac/Safari/VO]]="Applicable", "macOS_12, Safari, VoiceOver, ", " ") &IF(Final_Report[[#This Row],[Mac/Chrome/VO]]="Applicable", "macOS_12, Chrome, VoiceOver, ", " ") &IF(Final_Report[[#This Row],[Android/Talkback]]="Applicable", "TalkBack, Android Tablet", " ") ) &", " &IF(ISERROR(FIND("iOS 13",INDEX(Keyword[Component Keyword],MATCH(TRUE,INDEX((Keyword[Component Keyword]<>0),0),0)))=FALSE),INDEX(Keyword[Component Keyword],MATCH(TRUE,INDEX((Keyword[Component Keyword]<>0),0),0)),SUBSTITUTE(INDEX(Keyword[Component Keyword],MATCH(TRUE,INDEX((Keyword[Component Keyword]<>0),0),0)),"iOS 13","iOS")))-LEN(SUBSTITUTE((Final_Report[[#This Row],[WCAG 2.1 Success Criteria]] &_xlfn.CONCAT(" (Level ") &Final_Report[[#This Row],[WCAG 2.1 Conformance Level]] &_xlfn.CONCAT("), ") &IF(Final_Report[[#This Row],[Chrome/JAWS]]="Applicable","Windows_11, Chrome, JAWS, ", " ") &IF(Final_Report[[#This Row],[FF/NVDA]]="Applicable", "Windows_11, Firefox, NVDA, ", " ") &IF(Final_Report[[#This Row],[Chrome/NVDA]]="Applicable", "Windows_11, Chrome, NVDA, ", " ") &IF(Final_Report[[#This Row],[iOS/VO]]="Applicable", "iOS Tablet, VoiceOver, ", " ") &IF(Final_Report[[#This Row],[Mac/Safari/VO]]="Applicable", "macOS_12, Safari, VoiceOver, ", " ") &IF(Final_Report[[#This Row],[Mac/Chrome/VO]]="Applicable", "macOS_12, Chrome, VoiceOver, ", " ") &IF(Final_Report[[#This Row],[Android/Talkback]]="Applicable", "TalkBack, Android Tablet", " ") ) &", " &IF(ISERROR(FIND("iOS 13",INDEX(Keyword[Component Keyword],MATCH(TRUE,INDEX((Keyword[Component Keyword]<>0),0),0)))=FALSE),INDEX(Keyword[Component Keyword],MATCH(TRUE,INDEX((Keyword[Component Keyword]<>0),0),0)),SUBSTITUTE(INDEX(Keyword[Component Keyword],MATCH(TRUE,INDEX((Keyword[Component Keyword]<>0),0),0)),"iOS 13","iOS")),",",""))+1))-1)*999+1,999))))} -> N/A (Level N/A), Windows_11, Chrome, JAWS, NVDA, Accessibility, Audit, Marketing, MLM-XL, MLVISION, MyLab, US, VPAT | AM10: {=CONCATENATE(LEFT(AH10, SEARCH(" ", AH10) -1),", ",Labels[Labels])} -> #VALUE! | AN10: =IF(AJ10="Blocker","1 - Critical - showstopper",IF(AJ10="Critical","1 - Critical - showstopper",IF(AJ10="Major","1 - Critical - showstopper",IF(AJ10="Minor","3 - Medium - minor functionality broken",IF(AJ10="Trivial","4 - Low - cosmetic or usability"))))) -> FALSE | BC10: =VLOOKUP('Final Report'!D10,'Issue Variable'!A:N,11,FALSE) -> #N/A
A11: P2 | B11: =VLOOKUP(A11,URL[],2,0) -> Course Home - Calendar | C11: =VLOOKUP(A11,URL[],3,0) -> 0 | D11: Focus | E11: Focus moves inappropriately | F11: When user activate "Help" button it open a popup menu where focus does not moves to the menu and here using | G11: Applicable | I11: Applicable | P11: naveen.lagishetty | Q11: Delete | S11: No | T11: =IF(Final_Report[[#This Row],[Move to Report]]="Yes",VLOOKUP(E11,IssueVariable[],3,0),"N/A") -> N/A | U11: =IF(Final_Report[[#This Row],[Move to Report]]="Yes",VLOOKUP(E11,IssueVariable[],4,0),"N/A") -> N/A | V11: =Final_Report[[#This Row],[Issue Description]] -> N/A | X11: =Final_Report[[#This Row],[Code Snippet]] -> 0 | Y11: =IF(Final_Report[[#This Row],[Move to Report]]="Yes",VLOOKUP(E11,IssueVariable[],5,0),"N/A") -> N/A | Z11: =Final_Report[[#This Row],[Expected Result]] -> N/A | AA11: =IF(Final_Report[[#This Row],[Move to Report]]="Yes",VLOOKUP(E11,IssueVariable[],6,0),"N/A") -> N/A | AB11: =IF(Final_Report[[#This Row],[Move to Report]]="Yes",VLOOKUP(E11,IssueVariable[],7,0),"N/A") -> N/A | AC11: =Final_Report[[#This Row],[Recommendation]] -> N/A | AE11: =IF(Final_Report[[#This Row],[Move to Report]]="Yes",VLOOKUP(E11,IssueVariable[],8,0),"N/A") -> N/A | AF11: =Final_Report[[#This Row],[Steps to Reproduce]] -> N/A | AG11: =IF(Final_Report[[#This Row],[Move to Report]]="Yes",VLOOKUP(E11,IssueVariable[],9,0),"N/A") -> N/A | AH11: =IF(Final_Report[[#This Row],[Move to Report]]="Yes",VLOOKUP(E11,IssueVariable[],10,0),"N/A") -> N/A | AK11: {=Table95[Tested on]} -> Windows: 11 MAC OS: 12 iOS: 15 Android OS: 10 | AL11: {=_xlfn.TEXTJOIN(", ",TRUE,_xlfn.UNIQUE(TRIM(MID(SUBSTITUTE((Final_Report[[#This Row],[WCAG 2.1 Success Criteria]] &_xlfn.CONCAT(" (Level ") &Final_Report[[#This Row],[WCAG 2.1 Conformance Level]] &_xlfn.CONCAT("), ") &IF(Final_Report[[#This Row],[Chrome/JAWS]]="Applicable","Windows_11, Chrome, JAWS, ", " ") &IF(Final_Report[[#This Row],[FF/NVDA]]="Applicable", "Windows_11, Firefox, NVDA, ", " ") &IF(Final_Report[[#This Row],[Chrome/NVDA]]="Applicable", "Windows_11, Chrome, NVDA, ", " ") &IF(Final_Report[[#This Row],[iOS/VO]]="Applicable", "iOS Tablet, VoiceOver, ", " ") &IF(Final_Report[[#This Row],[Mac/Safari/VO]]="Applicable", "macOS_12, Safari, VoiceOver, ", " ") &IF(Final_Report[[#This Row],[Mac/Chrome/VO]]="Applicable", "macOS_12, Chrome, VoiceOver, ", " ") &IF(Final_Report[[#This Row],[Android/Talkback]]="Applicable", "TalkBack, Android Tablet", " ") ) &", " &IF(ISERROR(FIND("iOS 13",INDEX(Keyword[Component Keyword],MATCH(TRUE,INDEX((Keyword[Component Keyword]<>0),0),0)))=FALSE),INDEX(Keyword[Component Keyword],MATCH(TRUE,INDEX((Keyword[Component Keyword]<>0),0),0)),SUBSTITUTE(INDEX(Keyword[Component Keyword],MATCH(TRUE,INDEX((Keyword[Component Keyword]<>0),0),0)),"iOS 13","iOS")),",",REPT(" ",999)),(ROW($AAN$1:INDEX($AAX:$AAX,LEN((Final_Report[[#This Row],[WCAG 2.1 Success Criteria]] &_xlfn.CONCAT(" (Level ") &Final_Report[[#This Row],[WCAG 2.1 Conformance Level]] &_xlfn.CONCAT("), ") &IF(Final_Report[[#This Row],[Chrome/JAWS]]="Applicable","Windows_11, Chrome, JAWS, ", " ") &IF(Final_Report[[#This Row],[FF/NVDA]]="Applicable", "Windows_11, Firefox, NVDA, ", " ") &IF(Final_Report[[#This Row],[Chrome/NVDA]]="Applicable", "Windows_11, Chrome, NVDA, ", " ") &IF(Final_Report[[#This Row],[iOS/VO]]="Applicable", "iOS Tablet, VoiceOver, ", " ") &IF(Final_Report[[#This Row],[Mac/Safari/VO]]="Applicable", "macOS_12, Safari, VoiceOver, ", " ") &IF(Final_Report[[#This Row],[Mac/Chrome/VO]]="Applicable", "macOS_12, Chrome, VoiceOver, ", " ") &IF(Final_Report[[#This Row],[Android/Talkback]]="Applicable", "TalkBack, Android Tablet", " ") ) &", " &IF(ISERROR(FIND("iOS 13",INDEX(Keyword[Component Keyword],MATCH(TRUE,INDEX((Keyword[Component Keyword]<>0),0),0)))=FALSE),INDEX(Keyword[Component Keyword],MATCH(TRUE,INDEX((Keyword[Component Keyword]<>0),0),0)),SUBSTITUTE(INDEX(Keyword[Component Keyword],MATCH(TRUE,INDEX((Keyword[Component Keyword]<>0),0),0)),"iOS 13","iOS")))-LEN(SUBSTITUTE((Final_Report[[#This Row],[WCAG 2.1 Success Criteria]] &_xlfn.CONCAT(" (Level ") &Final_Report[[#This Row],[WCAG 2.1 Conformance Level]] &_xlfn.CONCAT("), ") &IF(Final_Report[[#This Row],[Chrome/JAWS]]="Applicable","Windows_11, Chrome, JAWS, ", " ") &IF(Final_Report[[#This Row],[FF/NVDA]]="Applicable", "Windows_11, Firefox, NVDA, ", " ") &IF(Final_Report[[#This Row],[Chrome/NVDA]]="Applicable", "Windows_11, Chrome, NVDA, ", " ") &IF(Final_Report[[#This Row],[iOS/VO]]="Applicable", "iOS Tablet, VoiceOver, ", " ") &IF(Final_Report[[#This Row],[Mac/Safari/VO]]="Applicable", "macOS_12, Safari, VoiceOver, ", " ") &IF(Final_Report[[#This Row],[Mac/Chrome/VO]]="Applicable", "macOS_12, Chrome, VoiceOver, ", " ") &IF(Final_Report[[#This Row],[Android/Talkback]]="Applicable", "TalkBack, Android Tablet", " ") ) &", " &IF(ISERROR(FIND("iOS 13",INDEX(Keyword[Component Keyword],MATCH(TRUE,INDEX((Keyword[Component Keyword]<>0),0),0)))=FALSE),INDEX(Keyword[Component Keyword],MATCH(TRUE,INDEX((Keyword[Component Keyword]<>0),0),0)),SUBSTITUTE(INDEX(Keyword[Component Keyword],MATCH(TRUE,INDEX((Keyword[Component Keyword]<>0),0),0)),"iOS 13","iOS")),",",""))+1))-1)*999+1,999))))} -> N/A (Level N/A), Windows_11, Chrome, JAWS, NVDA, Accessibility, Audit, Marketing, MLM-XL, MLVISION, MyLab, US, VPAT | AM11: {=CONCATENATE(LEFT(AH11, SEARCH(" ", AH11) -1),", ",Labels[Labels])} -> #VALUE! | AN11: =IF(AJ11="Blocker","1 - Critical - showstopper",IF(AJ11="Critical","1 - Critical - showstopper",IF(AJ11="Major","1 - Critical - showstopper",IF(AJ11="Minor","3 - Medium - minor functionality broken",IF(AJ11="Trivial","4 - Low - cosmetic or usability"))))) -> FALSE | BC11: =VLOOKUP('Final Report'!D11,'Issue Variable'!A:N,11,FALSE) -> #N/A
A12: P2 | B12: =VLOOKUP(A12,URL[],2,0) -> Course Home - Calendar | C12: =VLOOKUP(A12,URL[],3,0) -> 0 | D12: Colour | E12: Insufficient color contrast for states of user interface controls | F12: In "Entire Course To Date" tab under "Current Assignment" for each link has image link "Circle" blue and "Square" yellow where has insufficient color contrast | G12: Applicable | I12: Applicable | M12: Applicable | P12: naveen.lagishetty | Q12: No QA Needed | S12: Yes | T12: Web: Course Home - Calendar: Insufficient color contrast for states of user interface controls | U12: The color for user interface controls with their adjacent colours an insufficient contrast ratio were found on the page. Following are the instances affected: • The foreground #3BA3BF for "Circle Blue" icon image provided to "Chapter 2 Homework", "Ch 20 NEW Mini Sim on Socially Responsible Marketing" link has a color contrast ratio of 2.9:1 with #FFFFFF background. • The foreground #E39F00 for "Square Yellow" icon image provided to "Chapter 2 quiz" link has a color contrast ratio of 2.3:1 with #FFFFFF background. | V12: =Final_Report[[#This Row],[Issue Description]] -> The color for user interface controls with their adjacent colours an insufficient contrast ratio were found on the page. Following are the instances affected: • The foreground #3BA3BF for "Circle Blue" icon image provided to "Chapter 2 Homework", "Ch 20 NEW Mini Sim on Socially Responsible Marketing" link has a color contrast ratio of 2.9:1 with #FFFFFF background. • The foreground #E39F00 for "Square Yellow" icon image provided to "Chapter 2 quiz" link has a color contrast ratio of 2.3:1 with #FFFFFF background. | X12: =Final_Report[[#This Row],[Code Snippet]] -> 0 | Y12: =IF(Final_Report[[#This Row],[Move to Report]]="Yes",VLOOKUP(E12,IssueVariable[],5,0),"N/A") -> The user interface controls should have sufficient color contrast ratio with their adjacent colours. | Z12: =Final_Report[[#This Row],[Expected Result]] -> The user interface controls should have sufficient color contrast ratio with their adjacent colours. | AA12: =IF(Final_Report[[#This Row],[Move to Report]]="Yes",VLOOKUP(E12,IssueVariable[],6,0),"N/A") -> User Interface controls should have sufficient contrast with the adjacent colors on different states, i.e. hover, focus and active. This helps low vision users to identify the state of different user interface controls easily. All non-text elements, such as key images, user interface controls in different states (hover, active and focus) should have a contrast ratio of 3:1.This will ensure that users with color deficiencies and low vision can access the controls with ease. | AB12: =IF(Final_Report[[#This Row],[Move to Report]]="Yes",VLOOKUP(E12,IssueVariable[],7,0),"N/A") -> For all states of user interface controls, ensure that the color contrast for controls with their adjacent colors is 3:1. | AC12: =Final_Report[[#This Row],[Recommendation]] -> For all states of user interface controls, ensure that the color contrast for controls with their adjacent colors is 3:1. | AD12: URL: https://www.pearsonmylabandmastering.com/northamerica Username: Aqavpat-edu1 Password: AuditPa559338 Course Title: AQA_VPAT_Kotler_Principles of Marketing 19e Course Id: auditor49388 1. Launch the above URL with the given credentials and navigate to the mentioned course | AE12: 2. Navigate to Course Home > Calendar interactive element and activate it. 3.Inspect the controls of "Chapter 2 Homework", "Ch 20 NEW Mini Sim…" and "Chapter 2 quiz" link icons ("Circle", "Square") with their adjacent colors using CCA. | AF12: =Final_Report[[#This Row],[Steps to Reproduce]] -> 2. Navigate to Course Home > Calendar interactive element and activate it. 3.Inspect the controls of "Chapter 2 Homework", "Ch 20 NEW Mini Sim…" and "Chapter 2 quiz" link icons ("Circle", "Square") with their adjacent colors using CCA. | AG12: =IF(Final_Report[[#This Row],[Move to Report]]="Yes",VLOOKUP(E12,IssueVariable[],9,0),"N/A") -> AA | AH12: =IF(Final_Report[[#This Row],[Move to Report]]="Yes",VLOOKUP(E12,IssueVariable[],10,0),"N/A") -> 1.4.11 Non-text Contrast | AI12: Marketing_12a, Marketing_ 12b | AJ12: Major | AK12: {=Table95[Tested on]} -> Windows: 11 MAC OS: 12 iOS: 15 Android OS: 10 | AL12: {=_xlfn.TEXTJOIN(", ",TRUE,_xlfn.UNIQUE(TRIM(MID(SUBSTITUTE((Final_Report[[#This Row],[WCAG 2.1 Success Criteria]] &_xlfn.CONCAT(" (Level ") &Final_Report[[#This Row],[WCAG 2.1 Conformance Level]] &_xlfn.CONCAT("), ") &IF(Final_Report[[#This Row],[Chrome/JAWS]]="Applicable","Windows_11, Chrome, JAWS, ", " ") &IF(Final_Report[[#This Row],[FF/NVDA]]="Applicable", "Windows_11, Firefox, NVDA, ", " ") &IF(Final_Report[[#This Row],[Chrome/NVDA]]="Applicable", "Windows_11, Chrome, NVDA, ", " ") &IF(Final_Report[[#This Row],[iOS/VO]]="Applicable", "iOS Tablet, VoiceOver, ", " ") &IF(Final_Report[[#This Row],[Mac/Safari/VO]]="Applicable", "macOS_12, Safari, VoiceOver, ", " ") &IF(Final_Report[[#This Row],[Mac/Chrome/VO]]="Applicable", "macOS_12, Chrome, VoiceOver, ", " ") &IF(Final_Report[[#This Row],[Android/Talkback]]="Applicable", "TalkBack, Android Tablet", " ") ) &", " &IF(ISERROR(FIND("iOS 13",INDEX(Keyword[Component Keyword],MATCH(TRUE,INDEX((Keyword[Component Keyword]<>0),0),0)))=FALSE),INDEX(Keyword[Component Keyword],MATCH(TRUE,INDEX((Keyword[Component Keyword]<>0),0),0)),SUBSTITUTE(INDEX(Keyword[Component Keyword],MATCH(TRUE,INDEX((Keyword[Component Keyword]<>0),0),0)),"iOS 13","iOS")),",",REPT(" ",999)),(ROW($AAN$1:INDEX($AAX:$AAX,LEN((Final_Report[[#This Row],[WCAG 2.1 Success Criteria]] &_xlfn.CONCAT(" (Level ") &Final_Report[[#This Row],[WCAG 2.1 Conformance Level]] &_xlfn.CONCAT("), ") &IF(Final_Report[[#This Row],[Chrome/JAWS]]="Applicable","Windows_11, Chrome, JAWS, ", " ") &IF(Final_Report[[#This Row],[FF/NVDA]]="Applicable", "Windows_11, Firefox, NVDA, ", " ") &IF(Final_Report[[#This Row],[Chrome/NVDA]]="Applicable", "Windows_11, Chrome, NVDA, ", " ") &IF(Final_Report[[#This Row],[iOS/VO]]="Applicable", "iOS Tablet, VoiceOver, ", " ") &IF(Final_Report[[#This Row],[Mac/Safari/VO]]="Applicable", "macOS_12, Safari, VoiceOver, ", " ") &IF(Final_Report[[#This Row],[Mac/Chrome/VO]]="Applicable", "macOS_12, Chrome, VoiceOver, ", " ") &IF(Final_Report[[#This Row],[Android/Talkback]]="Applicable", "TalkBack, Android Tablet", " ") ) &", " &IF(ISERROR(FIND("iOS 13",INDEX(Keyword[Component Keyword],MATCH(TRUE,INDEX((Keyword[Component Keyword]<>0),0),0)))=FALSE),INDEX(Keyword[Component Keyword],MATCH(TRUE,INDEX((Keyword[Component Keyword]<>0),0),0)),SUBSTITUTE(INDEX(Keyword[Component Keyword],MATCH(TRUE,INDEX((Keyword[Component Keyword]<>0),0),0)),"iOS 13","iOS")))-LEN(SUBSTITUTE((Final_Report[[#This Row],[WCAG 2.1 Success Criteria]] &_xlfn.CONCAT(" (Level ") &Final_Report[[#This Row],[WCAG 2.1 Conformance Level]] &_xlfn.CONCAT("), ") &IF(Final_Report[[#This Row],[Chrome/JAWS]]="Applicable","Windows_11, Chrome, JAWS, ", " ") &IF(Final_Report[[#This Row],[FF/NVDA]]="Applicable", "Windows_11, Firefox, NVDA, ", " ") &IF(Final_Report[[#This Row],[Chrome/NVDA]]="Applicable", "Windows_11, Chrome, NVDA, ", " ") &IF(Final_Report[[#This Row],[iOS/VO]]="Applicable", "iOS Tablet, VoiceOver, ", " ") &IF(Final_Report[[#This Row],[Mac/Safari/VO]]="Applicable", "macOS_12, Safari, VoiceOver, ", " ") &IF(Final_Report[[#This Row],[Mac/Chrome/VO]]="Applicable", "macOS_12, Chrome, VoiceOver, ", " ") &IF(Final_Report[[#This Row],[Android/Talkback]]="Applicable", "TalkBack, Android Tablet", " ") ) &", " &IF(ISERROR(FIND("iOS 13",INDEX(Keyword[Component Keyword],MATCH(TRUE,INDEX((Keyword[Component Keyword]<>0),0),0)))=FALSE),INDEX(Keyword[Component Keyword],MATCH(TRUE,INDEX((Keyword[Component Keyword]<>0),0),0)),SUBSTITUTE(INDEX(Keyword[Component Keyword],MATCH(TRUE,INDEX((Keyword[Component Keyword]<>0),0),0)),"iOS 13","iOS")),",",""))+1))-1)*999+1,999))))} -> 1.4.11 Non-text Contrast (Level AA), Windows_11, Chrome, JAWS, NVDA, TalkBack, Android Tablet, Accessibility, Audit, Marketing, MLM-XL, MLVISION, MyLab, US, VPAT | AM12: {=CONCATENATE(LEFT(AH12, SEARCH(" ", AH12) -1),", ",Labels[Labels])} -> 1.4.11, Accessibility, Audit, Marketing, MLM-XL, MLVISION, MyLab, US, VPAT | AN12: =IF(AJ12="Blocker","1 - Critical - showstopper",IF(AJ12="Critical","1 - Critical - showstopper",IF(AJ12="Major","1 - Critical - showstopper",IF(AJ12="Minor","3 - Medium - minor functionality broken",IF(AJ12="Trivial","4 - Low - cosmetic or usability"))))) -> 1 - Critical - showstopper | AO12: naveen.lagishetty | AP12: 5 | AQ12: 5 | AS12: 5 | AT12: manisha.prakash | AU12: issue is invalid manasi pls check this is known or not | AV12: Technical Issues | AW12: 5 | AX12: Delete - QA | BC12: =VLOOKUP('Final Report'!D12,'Issue Variable'!A:N,11,FALSE) -> #N/A
A13: P3 | B13: =VLOOKUP(A13,URL[],2,0) -> Student Success Hub | C13: =VLOOKUP(A13,URL[],3,0) -> 0 | D13: Iframe | E13: Inappropriate iframe title | F13: Ifram has no title attirube. This issue applicable all the left navigation items Known issue - ACDS-149081, ACDS-149081 | G13: Applicable | H13: Applicable | I13: Applicable | P13: naveen.lagishetty | Q13: No QA Needed | S13: No | T13: =IF(Final_Report[[#This Row],[Move to Report]]="Yes",VLOOKUP(E13,IssueVariable[],3,0),"N/A") -> N/A | U13: =IF(Final_Report[[#This Row],[Move to Report]]="Yes",VLOOKUP(E13,IssueVariable[],4,0),"N/A") -> N/A | V13: =Final_Report[[#This Row],[Issue Description]] -> N/A | X13: =Final_Report[[#This Row],[Code Snippet]] -> 0 | Y13: =IF(Final_Report[[#This Row],[Move to Report]]="Yes",VLOOKUP(E13,IssueVariable[],5,0),"N/A") -> N/A | Z13: =Final_Report[[#This Row],[Expected Result]] -> N/A | AA13: =IF(Final_Report[[#This Row],[Move to Report]]="Yes",VLOOKUP(E13,IssueVariable[],6,0),"N/A") -> N/A | AB13: =IF(Final_Report[[#This Row],[Move to Report]]="Yes",VLOOKUP(E13,IssueVariable[],7,0),"N/A") -> N/A | AC13: =Final_Report[[#This Row],[Recommendation]] -> N/A | AE13: =IF(Final_Report[[#This Row],[Move to Report]]="Yes",VLOOKUP(E13,IssueVariable[],8,0),"N/A") -> N/A | AF13: =Final_Report[[#This Row],[Steps to Reproduce]] -> N/A | AG13: =IF(Final_Report[[#This Row],[Move to Report]]="Yes",VLOOKUP(E13,IssueVariable[],9,0),"N/A") -> N/A | AH13: =IF(Final_Report[[#This Row],[Move to Report]]="Yes",VLOOKUP(E13,IssueVariable[],10,0),"N/A") -> N/A | AK13: {=Table95[Tested on]} -> Windows: 11 MAC OS: 12 iOS: 15 Android OS: 10 | AL13: {=_xlfn.TEXTJOIN(", ",TRUE,_xlfn.UNIQUE(TRIM(MID(SUBSTITUTE((Final_Report[[#This Row],[WCAG 2.1 Success Criteria]] &_xlfn.CONCAT(" (Level ") &Final_Report[[#This Row],[WCAG 2.1 Conformance Level]] &_xlfn.CONCAT("), ") &IF(Final_Report[[#This Row],[Chrome/JAWS]]="Applicable","Windows_11, Chrome, JAWS, ", " ") &IF(Final_Report[[#This Row],[FF/NVDA]]="Applicable", "Windows_11, Firefox, NVDA, ", " ") &IF(Final_Report[[#This Row],[Chrome/NVDA]]="Applicable", "Windows_11, Chrome, NVDA, ", " ") &IF(Final_Report[[#This Row],[iOS/VO]]="Applicable", "iOS Tablet, VoiceOver, ", " ") &IF(Final_Report[[#This Row],[Mac/Safari/VO]]="Applicable", "macOS_12, Safari, VoiceOver, ", " ") &IF(Final_Report[[#This Row],[Mac/Chrome/VO]]="Applicable", "macOS_12, Chrome, VoiceOver, ", " ") &IF(Final_Report[[#This Row],[Android/Talkback]]="Applicable", "TalkBack, Android Tablet", " ") ) &", " &IF(ISERROR(FIND("iOS 13",INDEX(Keyword[Component Keyword],MATCH(TRUE,INDEX((Keyword[Component Keyword]<>0),0),0)))=FALSE),INDEX(Keyword[Component Keyword],MATCH(TRUE,INDEX((Keyword[Component Keyword]<>0),0),0)),SUBSTITUTE(INDEX(Keyword[Component Keyword],MATCH(TRUE,INDEX((Keyword[Component Keyword]<>0),0),0)),"iOS 13","iOS")),",",REPT(" ",999)),(ROW($AAN$1:INDEX($AAX:$AAX,LEN((Final_Report[[#This Row],[WCAG 2.1 Success Criteria]] &_xlfn.CONCAT(" (Level ") &Final_Report[[#This Row],[WCAG 2.1 Conformance Level]] &_xlfn.CONCAT("), ") &IF(Final_Report[[#This Row],[Chrome/JAWS]]="Applicable","Windows_11, Chrome, JAWS, ", " ") &IF(Final_Report[[#This Row],[FF/NVDA]]="Applicable", "Windows_11, Firefox, NVDA, ", " ") &IF(Final_Report[[#This Row],[Chrome/NVDA]]="Applicable", "Windows_11, Chrome, NVDA, ", " ") &IF(Final_Report[[#This Row],[iOS/VO]]="Applicable", "iOS Tablet, VoiceOver, ", " ") &IF(Final_Report[[#This Row],[Mac/Safari/VO]]="Applicable", "macOS_12, Safari, VoiceOver, ", " ") &IF(Final_Report[[#This Row],[Mac/Chrome/VO]]="Applicable", "macOS_12, Chrome, VoiceOver, ", " ") &IF(Final_Report[[#This Row],[Android/Talkback]]="Applicable", "TalkBack, Android Tablet", " ") ) &", " &IF(ISERROR(FIND("iOS 13",INDEX(Keyword[Component Keyword],MATCH(TRUE,INDEX((Keyword[Component Keyword]<>0),0),0)))=FALSE),INDEX(Keyword[Component Keyword],MATCH(TRUE,INDEX((Keyword[Component Keyword]<>0),0),0)),SUBSTITUTE(INDEX(Keyword[Component Keyword],MATCH(TRUE,INDEX((Keyword[Component Keyword]<>0),0),0)),"iOS 13","iOS")))-LEN(SUBSTITUTE((Final_Report[[#This Row],[WCAG 2.1 Success Criteria]] &_xlfn.CONCAT(" (Level ") &Final_Report[[#This Row],[WCAG 2.1 Conformance Level]] &_xlfn.CONCAT("), ") &IF(Final_Report[[#This Row],[Chrome/JAWS]]="Applicable","Windows_11, Chrome, JAWS, ", " ") &IF(Final_Report[[#This Row],[FF/NVDA]]="Applicable", "Windows_11, Firefox, NVDA, ", " ") &IF(Final_Report[[#This Row],[Chrome/NVDA]]="Applicable", "Windows_11, Chrome, NVDA, ", " ") &IF(Final_Report[[#This Row],[iOS/VO]]="Applicable", "iOS Tablet, VoiceOver, ", " ") &IF(Final_Report[[#This Row],[Mac/Safari/VO]]="Applicable", "macOS_12, Safari, VoiceOver, ", " ") &IF(Final_Report[[#This Row],[Mac/Chrome/VO]]="Applicable", "macOS_12, Chrome, VoiceOver, ", " ") &IF(Final_Report[[#This Row],[Android/Talkback]]="Applicable", "TalkBack, Android Tablet", " ") ) &", " &IF(ISERROR(FIND("iOS 13",INDEX(Keyword[Component Keyword],MATCH(TRUE,INDEX((Keyword[Component Keyword]<>0),0),0)))=FALSE),INDEX(Keyword[Component Keyword],MATCH(TRUE,INDEX((Keyword[Component Keyword]<>0),0),0)),SUBSTITUTE(INDEX(Keyword[Component Keyword],MATCH(TRUE,INDEX((Keyword[Component Keyword]<>0),0),0)),"iOS 13","iOS")),",",""))+1))-1)*999+1,999))))} -> N/A (Level N/A), Windows_11, Chrome, JAWS, Firefox, NVDA, Accessibility, Audit, Marketing, MLM-XL, MLVISION, MyLab, US, VPAT | AM13: {=CONCATENATE(LEFT(AH13, SEARCH(" ", AH13) -1),", ",Labels[Labels])} -> #VALUE! | AN13: =IF(AJ13="Blocker","1 - Critical - showstopper",IF(AJ13="Critical","1 - Critical - showstopper",IF(AJ13="Major","1 - Critical - showstopper",IF(AJ13="Minor","3 - Medium - minor functionality broken",IF(AJ13="Trivial","4 - Low - cosmetic or usability"))))) -> FALSE | AR13: Known issue - ACDS-149081, ACDS-149081 | BC13: =VLOOKUP('Final Report'!D13,'Issue Variable'!A:N,11,FALSE) -> #N/A
A14: P4 | B14: =VLOOKUP(A14,URL[],2,0) -> MyLab Tour for students | C14: =VLOOKUP(A14,URL[],3,0) -> 0 | D14: Table | E14: Incorrect table structure | F14: In main content area below the heading "Navigating your course" a table element present where doesn't have caption | G14: Applicable | H14: Applicable | I14: Applicable | J14: Applicable | K14: Applicable | L14: Applicable | M14: Applicable | P14: naveen.lagishetty | Q14: No QA Needed | S14: Yes | T14: Web: MyLab Tour for students: Incorrect table structure | U14: The table structure for the “Navigation course” table was found to be inappropriate. There is no table <caption> element provided. As a result, screen reader users cannot understand the table content effectively. | V14: =Final_Report[[#This Row],[Issue Description]] -> The table structure for the “Navigation course” table was found to be inappropriate. There is no table <caption> element provided. As a result, screen reader users cannot understand the table content effectively. | W14: <table class="body" style="width:60%"> <tbody> <tr style="height:30px;"> <th style="width:10%">Element Name</th> <th style="width:10%">Previous Name<br>(if different)</th> <th style="width:40%">Description</th> </tr> (...) </table </table> | X14: =Final_Report[[#This Row],[Code Snippet]] -> <table class="body" style="width:60%"> <tbody> <tr style="height:30px;"> <th style="width:10%">Element Name</th> <th style="width:10%">Previous Name<br>(if different)</th> <th style="width:40%">Description</th> </tr> (...) </table </table> | Y14: =IF(Final_Report[[#This Row],[Move to Report]]="Yes",VLOOKUP(E14,IssueVariable[],5,0),"N/A") -> The Structure of the table should be correctly identified for screen reader user. | Z14: =Final_Report[[#This Row],[Expected Result]] -> The Structure of the table should be correctly identified for screen reader user. | AA14: =IF(Final_Report[[#This Row],[Move to Report]]="Yes",VLOOKUP(E14,IssueVariable[],6,0),"N/A") -> Tables should be marked accurately. Data tables provide content in certain context. When the screen readers are informed about a table, they expect for table headers and data cells. Navigating through each cell enables them to identify and interpret tabular content. Table headers enable users identify the context of table data. Table headers are provided with <th> tags. A screen reader reads the table information in a linear order reading one cell at a time. Thus it is essential to mark-up the table headers to help users interpret the table data correctly. | AB14: Apply the following change mark-up the content such as "Navigating your course" using <caption> element. <table class="body" style="width:60%"> <caption>Navigating your course</caption> <tbody> <tr style="height:30px;"> <th style="width:10%">Element Name</th> <th style="width:10%">Previous Name<br>(if different)</th> <th style="width:40%">Description</th> </tr> (...) </table </table> | AC14: =Final_Report[[#This Row],[Recommendation]] -> Apply the following change mark-up the content such as "Navigating your course" using <caption> element. <table class="body" style="width:60%"> <caption>Navigating your course</caption> <tbody> <tr style="height:30px;"> <th style="width:10%">Element Name</th> <th style="width:10%">Previous Name<br>(if different)</th> <th style="width:40%">Description</th> </tr> (...) </table </table> | AD14: URL: https://www.pearsonmylabandmastering.com/northamerica Username: Aqavpat-edu1 Password: AuditPa559338 Course Title: AQA_VPAT_Kotler_Principles of Marketing 19e Course Id: auditor49388 1. Launch the above URL with the given credentials and navigate to the mentioned course | AE14: 2. Navigate to Student Success Hub > MyLab Tour for students interactive element and activate it. 3. Inspect the "Navigating your course" table. | AF14: =Final_Report[[#This Row],[Steps to Reproduce]] -> 2. Navigate to Student Success Hub > MyLab Tour for students interactive element and activate it. 3. Inspect the "Navigating your course" table. | AG14: =IF(Final_Report[[#This Row],[Move to Report]]="Yes",VLOOKUP(E14,IssueVariable[],9,0),"N/A") -> A | AH14: =IF(Final_Report[[#This Row],[Move to Report]]="Yes",VLOOKUP(E14,IssueVariable[],10,0),"N/A") -> 1.3.1 Info and Relationships | AI14: Marketing_14 | AJ14: Minor | AK14: {=Table95[Tested on]} -> Windows: 11 MAC OS: 12 iOS: 15 Android OS: 10 | AL14: {=_xlfn.TEXTJOIN(", ",TRUE,_xlfn.UNIQUE(TRIM(MID(SUBSTITUTE((Final_Report[[#This Row],[WCAG 2.1 Success Criteria]] &_xlfn.CONCAT(" (Level ") &Final_Report[[#This Row],[WCAG 2.1 Conformance Level]] &_xlfn.CONCAT("), ") &IF(Final_Report[[#This Row],[Chrome/JAWS]]="Applicable","Windows_11, Chrome, JAWS, ", " ") &IF(Final_Report[[#This Row],[FF/NVDA]]="Applicable", "Windows_11, Firefox, NVDA, ", " ") &IF(Final_Report[[#This Row],[Chrome/NVDA]]="Applicable", "Windows_11, Chrome, NVDA, ", " ") &IF(Final_Report[[#This Row],[iOS/VO]]="Applicable", "iOS Tablet, VoiceOver, ", " ") &IF(Final_Report[[#This Row],[Mac/Safari/VO]]="Applicable", "macOS_12, Safari, VoiceOver, ", " ") &IF(Final_Report[[#This Row],[Mac/Chrome/VO]]="Applicable", "macOS_12, Chrome, VoiceOver, ", " ") &IF(Final_Report[[#This Row],[Android/Talkback]]="Applicable", "TalkBack, Android Tablet", " ") ) &", " &IF(ISERROR(FIND("iOS 13",INDEX(Keyword[Component Keyword],MATCH(TRUE,INDEX((Keyword[Component Keyword]<>0),0),0)))=FALSE),INDEX(Keyword[Component Keyword],MATCH(TRUE,INDEX((Keyword[Component Keyword]<>0),0),0)),SUBSTITUTE(INDEX(Keyword[Component Keyword],MATCH(TRUE,INDEX((Keyword[Component Keyword]<>0),0),0)),"iOS 13","iOS")),",",REPT(" ",999)),(ROW($AAN$1:INDEX($AAX:$AAX,LEN((Final_Report[[#This Row],[WCAG 2.1 Success Criteria]] &_xlfn.CONCAT(" (Level ") &Final_Report[[#This Row],[WCAG 2.1 Conformance Level]] &_xlfn.CONCAT("), ") &IF(Final_Report[[#This Row],[Chrome/JAWS]]="Applicable","Windows_11, Chrome, JAWS, ", " ") &IF(Final_Report[[#This Row],[FF/NVDA]]="Applicable", "Windows_11, Firefox, NVDA, ", " ") &IF(Final_Report[[#This Row],[Chrome/NVDA]]="Applicable", "Windows_11, Chrome, NVDA, ", " ") &IF(Final_Report[[#This Row],[iOS/VO]]="Applicable", "iOS Tablet, VoiceOver, ", " ") &IF(Final_Report[[#This Row],[Mac/Safari/VO]]="Applicable", "macOS_12, Safari, VoiceOver, ", " ") &IF(Final_Report[[#This Row],[Mac/Chrome/VO]]="Applicable", "macOS_12, Chrome, VoiceOver, ", " ") &IF(Final_Report[[#This Row],[Android/Talkback]]="Applicable", "TalkBack, Android Tablet", " ") ) &", " &IF(ISERROR(FIND("iOS 13",INDEX(Keyword[Component Keyword],MATCH(TRUE,INDEX((Keyword[Component Keyword]<>0),0),0)))=FALSE),INDEX(Keyword[Component Keyword],MATCH(TRUE,INDEX((Keyword[Component Keyword]<>0),0),0)),SUBSTITUTE(INDEX(Keyword[Component Keyword],MATCH(TRUE,INDEX((Keyword[Component Keyword]<>0),0),0)),"iOS 13","iOS")))-LEN(SUBSTITUTE((Final_Report[[#This Row],[WCAG 2.1 Success Criteria]] &_xlfn.CONCAT(" (Level ") &Final_Report[[#This Row],[WCAG 2.1 Conformance Level]] &_xlfn.CONCAT("), ") &IF(Final_Report[[#This Row],[Chrome/JAWS]]="Applicable","Windows_11, Chrome, JAWS, ", " ") &IF(Final_Report[[#This Row],[FF/NVDA]]="Applicable", "Windows_11, Firefox, NVDA, ", " ") &IF(Final_Report[[#This Row],[Chrome/NVDA]]="Applicable", "Windows_11, Chrome, NVDA, ", " ") &IF(Final_Report[[#This Row],[iOS/VO]]="Applicable", "iOS Tablet, VoiceOver, ", " ") &IF(Final_Report[[#This Row],[Mac/Safari/VO]]="Applicable", "macOS_12, Safari, VoiceOver, ", " ") &IF(Final_Report[[#This Row],[Mac/Chrome/VO]]="Applicable", "macOS_12, Chrome, VoiceOver, ", " ") &IF(Final_Report[[#This Row],[Android/Talkback]]="Applicable", "TalkBack, Android Tablet", " ") ) &", " &IF(ISERROR(FIND("iOS 13",INDEX(Keyword[Component Keyword],MATCH(TRUE,INDEX((Keyword[Component Keyword]<>0),0),0)))=FALSE),INDEX(Keyword[Component Keyword],MATCH(TRUE,INDEX((Keyword[Component Keyword]<>0),0),0)),SUBSTITUTE(INDEX(Keyword[Component Keyword],MATCH(TRUE,INDEX((Keyword[Component Keyword]<>0),0),0)),"iOS 13","iOS")),",",""))+1))-1)*999+1,999))))} -> 1.3.1 Info and Relationships (Level A), Windows_11, Chrome, JAWS, Firefox, NVDA, iOS Tablet, VoiceOver, macOS_12, Safari, TalkBack, Android Tablet, Accessibility, Audit, Marketing, MLM-XL, MLVISION, MyLab, US, VPAT | AM14: {=CONCATENATE(LEFT(AH14, SEARCH(" ", AH14) -1),", ",Labels[Labels])} -> 1.3.1, Accessibility, Audit, Marketing, MLM-XL, MLVISION, MyLab, US, VPAT | AN14: =IF(AJ14="Blocker","1 - Critical - showstopper",IF(AJ14="Critical","1 - Critical - showstopper",IF(AJ14="Major","1 - Critical - showstopper",IF(AJ14="Minor","3 - Medium - minor functionality broken",IF(AJ14="Trivial","4 - Low - cosmetic or usability"))))) -> 3 - Medium - minor functionality broken | AO14: naveen.lagishetty | AP14: 5 | AQ14: 5 | AS14: 5 | AT14: manisha.prakash | AU14: invalid | AV14: Technical Issues | AW14: 5 | AX14: Delete - QA | BC14: =VLOOKUP('Final Report'!D14,'Issue Variable'!A:N,11,FALSE) -> #N/A
A15: P5 | B15: =VLOOKUP(A15,URL[],2,0) -> Dynamic Study Modules | C15: =VLOOKUP(A15,URL[],3,0) -> 0 | D15: Headings | E15: Inappropriate heading structure | F15: In iFrame heading text "study better" starts from h3 | G15: Applicable | H15: Applicable | I15: Applicable | P15: naveen.lagishetty | Q15: Delete | S15: No | T15: =IF(Final_Report[[#This Row],[Move to Report]]="Yes",VLOOKUP(E15,IssueVariable[],3,0),"N/A") -> N/A | U15: =IF(Final_Report[[#This Row],[Move to Report]]="Yes",VLOOKUP(E15,IssueVariable[],4,0),"N/A") -> N/A | V15: =Final_Report[[#This Row],[Issue Description]] -> N/A | X15: =Final_Report[[#This Row],[Code Snippet]] -> 0 | Y15: =IF(Final_Report[[#This Row],[Move to Report]]="Yes",VLOOKUP(E15,IssueVariable[],5,0),"N/A") -> N/A | Z15: =Final_Report[[#This Row],[Expected Result]] -> N/A | AA15: =IF(Final_Report[[#This Row],[Move to Report]]="Yes",VLOOKUP(E15,IssueVariable[],6,0),"N/A") -> N/A | AB15: =IF(Final_Report[[#This Row],[Move to Report]]="Yes",VLOOKUP(E15,IssueVariable[],7,0),"N/A") -> N/A | AC15: =Final_Report[[#This Row],[Recommendation]] -> N/A | AE15: =IF(Final_Report[[#This Row],[Move to Report]]="Yes",VLOOKUP(E15,IssueVariable[],8,0),"N/A") -> N/A | AF15: =Final_Report[[#This Row],[Steps to Reproduce]] -> N/A | AG15: =IF(Final_Report[[#This Row],[Move to Report]]="Yes",VLOOKUP(E15,IssueVariable[],9,0),"N/A") -> N/A | AH15: =IF(Final_Report[[#This Row],[Move to Report]]="Yes",VLOOKUP(E15,IssueVariable[],10,0),"N/A") -> N/A | AK15: {=Table95[Tested on]} -> Windows: 11 MAC OS: 12 iOS: 15 Android OS: 10 | AL15: {=_xlfn.TEXTJOIN(", ",TRUE,_xlfn.UNIQUE(TRIM(MID(SUBSTITUTE((Final_Report[[#This Row],[WCAG 2.1 Success Criteria]] &_xlfn.CONCAT(" (Level ") &Final_Report[[#This Row],[WCAG 2.1 Conformance Level]] &_xlfn.CONCAT("), ") &IF(Final_Report[[#This Row],[Chrome/JAWS]]="Applicable","Windows_11, Chrome, JAWS, ", " ") &IF(Final_Report[[#This Row],[FF/NVDA]]="Applicable", "Windows_11, Firefox, NVDA, ", " ") &IF(Final_Report[[#This Row],[Chrome/NVDA]]="Applicable", "Windows_11, Chrome, NVDA, ", " ") &IF(Final_Report[[#This Row],[iOS/VO]]="Applicable", "iOS Tablet, VoiceOver, ", " ") &IF(Final_Report[[#This Row],[Mac/Safari/VO]]="Applicable", "macOS_12, Safari, VoiceOver, ", " ") &IF(Final_Report[[#This Row],[Mac/Chrome/VO]]="Applicable", "macOS_12, Chrome, VoiceOver, ", " ") &IF(Final_Report[[#This Row],[Android/Talkback]]="Applicable", "TalkBack, Android Tablet", " ") ) &", " &IF(ISERROR(FIND("iOS 13",INDEX(Keyword[Component Keyword],MATCH(TRUE,INDEX((Keyword[Component Keyword]<>0),0),0)))=FALSE),INDEX(Keyword[Component Keyword],MATCH(TRUE,INDEX((Keyword[Component Keyword]<>0),0),0)),SUBSTITUTE(INDEX(Keyword[Component Keyword],MATCH(TRUE,INDEX((Keyword[Component Keyword]<>0),0),0)),"iOS 13","iOS")),",",REPT(" ",999)),(ROW($AAN$1:INDEX($AAX:$AAX,LEN((Final_Report[[#This Row],[WCAG 2.1 Success Criteria]] &_xlfn.CONCAT(" (Level ") &Final_Report[[#This Row],[WCAG 2.1 Conformance Level]] &_xlfn.CONCAT("), ") &IF(Final_Report[[#This Row],[Chrome/JAWS]]="Applicable","Windows_11, Chrome, JAWS, ", " ") &IF(Final_Report[[#This Row],[FF/NVDA]]="Applicable", "Windows_11, Firefox, NVDA, ", " ") &IF(Final_Report[[#This Row],[Chrome/NVDA]]="Applicable", "Windows_11, Chrome, NVDA, ", " ") &IF(Final_Report[[#This Row],[iOS/VO]]="Applicable", "iOS Tablet, VoiceOver, ", " ") &IF(Final_Report[[#This Row],[Mac/Safari/VO]]="Applicable", "macOS_12, Safari, VoiceOver, ", " ") &IF(Final_Report[[#This Row],[Mac/Chrome/VO]]="Applicable", "macOS_12, Chrome, VoiceOver, ", " ") &IF(Final_Report[[#This Row],[Android/Talkback]]="Applicable", "TalkBack, Android Tablet", " ") ) &", " &IF(ISERROR(FIND("iOS 13",INDEX(Keyword[Component Keyword],MATCH(TRUE,INDEX((Keyword[Component Keyword]<>0),0),0)))=FALSE),INDEX(Keyword[Component Keyword],MATCH(TRUE,INDEX((Keyword[Component Keyword]<>0),0),0)),SUBSTITUTE(INDEX(Keyword[Component Keyword],MATCH(TRUE,INDEX((Keyword[Component Keyword]<>0),0),0)),"iOS 13","iOS")))-LEN(SUBSTITUTE((Final_Report[[#This Row],[WCAG 2.1 Success Criteria]] &_xlfn.CONCAT(" (Level ") &Final_Report[[#This Row],[WCAG 2.1 Conformance Level]] &_xlfn.CONCAT("), ") &IF(Final_Report[[#This Row],[Chrome/JAWS]]="Applicable","Windows_11, Chrome, JAWS, ", " ") &IF(Final_Report[[#This Row],[FF/NVDA]]="Applicable", "Windows_11, Firefox, NVDA, ", " ") &IF(Final_Report[[#This Row],[Chrome/NVDA]]="Applicable", "Windows_11, Chrome, NVDA, ", " ") &IF(Final_Report[[#This Row],[iOS/VO]]="Applicable", "iOS Tablet, VoiceOver, ", " ") &IF(Final_Report[[#This Row],[Mac/Safari/VO]]="Applicable", "macOS_12, Safari, VoiceOver, ", " ") &IF(Final_Report[[#This Row],[Mac/Chrome/VO]]="Applicable", "macOS_12, Chrome, VoiceOver, ", " ") &IF(Final_Report[[#This Row],[Android/Talkback]]="Applicable", "TalkBack, Android Tablet", " ") ) &", " &IF(ISERROR(FIND("iOS 13",INDEX(Keyword[Component Keyword],MATCH(TRUE,INDEX((Keyword[Component Keyword]<>0),0),0)))=FALSE),INDEX(Keyword[Component Keyword],MATCH(TRUE,INDEX((Keyword[Component Keyword]<>0),0),0)),SUBSTITUTE(INDEX(Keyword[Component Keyword],MATCH(TRUE,INDEX((Keyword[Component Keyword]<>0),0),0)),"iOS 13","iOS")),",",""))+1))-1)*999+1,999))))} -> N/A (Level N/A), Windows_11, Chrome, JAWS, Firefox, NVDA, Accessibility, Audit, Marketing, MLM-XL, MLVISION, MyLab, US, VPAT | AM15: {=CONCATENATE(LEFT(AH15, SEARCH(" ", AH15) -1),", ",Labels[Labels])} -> #VALUE! | AN15: =IF(AJ15="Blocker","1 - Critical - showstopper",IF(AJ15="Critical","1 - Critical - showstopper",IF(AJ15="Major","1 - Critical - showstopper",IF(AJ15="Minor","3 - Medium - minor functionality broken",IF(AJ15="Trivial","4 - Low - cosmetic or usability"))))) -> FALSE | BC15: =VLOOKUP('Final Report'!D15,'Issue Variable'!A:N,11,FALSE) -> #N/A
A16: P5 | B16: =VLOOKUP(A16,URL[],2,0) -> Dynamic Study Modules | C16: =VLOOKUP(A16,URL[],3,0) -> 0 | D16: Colour | E16: Insufficient color contrast for states of user interface controls | F16: In main content area button text such as "Access Dynamic Study Modules" on focus has insufficnet color contrast Fg: #FFFFFF, Bg: #808080, 3.9:1 | G16: Applicable | I16: Applicable | P16: naveen.lagishetty | Q16: Delete | S16: No | T16: =IF(Final_Report[[#This Row],[Move to Report]]="Yes",VLOOKUP(E16,IssueVariable[],3,0),"N/A") -> N/A | U16: =IF(Final_Report[[#This Row],[Move to Report]]="Yes",VLOOKUP(E16,IssueVariable[],4,0),"N/A") -> N/A | V16: =Final_Report[[#This Row],[Issue Description]] -> N/A | X16: =Final_Report[[#This Row],[Code Snippet]] -> 0 | Y16: =IF(Final_Report[[#This Row],[Move to Report]]="Yes",VLOOKUP(E16,IssueVariable[],5,0),"N/A") -> N/A | Z16: =Final_Report[[#This Row],[Expected Result]] -> N/A | AA16: =IF(Final_Report[[#This Row],[Move to Report]]="Yes",VLOOKUP(E16,IssueVariable[],6,0),"N/A") -> N/A | AB16: =IF(Final_Report[[#This Row],[Move to Report]]="Yes",VLOOKUP(E16,IssueVariable[],7,0),"N/A") -> N/A | AC16: =Final_Report[[#This Row],[Recommendation]] -> N/A | AE16: =IF(Final_Report[[#This Row],[Move to Report]]="Yes",VLOOKUP(E16,IssueVariable[],8,0),"N/A") -> N/A | AF16: =Final_Report[[#This Row],[Steps to Reproduce]] -> N/A | AG16: =IF(Final_Report[[#This Row],[Move to Report]]="Yes",VLOOKUP(E16,IssueVariable[],9,0),"N/A") -> N/A | AH16: =IF(Final_Report[[#This Row],[Move to Report]]="Yes",VLOOKUP(E16,IssueVariable[],10,0),"N/A") -> N/A | AJ16: Major | AK16: {=Table95[Tested on]} -> Windows: 11 MAC OS: 12 iOS: 15 Android OS: 10 | AL16: {=_xlfn.TEXTJOIN(", ",TRUE,_xlfn.UNIQUE(TRIM(MID(SUBSTITUTE((Final_Report[[#This Row],[WCAG 2.1 Success Criteria]] &_xlfn.CONCAT(" (Level ") &Final_Report[[#This Row],[WCAG 2.1 Conformance Level]] &_xlfn.CONCAT("), ") &IF(Final_Report[[#This Row],[Chrome/JAWS]]="Applicable","Windows_11, Chrome, JAWS, ", " ") &IF(Final_Report[[#This Row],[FF/NVDA]]="Applicable", "Windows_11, Firefox, NVDA, ", " ") &IF(Final_Report[[#This Row],[Chrome/NVDA]]="Applicable", "Windows_11, Chrome, NVDA, ", " ") &IF(Final_Report[[#This Row],[iOS/VO]]="Applicable", "iOS Tablet, VoiceOver, ", " ") &IF(Final_Report[[#This Row],[Mac/Safari/VO]]="Applicable", "macOS_12, Safari, VoiceOver, ", " ") &IF(Final_Report[[#This Row],[Mac/Chrome/VO]]="Applicable", "macOS_12, Chrome, VoiceOver, ", " ") &IF(Final_Report[[#This Row],[Android/Talkback]]="Applicable", "TalkBack, Android Tablet", " ") ) &", " &IF(ISERROR(FIND("iOS 13",INDEX(Keyword[Component Keyword],MATCH(TRUE,INDEX((Keyword[Component Keyword]<>0),0),0)))=FALSE),INDEX(Keyword[Component Keyword],MATCH(TRUE,INDEX((Keyword[Component Keyword]<>0),0),0)),SUBSTITUTE(INDEX(Keyword[Component Keyword],MATCH(TRUE,INDEX((Keyword[Component Keyword]<>0),0),0)),"iOS 13","iOS")),",",REPT(" ",999)),(ROW($AAN$1:INDEX($AAX:$AAX,LEN((Final_Report[[#This Row],[WCAG 2.1 Success Criteria]] &_xlfn.CONCAT(" (Level ") &Final_Report[[#This Row],[WCAG 2.1 Conformance Level]] &_xlfn.CONCAT("), ") &IF(Final_Report[[#This Row],[Chrome/JAWS]]="Applicable","Windows_11, Chrome, JAWS, ", " ") &IF(Final_Report[[#This Row],[FF/NVDA]]="Applicable", "Windows_11, Firefox, NVDA, ", " ") &IF(Final_Report[[#This Row],[Chrome/NVDA]]="Applicable", "Windows_11, Chrome, NVDA, ", " ") &IF(Final_Report[[#This Row],[iOS/VO]]="Applicable", "iOS Tablet, VoiceOver, ", " ") &IF(Final_Report[[#This Row],[Mac/Safari/VO]]="Applicable", "macOS_12, Safari, VoiceOver, ", " ") &IF(Final_Report[[#This Row],[Mac/Chrome/VO]]="Applicable", "macOS_12, Chrome, VoiceOver, ", " ") &IF(Final_Report[[#This Row],[Android/Talkback]]="Applicable", "TalkBack, Android Tablet", " ") ) &", " &IF(ISERROR(FIND("iOS 13",INDEX(Keyword[Component Keyword],MATCH(TRUE,INDEX((Keyword[Component Keyword]<>0),0),0)))=FALSE),INDEX(Keyword[Component Keyword],MATCH(TRUE,INDEX((Keyword[Component Keyword]<>0),0),0)),SUBSTITUTE(INDEX(Keyword[Component Keyword],MATCH(TRUE,INDEX((Keyword[Component Keyword]<>0),0),0)),"iOS 13","iOS")))-LEN(SUBSTITUTE((Final_Report[[#This Row],[WCAG 2.1 Success Criteria]] &_xlfn.CONCAT(" (Level ") &Final_Report[[#This Row],[WCAG 2.1 Conformance Level]] &_xlfn.CONCAT("), ") &IF(Final_Report[[#This Row],[Chrome/JAWS]]="Applicable","Windows_11, Chrome, JAWS, ", " ") &IF(Final_Report[[#This Row],[FF/NVDA]]="Applicable", "Windows_11, Firefox, NVDA, ", " ") &IF(Final_Report[[#This Row],[Chrome/NVDA]]="Applicable", "Windows_11, Chrome, NVDA, ", " ") &IF(Final_Report[[#This Row],[iOS/VO]]="Applicable", "iOS Tablet, VoiceOver, ", " ") &IF(Final_Report[[#This Row],[Mac/Safari/VO]]="Applicable", "macOS_12, Safari, VoiceOver, ", " ") &IF(Final_Report[[#This Row],[Mac/Chrome/VO]]="Applicable", "macOS_12, Chrome, VoiceOver, ", " ") &IF(Final_Report[[#This Row],[Android/Talkback]]="Applicable", "TalkBack, Android Tablet", " ") ) &", " &IF(ISERROR(FIND("iOS 13",INDEX(Keyword[Component Keyword],MATCH(TRUE,INDEX((Keyword[Component Keyword]<>0),0),0)))=FALSE),INDEX(Keyword[Component Keyword],MATCH(TRUE,INDEX((Keyword[Component Keyword]<>0),0),0)),SUBSTITUTE(INDEX(Keyword[Component Keyword],MATCH(TRUE,INDEX((Keyword[Component Keyword]<>0),0),0)),"iOS 13","iOS")),",",""))+1))-1)*999+1,999))))} -> N/A (Level N/A), Windows_11, Chrome, JAWS, NVDA, Accessibility, Audit, Marketing, MLM-XL, MLVISION, MyLab, US, VPAT | AM16: {=CONCATENATE(LEFT(AH16, SEARCH(" ", AH16) -1),", ",Labels[Labels])} -> #VALUE! | AN16: =IF(AJ16="Blocker","1 - Critical - showstopper",IF(AJ16="Critical","1 - Critical - showstopper",IF(AJ16="Major","1 - Critical - showstopper",IF(AJ16="Minor","3 - Medium - minor functionality broken",IF(AJ16="Trivial","4 - Low - cosmetic or usability"))))) -> 1 - Critical - showstopper | AO16: naveen.lagishetty | BC16: =VLOOKUP('Final Report'!D16,'Issue Variable'!A:N,11,FALSE) -> #N/A
A17: P5 | B17: =VLOOKUP(A17,URL[],2,0) -> Dynamic Study Modules | C17: =VLOOKUP(A17,URL[],3,0) -> 0 | D17: Links | E17: Unclear link text | F17: In main content area button text such as "Access Dynamic Study Modules" on click it opens a new windo where Screen reader users it doesn't announce. Here visually hidden text "Opens a new window" required for sr users - Known issue - ACDS-225990 | G17: Applicable | H17: Applicable | I17: Applicable | P17: naveen.lagishetty | Q17: No QA Needed | S17: No | T17: =IF(Final_Report[[#This Row],[Move to Report]]="Yes",VLOOKUP(E17,IssueVariable[],3,0),"N/A") -> N/A | U17: =IF(Final_Report[[#This Row],[Move to Report]]="Yes",VLOOKUP(E17,IssueVariable[],4,0),"N/A") -> N/A | V17: =Final_Report[[#This Row],[Issue Description]] -> N/A | X17: =Final_Report[[#This Row],[Code Snippet]] -> 0 | Y17: =IF(Final_Report[[#This Row],[Move to Report]]="Yes",VLOOKUP(E17,IssueVariable[],5,0),"N/A") -> N/A | Z17: =Final_Report[[#This Row],[Expected Result]] -> N/A | AA17: =IF(Final_Report[[#This Row],[Move to Report]]="Yes",VLOOKUP(E17,IssueVariable[],6,0),"N/A") -> N/A | AB17: =IF(Final_Report[[#This Row],[Move to Report]]="Yes",VLOOKUP(E17,IssueVariable[],7,0),"N/A") -> N/A | AC17: =Final_Report[[#This Row],[Recommendation]] -> N/A | AE17: =IF(Final_Report[[#This Row],[Move to Report]]="Yes",VLOOKUP(E17,IssueVariable[],8,0),"N/A") -> N/A | AF17: =Final_Report[[#This Row],[Steps to Reproduce]] -> N/A | AG17: =IF(Final_Report[[#This Row],[Move to Report]]="Yes",VLOOKUP(E17,IssueVariable[],9,0),"N/A") -> N/A | AH17: =IF(Final_Report[[#This Row],[Move to Report]]="Yes",VLOOKUP(E17,IssueVariable[],10,0),"N/A") -> N/A | AK17: {=Table95[Tested on]} -> Windows: 11 MAC OS: 12 iOS: 15 Android OS: 10 | AL17: {=_xlfn.TEXTJOIN(", ",TRUE,_xlfn.UNIQUE(TRIM(MID(SUBSTITUTE((Final_Report[[#This Row],[WCAG 2.1 Success Criteria]] &_xlfn.CONCAT(" (Level ") &Final_Report[[#This Row],[WCAG 2.1 Conformance Level]] &_xlfn.CONCAT("), ") &IF(Final_Report[[#This Row],[Chrome/JAWS]]="Applicable","Windows_11, Chrome, JAWS, ", " ") &IF(Final_Report[[#This Row],[FF/NVDA]]="Applicable", "Windows_11, Firefox, NVDA, ", " ") &IF(Final_Report[[#This Row],[Chrome/NVDA]]="Applicable", "Windows_11, Chrome, NVDA, ", " ") &IF(Final_Report[[#This Row],[iOS/VO]]="Applicable", "iOS Tablet, VoiceOver, ", " ") &IF(Final_Report[[#This Row],[Mac/Safari/VO]]="Applicable", "macOS_12, Safari, VoiceOver, ", " ") &IF(Final_Report[[#This Row],[Mac/Chrome/VO]]="Applicable", "macOS_12, Chrome, VoiceOver, ", " ") &IF(Final_Report[[#This Row],[Android/Talkback]]="Applicable", "TalkBack, Android Tablet", " ") ) &", " &IF(ISERROR(FIND("iOS 13",INDEX(Keyword[Component Keyword],MATCH(TRUE,INDEX((Keyword[Component Keyword]<>0),0),0)))=FALSE),INDEX(Keyword[Component Keyword],MATCH(TRUE,INDEX((Keyword[Component Keyword]<>0),0),0)),SUBSTITUTE(INDEX(Keyword[Component Keyword],MATCH(TRUE,INDEX((Keyword[Component Keyword]<>0),0),0)),"iOS 13","iOS")),",",REPT(" ",999)),(ROW($AAN$1:INDEX($AAX:$AAX,LEN((Final_Report[[#This Row],[WCAG 2.1 Success Criteria]] &_xlfn.CONCAT(" (Level ") &Final_Report[[#This Row],[WCAG 2.1 Conformance Level]] &_xlfn.CONCAT("), ") &IF(Final_Report[[#This Row],[Chrome/JAWS]]="Applicable","Windows_11, Chrome, JAWS, ", " ") &IF(Final_Report[[#This Row],[FF/NVDA]]="Applicable", "Windows_11, Firefox, NVDA, ", " ") &IF(Final_Report[[#This Row],[Chrome/NVDA]]="Applicable", "Windows_11, Chrome, NVDA, ", " ") &IF(Final_Report[[#This Row],[iOS/VO]]="Applicable", "iOS Tablet, VoiceOver, ", " ") &IF(Final_Report[[#This Row],[Mac/Safari/VO]]="Applicable", "macOS_12, Safari, VoiceOver, ", " ") &IF(Final_Report[[#This Row],[Mac/Chrome/VO]]="Applicable", "macOS_12, Chrome, VoiceOver, ", " ") &IF(Final_Report[[#This Row],[Android/Talkback]]="Applicable", "TalkBack, Android Tablet", " ") ) &", " &IF(ISERROR(FIND("iOS 13",INDEX(Keyword[Component Keyword],MATCH(TRUE,INDEX((Keyword[Component Keyword]<>0),0),0)))=FALSE),INDEX(Keyword[Component Keyword],MATCH(TRUE,INDEX((Keyword[Component Keyword]<>0),0),0)),SUBSTITUTE(INDEX(Keyword[Component Keyword],MATCH(TRUE,INDEX((Keyword[Component Keyword]<>0),0),0)),"iOS 13","iOS")))-LEN(SUBSTITUTE((Final_Report[[#This Row],[WCAG 2.1 Success Criteria]] &_xlfn.CONCAT(" (Level ") &Final_Report[[#This Row],[WCAG 2.1 Conformance Level]] &_xlfn.CONCAT("), ") &IF(Final_Report[[#This Row],[Chrome/JAWS]]="Applicable","Windows_11, Chrome, JAWS, ", " ") &IF(Final_Report[[#This Row],[FF/NVDA]]="Applicable", "Windows_11, Firefox, NVDA, ", " ") &IF(Final_Report[[#This Row],[Chrome/NVDA]]="Applicable", "Windows_11, Chrome, NVDA, ", " ") &IF(Final_Report[[#This Row],[iOS/VO]]="Applicable", "iOS Tablet, VoiceOver, ", " ") &IF(Final_Report[[#This Row],[Mac/Safari/VO]]="Applicable", "macOS_12, Safari, VoiceOver, ", " ") &IF(Final_Report[[#This Row],[Mac/Chrome/VO]]="Applicable", "macOS_12, Chrome, VoiceOver, ", " ") &IF(Final_Report[[#This Row],[Android/Talkback]]="Applicable", "TalkBack, Android Tablet", " ") ) &", " &IF(ISERROR(FIND("iOS 13",INDEX(Keyword[Component Keyword],MATCH(TRUE,INDEX((Keyword[Component Keyword]<>0),0),0)))=FALSE),INDEX(Keyword[Component Keyword],MATCH(TRUE,INDEX((Keyword[Component Keyword]<>0),0),0)),SUBSTITUTE(INDEX(Keyword[Component Keyword],MATCH(TRUE,INDEX((Keyword[Component Keyword]<>0),0),0)),"iOS 13","iOS")),",",""))+1))-1)*999+1,999))))} -> N/A (Level N/A), Windows_11, Chrome, JAWS, Firefox, NVDA, Accessibility, Audit, Marketing, MLM-XL, MLVISION, MyLab, US, VPAT | AM17: {=CONCATENATE(LEFT(AH17, SEARCH(" ", AH17) -1),", ",Labels[Labels])} -> #VALUE! | AN17: =IF(AJ17="Blocker","1 - Critical - showstopper",IF(AJ17="Critical","1 - Critical - showstopper",IF(AJ17="Major","1 - Critical - showstopper",IF(AJ17="Minor","3 - Medium - minor functionality broken",IF(AJ17="Trivial","4 - Low - cosmetic or usability"))))) -> FALSE | AR17: Known issue - ACDS-225990 | BC17: =VLOOKUP('Final Report'!D17,'Issue Variable'!A:N,11,FALSE) -> #N/A
A18: P6 | B18: =VLOOKUP(A18,URL[],2,0) -> Multimedia Library Mainpage | C18: =VLOOKUP(A18,URL[],3,0) -> 0 | D18: Headings | E18: Identical heading text | F18: Identical heading text "Multimedia Library" found - Known issue - ACDS-264290 | G18: Applicable | H18: Applicable | I18: Applicable | P18: naveen.lagishetty | Q18: No QA Needed | S18: No | T18: =IF(Final_Report[[#This Row],[Move to Report]]="Yes",VLOOKUP(E18,IssueVariable[],3,0),"N/A") -> N/A | U18: =IF(Final_Report[[#This Row],[Move to Report]]="Yes",VLOOKUP(E18,IssueVariable[],4,0),"N/A") -> N/A | V18: =Final_Report[[#This Row],[Issue Description]] -> N/A | X18: =Final_Report[[#This Row],[Code Snippet]] -> 0 | Y18: =IF(Final_Report[[#This Row],[Move to Report]]="Yes",VLOOKUP(E18,IssueVariable[],5,0),"N/A") -> N/A | Z18: =Final_Report[[#This Row],[Expected Result]] -> N/A | AA18: =IF(Final_Report[[#This Row],[Move to Report]]="Yes",VLOOKUP(E18,IssueVariable[],6,0),"N/A") -> N/A | AB18: =IF(Final_Report[[#This Row],[Move to Report]]="Yes",VLOOKUP(E18,IssueVariable[],7,0),"N/A") -> N/A | AC18: =Final_Report[[#This Row],[Recommendation]] -> N/A | AE18: =IF(Final_Report[[#This Row],[Move to Report]]="Yes",VLOOKUP(E18,IssueVariable[],8,0),"N/A") -> N/A | AF18: =Final_Report[[#This Row],[Steps to Reproduce]] -> N/A | AG18: =IF(Final_Report[[#This Row],[Move to Report]]="Yes",VLOOKUP(E18,IssueVariable[],9,0),"N/A") -> N/A | AH18: =IF(Final_Report[[#This Row],[Move to Report]]="Yes",VLOOKUP(E18,IssueVariable[],10,0),"N/A") -> N/A | AK18: {=Table95[Tested on]} -> Windows: 11 MAC OS: 12 iOS: 15 Android OS: 10 | AL18: {=_xlfn.TEXTJOIN(", ",TRUE,_xlfn.UNIQUE(TRIM(MID(SUBSTITUTE((Final_Report[[#This Row],[WCAG 2.1 Success Criteria]] &_xlfn.CONCAT(" (Level ") &Final_Report[[#This Row],[WCAG 2.1 Conformance Level]] &_xlfn.CONCAT("), ") &IF(Final_Report[[#This Row],[Chrome/JAWS]]="Applicable","Windows_11, Chrome, JAWS, ", " ") &IF(Final_Report[[#This Row],[FF/NVDA]]="Applicable", "Windows_11, Firefox, NVDA, ", " ") &IF(Final_Report[[#This Row],[Chrome/NVDA]]="Applicable", "Windows_11, Chrome, NVDA, ", " ") &IF(Final_Report[[#This Row],[iOS/VO]]="Applicable", "iOS Tablet, VoiceOver, ", " ") &IF(Final_Report[[#This Row],[Mac/Safari/VO]]="Applicable", "macOS_12, Safari, VoiceOver, ", " ") &IF(Final_Report[[#This Row],[Mac/Chrome/VO]]="Applicable", "macOS_12, Chrome, VoiceOver, ", " ") &IF(Final_Report[[#This Row],[Android/Talkback]]="Applicable", "TalkBack, Android Tablet", " ") ) &", " &IF(ISERROR(FIND("iOS 13",INDEX(Keyword[Component Keyword],MATCH(TRUE,INDEX((Keyword[Component Keyword]<>0),0),0)))=FALSE),INDEX(Keyword[Component Keyword],MATCH(TRUE,INDEX((Keyword[Component Keyword]<>0),0),0)),SUBSTITUTE(INDEX(Keyword[Component Keyword],MATCH(TRUE,INDEX((Keyword[Component Keyword]<>0),0),0)),"iOS 13","iOS")),",",REPT(" ",999)),(ROW($AAN$1:INDEX($AAX:$AAX,LEN((Final_Report[[#This Row],[WCAG 2.1 Success Criteria]] &_xlfn.CONCAT(" (Level ") &Final_Report[[#This Row],[WCAG 2.1 Conformance Level]] &_xlfn.CONCAT("), ") &IF(Final_Report[[#This Row],[Chrome/JAWS]]="Applicable","Windows_11, Chrome, JAWS, ", " ") &IF(Final_Report[[#This Row],[FF/NVDA]]="Applicable", "Windows_11, Firefox, NVDA, ", " ") &IF(Final_Report[[#This Row],[Chrome/NVDA]]="Applicable", "Windows_11, Chrome, NVDA, ", " ") &IF(Final_Report[[#This Row],[iOS/VO]]="Applicable", "iOS Tablet, VoiceOver, ", " ") &IF(Final_Report[[#This Row],[Mac/Safari/VO]]="Applicable", "macOS_12, Safari, VoiceOver, ", " ") &IF(Final_Report[[#This Row],[Mac/Chrome/VO]]="Applicable", "macOS_12, Chrome, VoiceOver, ", " ") &IF(Final_Report[[#This Row],[Android/Talkback]]="Applicable", "TalkBack, Android Tablet", " ") ) &", " &IF(ISERROR(FIND("iOS 13",INDEX(Keyword[Component Keyword],MATCH(TRUE,INDEX((Keyword[Component Keyword]<>0),0),0)))=FALSE),INDEX(Keyword[Component Keyword],MATCH(TRUE,INDEX((Keyword[Component Keyword]<>0),0),0)),SUBSTITUTE(INDEX(Keyword[Component Keyword],MATCH(TRUE,INDEX((Keyword[Component Keyword]<>0),0),0)),"iOS 13","iOS")))-LEN(SUBSTITUTE((Final_Report[[#This Row],[WCAG 2.1 Success Criteria]] &_xlfn.CONCAT(" (Level ") &Final_Report[[#This Row],[WCAG 2.1 Conformance Level]] &_xlfn.CONCAT("), ") &IF(Final_Report[[#This Row],[Chrome/JAWS]]="Applicable","Windows_11, Chrome, JAWS, ", " ") &IF(Final_Report[[#This Row],[FF/NVDA]]="Applicable", "Windows_11, Firefox, NVDA, ", " ") &IF(Final_Report[[#This Row],[Chrome/NVDA]]="Applicable", "Windows_11, Chrome, NVDA, ", " ") &IF(Final_Report[[#This Row],[iOS/VO]]="Applicable", "iOS Tablet, VoiceOver, ", " ") &IF(Final_Report[[#This Row],[Mac/Safari/VO]]="Applicable", "macOS_12, Safari, VoiceOver, ", " ") &IF(Final_Report[[#This Row],[Mac/Chrome/VO]]="Applicable", "macOS_12, Chrome, VoiceOver, ", " ") &IF(Final_Report[[#This Row],[Android/Talkback]]="Applicable", "TalkBack, Android Tablet", " ") ) &", " &IF(ISERROR(FIND("iOS 13",INDEX(Keyword[Component Keyword],MATCH(TRUE,INDEX((Keyword[Component Keyword]<>0),0),0)))=FALSE),INDEX(Keyword[Component Keyword],MATCH(TRUE,INDEX((Keyword[Component Keyword]<>0),0),0)),SUBSTITUTE(INDEX(Keyword[Component Keyword],MATCH(TRUE,INDEX((Keyword[Component Keyword]<>0),0),0)),"iOS 13","iOS")),",",""))+1))-1)*999+1,999))))} -> N/A (Level N/A), Windows_11, Chrome, JAWS, Firefox, NVDA, Accessibility, Audit, Marketing, MLM-XL, MLVISION, MyLab, US, VPAT | AM18: {=CONCATENATE(LEFT(AH18, SEARCH(" ", AH18) -1),", ",Labels[Labels])} -> #VALUE! | AN18: =IF(AJ18="Blocker","1 - Critical - showstopper",IF(AJ18="Critical","1 - Critical - showstopper",IF(AJ18="Major","1 - Critical - showstopper",IF(AJ18="Minor","3 - Medium - minor functionality broken",IF(AJ18="Trivial","4 - Low - cosmetic or usability"))))) -> FALSE | AR18: Known issue - ACDS-264290 | BC18: =VLOOKUP('Final Report'!D18,'Issue Variable'!A:N,11,FALSE) -> #N/A
A19: P6 | B19: =VLOOKUP(A19,URL[],2,0) -> Multimedia Library Mainpage | C19: =VLOOKUP(A19,URL[],3,0) -> 0 | D19: Headings | E19: Missing heading mark -up | F19: Missing heading markup text such as "Kotler/Armstrong/Balasubramanian, Principles of Marketing, 19e" in main content area | G19: Applicable | H19: Applicable | I19: Applicable | P19: naveen.lagishetty | Q19: delete | S19: No | T19: =IF(Final_Report[[#This Row],[Move to Report]]="Yes",VLOOKUP(E19,IssueVariable[],3,0),"N/A") -> N/A | U19: =IF(Final_Report[[#This Row],[Move to Report]]="Yes",VLOOKUP(E19,IssueVariable[],4,0),"N/A") -> N/A | V19: =Final_Report[[#This Row],[Issue Description]] -> N/A | X19: =Final_Report[[#This Row],[Code Snippet]] -> 0 | Y19: =IF(Final_Report[[#This Row],[Move to Report]]="Yes",VLOOKUP(E19,IssueVariable[],5,0),"N/A") -> N/A | Z19: =Final_Report[[#This Row],[Expected Result]] -> N/A | AA19: =IF(Final_Report[[#This Row],[Move to Report]]="Yes",VLOOKUP(E19,IssueVariable[],6,0),"N/A") -> N/A | AB19: =IF(Final_Report[[#This Row],[Move to Report]]="Yes",VLOOKUP(E19,IssueVariable[],7,0),"N/A") -> N/A | AC19: =Final_Report[[#This Row],[Recommendation]] -> N/A | AE19: =IF(Final_Report[[#This Row],[Move to Report]]="Yes",VLOOKUP(E19,IssueVariable[],8,0),"N/A") -> N/A | AF19: =Final_Report[[#This Row],[Steps to Reproduce]] -> N/A | AG19: =IF(Final_Report[[#This Row],[Move to Report]]="Yes",VLOOKUP(E19,IssueVariable[],9,0),"N/A") -> N/A | AH19: =IF(Final_Report[[#This Row],[Move to Report]]="Yes",VLOOKUP(E19,IssueVariable[],10,0),"N/A") -> N/A | AK19: {=Table95[Tested on]} -> Windows: 11 MAC OS: 12 iOS: 15 Android OS: 10 | AL19: {=_xlfn.TEXTJOIN(", ",TRUE,_xlfn.UNIQUE(TRIM(MID(SUBSTITUTE((Final_Report[[#This Row],[WCAG 2.1 Success Criteria]] &_xlfn.CONCAT(" (Level ") &Final_Report[[#This Row],[WCAG 2.1 Conformance Level]] &_xlfn.CONCAT("), ") &IF(Final_Report[[#This Row],[Chrome/JAWS]]="Applicable","Windows_11, Chrome, JAWS, ", " ") &IF(Final_Report[[#This Row],[FF/NVDA]]="Applicable", "Windows_11, Firefox, NVDA, ", " ") &IF(Final_Report[[#This Row],[Chrome/NVDA]]="Applicable", "Windows_11, Chrome, NVDA, ", " ") &IF(Final_Report[[#This Row],[iOS/VO]]="Applicable", "iOS Tablet, VoiceOver, ", " ") &IF(Final_Report[[#This Row],[Mac/Safari/VO]]="Applicable", "macOS_12, Safari, VoiceOver, ", " ") &IF(Final_Report[[#This Row],[Mac/Chrome/VO]]="Applicable", "macOS_12, Chrome, VoiceOver, ", " ") &IF(Final_Report[[#This Row],[Android/Talkback]]="Applicable", "TalkBack, Android Tablet", " ") ) &", " &IF(ISERROR(FIND("iOS 13",INDEX(Keyword[Component Keyword],MATCH(TRUE,INDEX((Keyword[Component Keyword]<>0),0),0)))=FALSE),INDEX(Keyword[Component Keyword],MATCH(TRUE,INDEX((Keyword[Component Keyword]<>0),0),0)),SUBSTITUTE(INDEX(Keyword[Component Keyword],MATCH(TRUE,INDEX((Keyword[Component Keyword]<>0),0),0)),"iOS 13","iOS")),",",REPT(" ",999)),(ROW($AAN$1:INDEX($AAX:$AAX,LEN((Final_Report[[#This Row],[WCAG 2.1 Success Criteria]] &_xlfn.CONCAT(" (Level ") &Final_Report[[#This Row],[WCAG 2.1 Conformance Level]] &_xlfn.CONCAT("), ") &IF(Final_Report[[#This Row],[Chrome/JAWS]]="Applicable","Windows_11, Chrome, JAWS, ", " ") &IF(Final_Report[[#This Row],[FF/NVDA]]="Applicable", "Windows_11, Firefox, NVDA, ", " ") &IF(Final_Report[[#This Row],[Chrome/NVDA]]="Applicable", "Windows_11, Chrome, NVDA, ", " ") &IF(Final_Report[[#This Row],[iOS/VO]]="Applicable", "iOS Tablet, VoiceOver, ", " ") &IF(Final_Report[[#This Row],[Mac/Safari/VO]]="Applicable", "macOS_12, Safari, VoiceOver, ", " ") &IF(Final_Report[[#This Row],[Mac/Chrome/VO]]="Applicable", "macOS_12, Chrome, VoiceOver, ", " ") &IF(Final_Report[[#This Row],[Android/Talkback]]="Applicable", "TalkBack, Android Tablet", " ") ) &", " &IF(ISERROR(FIND("iOS 13",INDEX(Keyword[Component Keyword],MATCH(TRUE,INDEX((Keyword[Component Keyword]<>0),0),0)))=FALSE),INDEX(Keyword[Component Keyword],MATCH(TRUE,INDEX((Keyword[Component Keyword]<>0),0),0)),SUBSTITUTE(INDEX(Keyword[Component Keyword],MATCH(TRUE,INDEX((Keyword[Component Keyword]<>0),0),0)),"iOS 13","iOS")))-LEN(SUBSTITUTE((Final_Report[[#This Row],[WCAG 2.1 Success Criteria]] &_xlfn.CONCAT(" (Level ") &Final_Report[[#This Row],[WCAG 2.1 Conformance Level]] &_xlfn.CONCAT("), ") &IF(Final_Report[[#This Row],[Chrome/JAWS]]="Applicable","Windows_11, Chrome, JAWS, ", " ") &IF(Final_Report[[#This Row],[FF/NVDA]]="Applicable", "Windows_11, Firefox, NVDA, ", " ") &IF(Final_Report[[#This Row],[Chrome/NVDA]]="Applicable", "Windows_11, Chrome, NVDA, ", " ") &IF(Final_Report[[#This Row],[iOS/VO]]="Applicable", "iOS Tablet, VoiceOver, ", " ") &IF(Final_Report[[#This Row],[Mac/Safari/VO]]="Applicable", "macOS_12, Safari, VoiceOver, ", " ") &IF(Final_Report[[#This Row],[Mac/Chrome/VO]]="Applicable", "macOS_12, Chrome, VoiceOver, ", " ") &IF(Final_Report[[#This Row],[Android/Talkback]]="Applicable", "TalkBack, Android Tablet", " ") ) &", " &IF(ISERROR(FIND("iOS 13",INDEX(Keyword[Component Keyword],MATCH(TRUE,INDEX((Keyword[Component Keyword]<>0),0),0)))=FALSE),INDEX(Keyword[Component Keyword],MATCH(TRUE,INDEX((Keyword[Component Keyword]<>0),0),0)),SUBSTITUTE(INDEX(Keyword[Component Keyword],MATCH(TRUE,INDEX((Keyword[Component Keyword]<>0),0),0)),"iOS 13","iOS")),",",""))+1))-1)*999+1,999))))} -> N/A (Level N/A), Windows_11, Chrome, JAWS, Firefox, NVDA, Accessibility, Audit, Marketing, MLM-XL, MLVISION, MyLab, US, VPAT | AM19: {=CONCATENATE(LEFT(AH19, SEARCH(" ", AH19) -1),", ",Labels[Labels])} -> #VALUE! | AN19: =IF(AJ19="Blocker","1 - Critical - showstopper",IF(AJ19="Critical","1 - Critical - showstopper",IF(AJ19="Major","1 - Critical - showstopper",IF(AJ19="Minor","3 - Medium - minor functionality broken",IF(AJ19="Trivial","4 - Low - cosmetic or usability"))))) -> FALSE | BC19: =VLOOKUP('Final Report'!D19,'Issue Variable'!A:N,11,FALSE) -> #N/A
A20: P6 | B20: =VLOOKUP(A20,URL[],2,0) -> Multimedia Library Mainpage | C20: =VLOOKUP(A20,URL[],3,0) -> 0 | D20: Images | E20: Missing textual description for informative image | F20: In main content area after text "Kotler/Armstrong/Balasubramanian, Principles of Marketing, 19e" elment there is an image has missing textual description | G20: Applicable | H20: Applicable | I20: Applicable | P20: naveen.lagishetty | Q20: delete | S20: No | T20: =IF(Final_Report[[#This Row],[Move to Report]]="Yes",VLOOKUP(E20,IssueVariable[],3,0),"N/A") -> N/A | U20: =IF(Final_Report[[#This Row],[Move to Report]]="Yes",VLOOKUP(E20,IssueVariable[],4,0),"N/A") -> N/A | V20: =Final_Report[[#This Row],[Issue Description]] -> N/A | X20: =Final_Report[[#This Row],[Code Snippet]] -> 0 | Y20: =IF(Final_Report[[#This Row],[Move to Report]]="Yes",VLOOKUP(E20,IssueVariable[],5,0),"N/A") -> N/A | Z20: =Final_Report[[#This Row],[Expected Result]] -> N/A | AA20: =IF(Final_Report[[#This Row],[Move to Report]]="Yes",VLOOKUP(E20,IssueVariable[],6,0),"N/A") -> N/A | AB20: =IF(Final_Report[[#This Row],[Move to Report]]="Yes",VLOOKUP(E20,IssueVariable[],7,0),"N/A") -> N/A | AC20: =Final_Report[[#This Row],[Recommendation]] -> N/A | AE20: =IF(Final_Report[[#This Row],[Move to Report]]="Yes",VLOOKUP(E20,IssueVariable[],8,0),"N/A") -> N/A | AF20: =Final_Report[[#This Row],[Steps to Reproduce]] -> N/A | AG20: =IF(Final_Report[[#This Row],[Move to Report]]="Yes",VLOOKUP(E20,IssueVariable[],9,0),"N/A") -> N/A | AH20: =IF(Final_Report[[#This Row],[Move to Report]]="Yes",VLOOKUP(E20,IssueVariable[],10,0),"N/A") -> N/A | AK20: {=Table95[Tested on]} -> Windows: 11 MAC OS: 12 iOS: 15 Android OS: 10 | AL20: {=_xlfn.TEXTJOIN(", ",TRUE,_xlfn.UNIQUE(TRIM(MID(SUBSTITUTE((Final_Report[[#This Row],[WCAG 2.1 Success Criteria]] &_xlfn.CONCAT(" (Level ") &Final_Report[[#This Row],[WCAG 2.1 Conformance Level]] &_xlfn.CONCAT("), ") &IF(Final_Report[[#This Row],[Chrome/JAWS]]="Applicable","Windows_11, Chrome, JAWS, ", " ") &IF(Final_Report[[#This Row],[FF/NVDA]]="Applicable", "Windows_11, Firefox, NVDA, ", " ") &IF(Final_Report[[#This Row],[Chrome/NVDA]]="Applicable", "Windows_11, Chrome, NVDA, ", " ") &IF(Final_Report[[#This Row],[iOS/VO]]="Applicable", "iOS Tablet, VoiceOver, ", " ") &IF(Final_Report[[#This Row],[Mac/Safari/VO]]="Applicable", "macOS_12, Safari, VoiceOver, ", " ") &IF(Final_Report[[#This Row],[Mac/Chrome/VO]]="Applicable", "macOS_12, Chrome, VoiceOver, ", " ") &IF(Final_Report[[#This Row],[Android/Talkback]]="Applicable", "TalkBack, Android Tablet", " ") ) &", " &IF(ISERROR(FIND("iOS 13",INDEX(Keyword[Component Keyword],MATCH(TRUE,INDEX((Keyword[Component Keyword]<>0),0),0)))=FALSE),INDEX(Keyword[Component Keyword],MATCH(TRUE,INDEX((Keyword[Component Keyword]<>0),0),0)),SUBSTITUTE(INDEX(Keyword[Component Keyword],MATCH(TRUE,INDEX((Keyword[Component Keyword]<>0),0),0)),"iOS 13","iOS")),",",REPT(" ",999)),(ROW($AAN$1:INDEX($AAX:$AAX,LEN((Final_Report[[#This Row],[WCAG 2.1 Success Criteria]] &_xlfn.CONCAT(" (Level ") &Final_Report[[#This Row],[WCAG 2.1 Conformance Level]] &_xlfn.CONCAT("), ") &IF(Final_Report[[#This Row],[Chrome/JAWS]]="Applicable","Windows_11, Chrome, JAWS, ", " ") &IF(Final_Report[[#This Row],[FF/NVDA]]="Applicable", "Windows_11, Firefox, NVDA, ", " ") &IF(Final_Report[[#This Row],[Chrome/NVDA]]="Applicable", "Windows_11, Chrome, NVDA, ", " ") &IF(Final_Report[[#This Row],[iOS/VO]]="Applicable", "iOS Tablet, VoiceOver, ", " ") &IF(Final_Report[[#This Row],[Mac/Safari/VO]]="Applicable", "macOS_12, Safari, VoiceOver, ", " ") &IF(Final_Report[[#This Row],[Mac/Chrome/VO]]="Applicable", "macOS_12, Chrome, VoiceOver, ", " ") &IF(Final_Report[[#This Row],[Android/Talkback]]="Applicable", "TalkBack, Android Tablet", " ") ) &", " &IF(ISERROR(FIND("iOS 13",INDEX(Keyword[Component Keyword],MATCH(TRUE,INDEX((Keyword[Component Keyword]<>0),0),0)))=FALSE),INDEX(Keyword[Component Keyword],MATCH(TRUE,INDEX((Keyword[Component Keyword]<>0),0),0)),SUBSTITUTE(INDEX(Keyword[Component Keyword],MATCH(TRUE,INDEX((Keyword[Component Keyword]<>0),0),0)),"iOS 13","iOS")))-LEN(SUBSTITUTE((Final_Report[[#This Row],[WCAG 2.1 Success Criteria]] &_xlfn.CONCAT(" (Level ") &Final_Report[[#This Row],[WCAG 2.1 Conformance Level]] &_xlfn.CONCAT("), ") &IF(Final_Report[[#This Row],[Chrome/JAWS]]="Applicable","Windows_11, Chrome, JAWS, ", " ") &IF(Final_Report[[#This Row],[FF/NVDA]]="Applicable", "Windows_11, Firefox, NVDA, ", " ") &IF(Final_Report[[#This Row],[Chrome/NVDA]]="Applicable", "Windows_11, Chrome, NVDA, ", " ") &IF(Final_Report[[#This Row],[iOS/VO]]="Applicable", "iOS Tablet, VoiceOver, ", " ") &IF(Final_Report[[#This Row],[Mac/Safari/VO]]="Applicable", "macOS_12, Safari, VoiceOver, ", " ") &IF(Final_Report[[#This Row],[Mac/Chrome/VO]]="Applicable", "macOS_12, Chrome, VoiceOver, ", " ") &IF(Final_Report[[#This Row],[Android/Talkback]]="Applicable", "TalkBack, Android Tablet", " ") ) &", " &IF(ISERROR(FIND("iOS 13",INDEX(Keyword[Component Keyword],MATCH(TRUE,INDEX((Keyword[Component Keyword]<>0),0),0)))=FALSE),INDEX(Keyword[Component Keyword],MATCH(TRUE,INDEX((Keyword[Component Keyword]<>0),0),0)),SUBSTITUTE(INDEX(Keyword[Component Keyword],MATCH(TRUE,INDEX((Keyword[Component Keyword]<>0),0),0)),"iOS 13","iOS")),",",""))+1))-1)*999+1,999))))} -> N/A (Level N/A), Windows_11, Chrome, JAWS, Firefox, NVDA, Accessibility, Audit, Marketing, MLM-XL, MLVISION, MyLab, US, VPAT | AM20: {=CONCATENATE(LEFT(AH20, SEARCH(" ", AH20) -1),", ",Labels[Labels])} -> #VALUE! | AN20: =IF(AJ20="Blocker","1 - Critical - showstopper",IF(AJ20="Critical","1 - Critical - showstopper",IF(AJ20="Major","1 - Critical - showstopper",IF(AJ20="Minor","3 - Medium - minor functionality broken",IF(AJ20="Trivial","4 - Low - cosmetic or usability"))))) -> FALSE | BC20: =VLOOKUP('Final Report'!D20,'Issue Variable'!A:N,11,FALSE) -> #N/A
A21: P6 | B21: =VLOOKUP(A21,URL[],2,0) -> Multimedia Library Mainpage | C21: =VLOOKUP(A21,URL[],3,0) -> 0 | D21: Forms | E21: Feedback message difficult to locate | F21: In main content area wher sr user ("Find Now") submit the form without inputs visually result text "The Multimedia Library resources are not yet available for this course." appeared where sr focus is not taking. - Known issue - ACDS-265730 | G21: Applicable | H21: Applicable | I21: Applicable | P21: naveen.lagishetty | Q21: No QA Needed | S21: No | T21: Web: Multimedia Library Mainpage: Error messages difficult to locate | U21: The feedback message is difficult to locate. For example, when user activate "Find Now" button in the main content area, the feedback message "The Multimedia Library resources are not yet available for this course." gets displayed dynamically on the page which is not announced by the screen reader, as a result, screen reader users are unaware about the occurrence of the feedback message. | V21: =Final_Report[[#This Row],[Issue Description]] -> The feedback message is difficult to locate. For example, when user activate "Find Now" button in the main content area, the feedback message "The Multimedia Library resources are not yet available for this course." gets displayed dynamically on the page which is not announced by the screen reader, as a result, screen reader users are unaware about the occurrence of the feedback message. | X21: =Final_Report[[#This Row],[Code Snippet]] -> 0 | Y21: =IF(Final_Report[[#This Row],[Move to Report]]="Yes",VLOOKUP(E21,IssueVariable[],5,0),"N/A") -> N/A | Z21: =Final_Report[[#This Row],[Expected Result]] -> N/A | AA21: =IF(Final_Report[[#This Row],[Move to Report]]="Yes",VLOOKUP(E21,IssueVariable[],6,0),"N/A") -> N/A | AB21: Apply the following changes: • USe role alert and aria-atomic = "true" for the <div> element containing feedback messages. • Use CSS display: none property to hide the feedback message when not visible on the page, make sure that it changes to display: block when feedback messages are visible on the page. • For more information on how to implement this can be found at: https://www.w3.org/WAI/ARIA/apg/example-index/alert/alert.html | AC21: =Final_Report[[#This Row],[Recommendation]] -> Apply the following changes: • USe role alert and aria-atomic = "true" for the <div> element containing feedback messages. • Use CSS display: none property to hide the feedback message when not visible on the page, make sure that it changes to display: block when feedback messages are visible on the page. • For more information on how to implement this can be found at: https://www.w3.org/WAI/ARIA/apg/example-index/alert/alert.html | AE21: =IF(Final_Report[[#This Row],[Move to Report]]="Yes",VLOOKUP(E21,IssueVariable[],8,0),"N/A") -> N/A | AF21: =Final_Report[[#This Row],[Steps to Reproduce]] -> N/A | AG21: =IF(Final_Report[[#This Row],[Move to Report]]="Yes",VLOOKUP(E21,IssueVariable[],9,0),"N/A") -> N/A | AH21: =IF(Final_Report[[#This Row],[Move to Report]]="Yes",VLOOKUP(E21,IssueVariable[],10,0),"N/A") -> N/A | AJ21: Minor | AK21: {=Table95[Tested on]} -> Windows: 11 MAC OS: 12 iOS: 15 Android OS: 10 | AL21: {=_xlfn.TEXTJOIN(", ",TRUE,_xlfn.UNIQUE(TRIM(MID(SUBSTITUTE((Final_Report[[#This Row],[WCAG 2.1 Success Criteria]] &_xlfn.CONCAT(" (Level ") &Final_Report[[#This Row],[WCAG 2.1 Conformance Level]] &_xlfn.CONCAT("), ") &IF(Final_Report[[#This Row],[Chrome/JAWS]]="Applicable","Windows_11, Chrome, JAWS, ", " ") &IF(Final_Report[[#This Row],[FF/NVDA]]="Applicable", "Windows_11, Firefox, NVDA, ", " ") &IF(Final_Report[[#This Row],[Chrome/NVDA]]="Applicable", "Windows_11, Chrome, NVDA, ", " ") &IF(Final_Report[[#This Row],[iOS/VO]]="Applicable", "iOS Tablet, VoiceOver, ", " ") &IF(Final_Report[[#This Row],[Mac/Safari/VO]]="Applicable", "macOS_12, Safari, VoiceOver, ", " ") &IF(Final_Report[[#This Row],[Mac/Chrome/VO]]="Applicable", "macOS_12, Chrome, VoiceOver, ", " ") &IF(Final_Report[[#This Row],[Android/Talkback]]="Applicable", "TalkBack, Android Tablet", " ") ) &", " &IF(ISERROR(FIND("iOS 13",INDEX(Keyword[Component Keyword],MATCH(TRUE,INDEX((Keyword[Component Keyword]<>0),0),0)))=FALSE),INDEX(Keyword[Component Keyword],MATCH(TRUE,INDEX((Keyword[Component Keyword]<>0),0),0)),SUBSTITUTE(INDEX(Keyword[Component Keyword],MATCH(TRUE,INDEX((Keyword[Component Keyword]<>0),0),0)),"iOS 13","iOS")),",",REPT(" ",999)),(ROW($AAN$1:INDEX($AAX:$AAX,LEN((Final_Report[[#This Row],[WCAG 2.1 Success Criteria]] &_xlfn.CONCAT(" (Level ") &Final_Report[[#This Row],[WCAG 2.1 Conformance Level]] &_xlfn.CONCAT("), ") &IF(Final_Report[[#This Row],[Chrome/JAWS]]="Applicable","Windows_11, Chrome, JAWS, ", " ") &IF(Final_Report[[#This Row],[FF/NVDA]]="Applicable", "Windows_11, Firefox, NVDA, ", " ") &IF(Final_Report[[#This Row],[Chrome/NVDA]]="Applicable", "Windows_11, Chrome, NVDA, ", " ") &IF(Final_Report[[#This Row],[iOS/VO]]="Applicable", "iOS Tablet, VoiceOver, ", " ") &IF(Final_Report[[#This Row],[Mac/Safari/VO]]="Applicable", "macOS_12, Safari, VoiceOver, ", " ") &IF(Final_Report[[#This Row],[Mac/Chrome/VO]]="Applicable", "macOS_12, Chrome, VoiceOver, ", " ") &IF(Final_Report[[#This Row],[Android/Talkback]]="Applicable", "TalkBack, Android Tablet", " ") ) &", " &IF(ISERROR(FIND("iOS 13",INDEX(Keyword[Component Keyword],MATCH(TRUE,INDEX((Keyword[Component Keyword]<>0),0),0)))=FALSE),INDEX(Keyword[Component Keyword],MATCH(TRUE,INDEX((Keyword[Component Keyword]<>0),0),0)),SUBSTITUTE(INDEX(Keyword[Component Keyword],MATCH(TRUE,INDEX((Keyword[Component Keyword]<>0),0),0)),"iOS 13","iOS")))-LEN(SUBSTITUTE((Final_Report[[#This Row],[WCAG 2.1 Success Criteria]] &_xlfn.CONCAT(" (Level ") &Final_Report[[#This Row],[WCAG 2.1 Conformance Level]] &_xlfn.CONCAT("), ") &IF(Final_Report[[#This Row],[Chrome/JAWS]]="Applicable","Windows_11, Chrome, JAWS, ", " ") &IF(Final_Report[[#This Row],[FF/NVDA]]="Applicable", "Windows_11, Firefox, NVDA, ", " ") &IF(Final_Report[[#This Row],[Chrome/NVDA]]="Applicable", "Windows_11, Chrome, NVDA, ", " ") &IF(Final_Report[[#This Row],[iOS/VO]]="Applicable", "iOS Tablet, VoiceOver, ", " ") &IF(Final_Report[[#This Row],[Mac/Safari/VO]]="Applicable", "macOS_12, Safari, VoiceOver, ", " ") &IF(Final_Report[[#This Row],[Mac/Chrome/VO]]="Applicable", "macOS_12, Chrome, VoiceOver, ", " ") &IF(Final_Report[[#This Row],[Android/Talkback]]="Applicable", "TalkBack, Android Tablet", " ") ) &", " &IF(ISERROR(FIND("iOS 13",INDEX(Keyword[Component Keyword],MATCH(TRUE,INDEX((Keyword[Component Keyword]<>0),0),0)))=FALSE),INDEX(Keyword[Component Keyword],MATCH(TRUE,INDEX((Keyword[Component Keyword]<>0),0),0)),SUBSTITUTE(INDEX(Keyword[Component Keyword],MATCH(TRUE,INDEX((Keyword[Component Keyword]<>0),0),0)),"iOS 13","iOS")),",",""))+1))-1)*999+1,999))))} -> N/A (Level N/A), Windows_11, Chrome, JAWS, Firefox, NVDA, Accessibility, Audit, Marketing, MLM-XL, MLVISION, MyLab, US, VPAT | AM21: {=CONCATENATE(LEFT(AH21, SEARCH(" ", AH21) -1),", ",Labels[Labels])} -> #VALUE! | AN21: =IF(AJ21="Blocker","1 - Critical - showstopper",IF(AJ21="Critical","1 - Critical - showstopper",IF(AJ21="Major","1 - Critical - showstopper",IF(AJ21="Minor","3 - Medium - minor functionality broken",IF(AJ21="Trivial","4 - Low - cosmetic or usability"))))) -> 3 - Medium - minor functionality broken | AO21: naveen.lagishetty | AR21: Known issue - ACDS-265730 | BC21: =VLOOKUP('Final Report'!D21,'Issue Variable'!A:N,11,FALSE) -> #N/A
A22: P6 | B22: =VLOOKUP(A22,URL[],2,0) -> Multimedia Library Mainpage | C22: =VLOOKUP(A22,URL[],3,0) -> 0 | D22: ARIA | E22: Role defined inappropriately | F22: In main content area "Find Now" element exposed as link element which incorect it should be exposed as button element, so role="button" required. Similar instance is found in result content text such as "Get Started with MyLab Marketing" exposed as link element which is incorrect | G22: Applicable | H22: Applicable | I22: Applicable | J22: Applicable | K22: Applicable | L22: Applicable | M22: Applicable | P22: naveen.lagishetty | Q22: No QA Needed | S22: Yes | T22: Web: Multimedia Library Mainpage: Role defined inappropriately | U22: The role such as "Find Now" is defined inappropriately for the <a> element containing the across the tested pages. As a result, screen reader users found it difficult to understand the functionality effectively. | V22: The roles such as "figure" is defined inappropriately for the <a> element containing the various bookmarks links such as "BBBBB","BBBBB", "BBBBB" etc. across the tested pages. As a result, screen reader users found it difficult to understand the functionality effectively. | W22: <a href="javascript:__doPostBack('ctl00$ctl00$InsideForm$MasterContent$ButtonSearch','')" id="ButtonSearch" class="btn btn-primary " style="cursor: pointer;">Find Now </a> | X22: =Final_Report[[#This Row],[Code Snippet]] -> <a href="javascript:__doPostBack('ctl00$ctl00$InsideForm$MasterContent$ButtonSearch','')" id="ButtonSearch" class="btn btn-primary " style="cursor: pointer;">Find Now </a> | Y22: Screen reader users will access the interactive element effectively. Provide role="button" to <a> element. <a href="javascript:__doPostBack('ctl00$ctl00$InsideForm$MasterContent$ButtonSearch','')" role="button" id="ButtonSearch" class="btn btn-primary " style="cursor: pointer;">Find Now </a> | Z22: =Final_Report[[#This Row],[Expected Result]] -> Screen reader users will access the interactive element effectively. Provide role="button" to <a> element. <a href="javascript:__doPostBack('ctl00$ctl00$InsideForm$MasterContent$ButtonSearch','')" role="button" id="ButtonSearch" class="btn btn-primary " style="cursor: pointer;">Find Now </a> | AA22: =IF(Final_Report[[#This Row],[Move to Report]]="Yes",VLOOKUP(E22,IssueVariable[],6,0),"N/A") -> Assistive technologies rely on an element’s information, such as role, state and properties to convey the element information to their users. An element’s role helps assistive technology users to understand what key they need to press in order to interact with it. When appropriate role information is not specified accurately for a web page element, it becomes confusing for assistive technology users (especially screen reader users) and in some cases even difficult for users to interact with the functionality associated with the element. Screen reader renders the content from the mark-up and present the functionality to its users in the way that users can understand. If appropriate mark-up is not used to represent the content, it may pose problems, and thereby make the content difficult to interpret for screen reader users. | AB22: Provide role="button" to <a> element. | AC22: =Final_Report[[#This Row],[Recommendation]] -> Provide role="button" to <a> element. | AD22: URL: https://www.pearsonmylabandmastering.com/northamerica Username: Aqavpat-edu1 Password: AuditPa559338 Course Title: AQA_VPAT_Kotler_Principles of Marketing 19e Course Id: auditor49388 1. Launch the above URL with the given credentials and navigate to the mentioned course | AE22: 2. Navigate to Student Success Hub > Multimedia Library interactive element and activate it. 3.Inspect interactive element "Find Now". | AF22: =Final_Report[[#This Row],[Steps to Reproduce]] -> 2. Navigate to Student Success Hub > Multimedia Library interactive element and activate it. 3.Inspect interactive element "Find Now". | AG22: =IF(Final_Report[[#This Row],[Move to Report]]="Yes",VLOOKUP(E22,IssueVariable[],9,0),"N/A") -> A | AH22: =IF(Final_Report[[#This Row],[Move to Report]]="Yes",VLOOKUP(E22,IssueVariable[],10,0),"N/A") -> 4.1.2 Name, Role, Value | AI22: Marketing_22 | AJ22: Major | AK22: {=Table95[Tested on]} -> Windows: 11 MAC OS: 12 iOS: 15 Android OS: 10 | AL22: {=_xlfn.TEXTJOIN(", ",TRUE,_xlfn.UNIQUE(TRIM(MID(SUBSTITUTE((Final_Report[[#This Row],[WCAG 2.1 Success Criteria]] &_xlfn.CONCAT(" (Level ") &Final_Report[[#This Row],[WCAG 2.1 Conformance Level]] &_xlfn.CONCAT("), ") &IF(Final_Report[[#This Row],[Chrome/JAWS]]="Applicable","Windows_11, Chrome, JAWS, ", " ") &IF(Final_Report[[#This Row],[FF/NVDA]]="Applicable", "Windows_11, Firefox, NVDA, ", " ") &IF(Final_Report[[#This Row],[Chrome/NVDA]]="Applicable", "Windows_11, Chrome, NVDA, ", " ") &IF(Final_Report[[#This Row],[iOS/VO]]="Applicable", "iOS Tablet, VoiceOver, ", " ") &IF(Final_Report[[#This Row],[Mac/Safari/VO]]="Applicable", "macOS_12, Safari, VoiceOver, ", " ") &IF(Final_Report[[#This Row],[Mac/Chrome/VO]]="Applicable", "macOS_12, Chrome, VoiceOver, ", " ") &IF(Final_Report[[#This Row],[Android/Talkback]]="Applicable", "TalkBack, Android Tablet", " ") ) &", " &IF(ISERROR(FIND("iOS 13",INDEX(Keyword[Component Keyword],MATCH(TRUE,INDEX((Keyword[Component Keyword]<>0),0),0)))=FALSE),INDEX(Keyword[Component Keyword],MATCH(TRUE,INDEX((Keyword[Component Keyword]<>0),0),0)),SUBSTITUTE(INDEX(Keyword[Component Keyword],MATCH(TRUE,INDEX((Keyword[Component Keyword]<>0),0),0)),"iOS 13","iOS")),",",REPT(" ",999)),(ROW($AAN$1:INDEX($AAX:$AAX,LEN((Final_Report[[#This Row],[WCAG 2.1 Success Criteria]] &_xlfn.CONCAT(" (Level ") &Final_Report[[#This Row],[WCAG 2.1 Conformance Level]] &_xlfn.CONCAT("), ") &IF(Final_Report[[#This Row],[Chrome/JAWS]]="Applicable","Windows_11, Chrome, JAWS, ", " ") &IF(Final_Report[[#This Row],[FF/NVDA]]="Applicable", "Windows_11, Firefox, NVDA, ", " ") &IF(Final_Report[[#This Row],[Chrome/NVDA]]="Applicable", "Windows_11, Chrome, NVDA, ", " ") &IF(Final_Report[[#This Row],[iOS/VO]]="Applicable", "iOS Tablet, VoiceOver, ", " ") &IF(Final_Report[[#This Row],[Mac/Safari/VO]]="Applicable", "macOS_12, Safari, VoiceOver, ", " ") &IF(Final_Report[[#This Row],[Mac/Chrome/VO]]="Applicable", "macOS_12, Chrome, VoiceOver, ", " ") &IF(Final_Report[[#This Row],[Android/Talkback]]="Applicable", "TalkBack, Android Tablet", " ") ) &", " &IF(ISERROR(FIND("iOS 13",INDEX(Keyword[Component Keyword],MATCH(TRUE,INDEX((Keyword[Component Keyword]<>0),0),0)))=FALSE),INDEX(Keyword[Component Keyword],MATCH(TRUE,INDEX((Keyword[Component Keyword]<>0),0),0)),SUBSTITUTE(INDEX(Keyword[Component Keyword],MATCH(TRUE,INDEX((Keyword[Component Keyword]<>0),0),0)),"iOS 13","iOS")))-LEN(SUBSTITUTE((Final_Report[[#This Row],[WCAG 2.1 Success Criteria]] &_xlfn.CONCAT(" (Level ") &Final_Report[[#This Row],[WCAG 2.1 Conformance Level]] &_xlfn.CONCAT("), ") &IF(Final_Report[[#This Row],[Chrome/JAWS]]="Applicable","Windows_11, Chrome, JAWS, ", " ") &IF(Final_Report[[#This Row],[FF/NVDA]]="Applicable", "Windows_11, Firefox, NVDA, ", " ") &IF(Final_Report[[#This Row],[Chrome/NVDA]]="Applicable", "Windows_11, Chrome, NVDA, ", " ") &IF(Final_Report[[#This Row],[iOS/VO]]="Applicable", "iOS Tablet, VoiceOver, ", " ") &IF(Final_Report[[#This Row],[Mac/Safari/VO]]="Applicable", "macOS_12, Safari, VoiceOver, ", " ") &IF(Final_Report[[#This Row],[Mac/Chrome/VO]]="Applicable", "macOS_12, Chrome, VoiceOver, ", " ") &IF(Final_Report[[#This Row],[Android/Talkback]]="Applicable", "TalkBack, Android Tablet", " ") ) &", " &IF(ISERROR(FIND("iOS 13",INDEX(Keyword[Component Keyword],MATCH(TRUE,INDEX((Keyword[Component Keyword]<>0),0),0)))=FALSE),INDEX(Keyword[Component Keyword],MATCH(TRUE,INDEX((Keyword[Component Keyword]<>0),0),0)),SUBSTITUTE(INDEX(Keyword[Component Keyword],MATCH(TRUE,INDEX((Keyword[Component Keyword]<>0),0),0)),"iOS 13","iOS")),",",""))+1))-1)*999+1,999))))} -> 4.1.2 Name, Role, Value (Level A), Windows_11, Chrome, JAWS, Firefox, NVDA, iOS Tablet, VoiceOver, macOS_12, Safari, TalkBack, Android Tablet, Accessibility, Audit, Marketing, MLM-XL, MLVISION, MyLab, US, VPAT | AM22: {=CONCATENATE(LEFT(AH22, SEARCH(" ", AH22) -1),", ",Labels[Labels])} -> 4.1.2, Accessibility, Audit, Marketing, MLM-XL, MLVISION, MyLab, US, VPAT | AN22: =IF(AJ22="Blocker","1 - Critical - showstopper",IF(AJ22="Critical","1 - Critical - showstopper",IF(AJ22="Major","1 - Critical - showstopper",IF(AJ22="Minor","3 - Medium - minor functionality broken",IF(AJ22="Trivial","4 - Low - cosmetic or usability"))))) -> 1 - Critical - showstopper | AO22: naveen.lagishetty | AP22: 5 | AQ22: 5 | AS22: 5 | AT22: manasi.varma | AU22: not an issue | AV22: Technical Issues | AW22: 5 | AX22: Delete - QA | BC22: =VLOOKUP('Final Report'!D22,'Issue Variable'!A:N,11,FALSE) -> #N/A
A23: P6 | B23: =VLOOKUP(A23,URL[],2,0) -> Multimedia Library Mainpage | C23: =VLOOKUP(A23,URL[],3,0) -> 0 | D23: Headings | E23: Inappropriate heading structure | F23: In main content area wher sr user ("Find Now") submit the form with inputs below the form result gets updated wher heading structure is inappropriate. "Chapter 0. Get Started With MyLab Marketing" - H3 it should be H2 "Get Started" - H4 it should be H3 | G23: Applicable | H23: Applicable | I23: Applicable | P23: naveen.lagishetty | Q23: No QA Needed | S23: No | T23: =IF(Final_Report[[#This Row],[Move to Report]]="Yes",VLOOKUP(E23,IssueVariable[],3,0),"N/A") -> N/A | U23: =IF(Final_Report[[#This Row],[Move to Report]]="Yes",VLOOKUP(E23,IssueVariable[],4,0),"N/A") -> N/A | V23: =Final_Report[[#This Row],[Issue Description]] -> N/A | X23: =Final_Report[[#This Row],[Code Snippet]] -> 0 | Y23: =IF(Final_Report[[#This Row],[Move to Report]]="Yes",VLOOKUP(E23,IssueVariable[],5,0),"N/A") -> N/A | Z23: =Final_Report[[#This Row],[Expected Result]] -> N/A | AA23: =IF(Final_Report[[#This Row],[Move to Report]]="Yes",VLOOKUP(E23,IssueVariable[],6,0),"N/A") -> N/A | AB23: =IF(Final_Report[[#This Row],[Move to Report]]="Yes",VLOOKUP(E23,IssueVariable[],7,0),"N/A") -> N/A | AC23: =Final_Report[[#This Row],[Recommendation]] -> N/A | AE23: =IF(Final_Report[[#This Row],[Move to Report]]="Yes",VLOOKUP(E23,IssueVariable[],8,0),"N/A") -> N/A | AF23: =Final_Report[[#This Row],[Steps to Reproduce]] -> N/A | AG23: =IF(Final_Report[[#This Row],[Move to Report]]="Yes",VLOOKUP(E23,IssueVariable[],9,0),"N/A") -> N/A | AH23: =IF(Final_Report[[#This Row],[Move to Report]]="Yes",VLOOKUP(E23,IssueVariable[],10,0),"N/A") -> N/A | AK23: {=Table95[Tested on]} -> Windows: 11 MAC OS: 12 iOS: 15 Android OS: 10 | AL23: {=_xlfn.TEXTJOIN(", ",TRUE,_xlfn.UNIQUE(TRIM(MID(SUBSTITUTE((Final_Report[[#This Row],[WCAG 2.1 Success Criteria]] &_xlfn.CONCAT(" (Level ") &Final_Report[[#This Row],[WCAG 2.1 Conformance Level]] &_xlfn.CONCAT("), ") &IF(Final_Report[[#This Row],[Chrome/JAWS]]="Applicable","Windows_11, Chrome, JAWS, ", " ") &IF(Final_Report[[#This Row],[FF/NVDA]]="Applicable", "Windows_11, Firefox, NVDA, ", " ") &IF(Final_Report[[#This Row],[Chrome/NVDA]]="Applicable", "Windows_11, Chrome, NVDA, ", " ") &IF(Final_Report[[#This Row],[iOS/VO]]="Applicable", "iOS Tablet, VoiceOver, ", " ") &IF(Final_Report[[#This Row],[Mac/Safari/VO]]="Applicable", "macOS_12, Safari, VoiceOver, ", " ") &IF(Final_Report[[#This Row],[Mac/Chrome/VO]]="Applicable", "macOS_12, Chrome, VoiceOver, ", " ") &IF(Final_Report[[#This Row],[Android/Talkback]]="Applicable", "TalkBack, Android Tablet", " ") ) &", " &IF(ISERROR(FIND("iOS 13",INDEX(Keyword[Component Keyword],MATCH(TRUE,INDEX((Keyword[Component Keyword]<>0),0),0)))=FALSE),INDEX(Keyword[Component Keyword],MATCH(TRUE,INDEX((Keyword[Component Keyword]<>0),0),0)),SUBSTITUTE(INDEX(Keyword[Component Keyword],MATCH(TRUE,INDEX((Keyword[Component Keyword]<>0),0),0)),"iOS 13","iOS")),",",REPT(" ",999)),(ROW($AAN$1:INDEX($AAX:$AAX,LEN((Final_Report[[#This Row],[WCAG 2.1 Success Criteria]] &_xlfn.CONCAT(" (Level ") &Final_Report[[#This Row],[WCAG 2.1 Conformance Level]] &_xlfn.CONCAT("), ") &IF(Final_Report[[#This Row],[Chrome/JAWS]]="Applicable","Windows_11, Chrome, JAWS, ", " ") &IF(Final_Report[[#This Row],[FF/NVDA]]="Applicable", "Windows_11, Firefox, NVDA, ", " ") &IF(Final_Report[[#This Row],[Chrome/NVDA]]="Applicable", "Windows_11, Chrome, NVDA, ", " ") &IF(Final_Report[[#This Row],[iOS/VO]]="Applicable", "iOS Tablet, VoiceOver, ", " ") &IF(Final_Report[[#This Row],[Mac/Safari/VO]]="Applicable", "macOS_12, Safari, VoiceOver, ", " ") &IF(Final_Report[[#This Row],[Mac/Chrome/VO]]="Applicable", "macOS_12, Chrome, VoiceOver, ", " ") &IF(Final_Report[[#This Row],[Android/Talkback]]="Applicable", "TalkBack, Android Tablet", " ") ) &", " &IF(ISERROR(FIND("iOS 13",INDEX(Keyword[Component Keyword],MATCH(TRUE,INDEX((Keyword[Component Keyword]<>0),0),0)))=FALSE),INDEX(Keyword[Component Keyword],MATCH(TRUE,INDEX((Keyword[Component Keyword]<>0),0),0)),SUBSTITUTE(INDEX(Keyword[Component Keyword],MATCH(TRUE,INDEX((Keyword[Component Keyword]<>0),0),0)),"iOS 13","iOS")))-LEN(SUBSTITUTE((Final_Report[[#This Row],[WCAG 2.1 Success Criteria]] &_xlfn.CONCAT(" (Level ") &Final_Report[[#This Row],[WCAG 2.1 Conformance Level]] &_xlfn.CONCAT("), ") &IF(Final_Report[[#This Row],[Chrome/JAWS]]="Applicable","Windows_11, Chrome, JAWS, ", " ") &IF(Final_Report[[#This Row],[FF/NVDA]]="Applicable", "Windows_11, Firefox, NVDA, ", " ") &IF(Final_Report[[#This Row],[Chrome/NVDA]]="Applicable", "Windows_11, Chrome, NVDA, ", " ") &IF(Final_Report[[#This Row],[iOS/VO]]="Applicable", "iOS Tablet, VoiceOver, ", " ") &IF(Final_Report[[#This Row],[Mac/Safari/VO]]="Applicable", "macOS_12, Safari, VoiceOver, ", " ") &IF(Final_Report[[#This Row],[Mac/Chrome/VO]]="Applicable", "macOS_12, Chrome, VoiceOver, ", " ") &IF(Final_Report[[#This Row],[Android/Talkback]]="Applicable", "TalkBack, Android Tablet", " ") ) &", " &IF(ISERROR(FIND("iOS 13",INDEX(Keyword[Component Keyword],MATCH(TRUE,INDEX((Keyword[Component Keyword]<>0),0),0)))=FALSE),INDEX(Keyword[Component Keyword],MATCH(TRUE,INDEX((Keyword[Component Keyword]<>0),0),0)),SUBSTITUTE(INDEX(Keyword[Component Keyword],MATCH(TRUE,INDEX((Keyword[Component Keyword]<>0),0),0)),"iOS 13","iOS")),",",""))+1))-1)*999+1,999))))} -> N/A (Level N/A), Windows_11, Chrome, JAWS, Firefox, NVDA, Accessibility, Audit, Marketing, MLM-XL, MLVISION, MyLab, US, VPAT | AM23: {=CONCATENATE(LEFT(AH23, SEARCH(" ", AH23) -1),", ",Labels[Labels])} -> #VALUE! | AN23: =IF(AJ23="Blocker","1 - Critical - showstopper",IF(AJ23="Critical","1 - Critical - showstopper",IF(AJ23="Major","1 - Critical - showstopper",IF(AJ23="Minor","3 - Medium - minor functionality broken",IF(AJ23="Trivial","4 - Low - cosmetic or usability"))))) -> FALSE | BC23: =VLOOKUP('Final Report'!D23,'Issue Variable'!A:N,11,FALSE) -> #N/A
A24: P6 | B24: =VLOOKUP(A24,URL[],2,0) -> Multimedia Library Mainpage | C24: =VLOOKUP(A24,URL[],3,0) -> 0 | D24: Links | E24: Skip link does not work | F24: There is a "Skip to main content" link present where it does not work. - Known issue - ACDS-220431 | G24: Applicable | H24: Applicable | I24: Applicable | P24: naveen.lagishetty | Q24: No QA Needed | S24: No | T24: =IF(Final_Report[[#This Row],[Move to Report]]="Yes",VLOOKUP(E24,IssueVariable[],3,0),"N/A") -> N/A | U24: =IF(Final_Report[[#This Row],[Move to Report]]="Yes",VLOOKUP(E24,IssueVariable[],4,0),"N/A") -> N/A | V24: =Final_Report[[#This Row],[Issue Description]] -> N/A | X24: =Final_Report[[#This Row],[Code Snippet]] -> 0 | Y24: =IF(Final_Report[[#This Row],[Move to Report]]="Yes",VLOOKUP(E24,IssueVariable[],5,0),"N/A") -> N/A | Z24: =Final_Report[[#This Row],[Expected Result]] -> N/A | AA24: =IF(Final_Report[[#This Row],[Move to Report]]="Yes",VLOOKUP(E24,IssueVariable[],6,0),"N/A") -> N/A | AB24: =IF(Final_Report[[#This Row],[Move to Report]]="Yes",VLOOKUP(E24,IssueVariable[],7,0),"N/A") -> N/A | AC24: =Final_Report[[#This Row],[Recommendation]] -> N/A | AE24: =IF(Final_Report[[#This Row],[Move to Report]]="Yes",VLOOKUP(E24,IssueVariable[],8,0),"N/A") -> N/A | AF24: =Final_Report[[#This Row],[Steps to Reproduce]] -> N/A | AG24: =IF(Final_Report[[#This Row],[Move to Report]]="Yes",VLOOKUP(E24,IssueVariable[],9,0),"N/A") -> N/A | AH24: =IF(Final_Report[[#This Row],[Move to Report]]="Yes",VLOOKUP(E24,IssueVariable[],10,0),"N/A") -> N/A | AK24: {=Table95[Tested on]} -> Windows: 11 MAC OS: 12 iOS: 15 Android OS: 10 | AL24: {=_xlfn.TEXTJOIN(", ",TRUE,_xlfn.UNIQUE(TRIM(MID(SUBSTITUTE((Final_Report[[#This Row],[WCAG 2.1 Success Criteria]] &_xlfn.CONCAT(" (Level ") &Final_Report[[#This Row],[WCAG 2.1 Conformance Level]] &_xlfn.CONCAT("), ") &IF(Final_Report[[#This Row],[Chrome/JAWS]]="Applicable","Windows_11, Chrome, JAWS, ", " ") &IF(Final_Report[[#This Row],[FF/NVDA]]="Applicable", "Windows_11, Firefox, NVDA, ", " ") &IF(Final_Report[[#This Row],[Chrome/NVDA]]="Applicable", "Windows_11, Chrome, NVDA, ", " ") &IF(Final_Report[[#This Row],[iOS/VO]]="Applicable", "iOS Tablet, VoiceOver, ", " ") &IF(Final_Report[[#This Row],[Mac/Safari/VO]]="Applicable", "macOS_12, Safari, VoiceOver, ", " ") &IF(Final_Report[[#This Row],[Mac/Chrome/VO]]="Applicable", "macOS_12, Chrome, VoiceOver, ", " ") &IF(Final_Report[[#This Row],[Android/Talkback]]="Applicable", "TalkBack, Android Tablet", " ") ) &", " &IF(ISERROR(FIND("iOS 13",INDEX(Keyword[Component Keyword],MATCH(TRUE,INDEX((Keyword[Component Keyword]<>0),0),0)))=FALSE),INDEX(Keyword[Component Keyword],MATCH(TRUE,INDEX((Keyword[Component Keyword]<>0),0),0)),SUBSTITUTE(INDEX(Keyword[Component Keyword],MATCH(TRUE,INDEX((Keyword[Component Keyword]<>0),0),0)),"iOS 13","iOS")),",",REPT(" ",999)),(ROW($AAN$1:INDEX($AAX:$AAX,LEN((Final_Report[[#This Row],[WCAG 2.1 Success Criteria]] &_xlfn.CONCAT(" (Level ") &Final_Report[[#This Row],[WCAG 2.1 Conformance Level]] &_xlfn.CONCAT("), ") &IF(Final_Report[[#This Row],[Chrome/JAWS]]="Applicable","Windows_11, Chrome, JAWS, ", " ") &IF(Final_Report[[#This Row],[FF/NVDA]]="Applicable", "Windows_11, Firefox, NVDA, ", " ") &IF(Final_Report[[#This Row],[Chrome/NVDA]]="Applicable", "Windows_11, Chrome, NVDA, ", " ") &IF(Final_Report[[#This Row],[iOS/VO]]="Applicable", "iOS Tablet, VoiceOver, ", " ") &IF(Final_Report[[#This Row],[Mac/Safari/VO]]="Applicable", "macOS_12, Safari, VoiceOver, ", " ") &IF(Final_Report[[#This Row],[Mac/Chrome/VO]]="Applicable", "macOS_12, Chrome, VoiceOver, ", " ") &IF(Final_Report[[#This Row],[Android/Talkback]]="Applicable", "TalkBack, Android Tablet", " ") ) &", " &IF(ISERROR(FIND("iOS 13",INDEX(Keyword[Component Keyword],MATCH(TRUE,INDEX((Keyword[Component Keyword]<>0),0),0)))=FALSE),INDEX(Keyword[Component Keyword],MATCH(TRUE,INDEX((Keyword[Component Keyword]<>0),0),0)),SUBSTITUTE(INDEX(Keyword[Component Keyword],MATCH(TRUE,INDEX((Keyword[Component Keyword]<>0),0),0)),"iOS 13","iOS")))-LEN(SUBSTITUTE((Final_Report[[#This Row],[WCAG 2.1 Success Criteria]] &_xlfn.CONCAT(" (Level ") &Final_Report[[#This Row],[WCAG 2.1 Conformance Level]] &_xlfn.CONCAT("), ") &IF(Final_Report[[#This Row],[Chrome/JAWS]]="Applicable","Windows_11, Chrome, JAWS, ", " ") &IF(Final_Report[[#This Row],[FF/NVDA]]="Applicable", "Windows_11, Firefox, NVDA, ", " ") &IF(Final_Report[[#This Row],[Chrome/NVDA]]="Applicable", "Windows_11, Chrome, NVDA, ", " ") &IF(Final_Report[[#This Row],[iOS/VO]]="Applicable", "iOS Tablet, VoiceOver, ", " ") &IF(Final_Report[[#This Row],[Mac/Safari/VO]]="Applicable", "macOS_12, Safari, VoiceOver, ", " ") &IF(Final_Report[[#This Row],[Mac/Chrome/VO]]="Applicable", "macOS_12, Chrome, VoiceOver, ", " ") &IF(Final_Report[[#This Row],[Android/Talkback]]="Applicable", "TalkBack, Android Tablet", " ") ) &", " &IF(ISERROR(FIND("iOS 13",INDEX(Keyword[Component Keyword],MATCH(TRUE,INDEX((Keyword[Component Keyword]<>0),0),0)))=FALSE),INDEX(Keyword[Component Keyword],MATCH(TRUE,INDEX((Keyword[Component Keyword]<>0),0),0)),SUBSTITUTE(INDEX(Keyword[Component Keyword],MATCH(TRUE,INDEX((Keyword[Component Keyword]<>0),0),0)),"iOS 13","iOS")),",",""))+1))-1)*999+1,999))))} -> N/A (Level N/A), Windows_11, Chrome, JAWS, Firefox, NVDA, Accessibility, Audit, Marketing, MLM-XL, MLVISION, MyLab, US, VPAT | AM24: {=CONCATENATE(LEFT(AH24, SEARCH(" ", AH24) -1),", ",Labels[Labels])} -> #VALUE! | AN24: =IF(AJ24="Blocker","1 - Critical - showstopper",IF(AJ24="Critical","1 - Critical - showstopper",IF(AJ24="Major","1 - Critical - showstopper",IF(AJ24="Minor","3 - Medium - minor functionality broken",IF(AJ24="Trivial","4 - Low - cosmetic or usability"))))) -> FALSE | AR24: Known issue - ACDS-220431 | BC24: =VLOOKUP('Final Report'!D24,'Issue Variable'!A:N,11,FALSE) -> #N/A
A25: P6 | B25: =VLOOKUP(A25,URL[],2,0) -> Multimedia Library Mainpage | C25: =VLOOKUP(A25,URL[],3,0) -> 0 | D25: Content | E25: Content not available with browser zoom | F25: Content gets overlaps and left navigation section available as front popup so behind the iFrame content is not clearly visisble. - Its a Global issue | G25: Applicable | H25: Applicable | I25: Applicable | P25: naveen.lagishetty | Q25: No QA Needed | S25: No | T25: =IF(Final_Report[[#This Row],[Move to Report]]="Yes",VLOOKUP(E25,IssueVariable[],3,0),"N/A") -> N/A | U25: =IF(Final_Report[[#This Row],[Move to Report]]="Yes",VLOOKUP(E25,IssueVariable[],4,0),"N/A") -> N/A | V25: =Final_Report[[#This Row],[Issue Description]] -> N/A | X25: =Final_Report[[#This Row],[Code Snippet]] -> 0 | Y25: =IF(Final_Report[[#This Row],[Move to Report]]="Yes",VLOOKUP(E25,IssueVariable[],5,0),"N/A") -> N/A | Z25: =Final_Report[[#This Row],[Expected Result]] -> N/A | AA25: =IF(Final_Report[[#This Row],[Move to Report]]="Yes",VLOOKUP(E25,IssueVariable[],6,0),"N/A") -> N/A | AB25: =IF(Final_Report[[#This Row],[Move to Report]]="Yes",VLOOKUP(E25,IssueVariable[],7,0),"N/A") -> N/A | AC25: =Final_Report[[#This Row],[Recommendation]] -> N/A | AE25: =IF(Final_Report[[#This Row],[Move to Report]]="Yes",VLOOKUP(E25,IssueVariable[],8,0),"N/A") -> N/A | AF25: =Final_Report[[#This Row],[Steps to Reproduce]] -> N/A | AG25: =IF(Final_Report[[#This Row],[Move to Report]]="Yes",VLOOKUP(E25,IssueVariable[],9,0),"N/A") -> N/A | AH25: =IF(Final_Report[[#This Row],[Move to Report]]="Yes",VLOOKUP(E25,IssueVariable[],10,0),"N/A") -> N/A | AK25: {=Table95[Tested on]} -> Windows: 11 MAC OS: 12 iOS: 15 Android OS: 10 | AL25: {=_xlfn.TEXTJOIN(", ",TRUE,_xlfn.UNIQUE(TRIM(MID(SUBSTITUTE((Final_Report[[#This Row],[WCAG 2.1 Success Criteria]] &_xlfn.CONCAT(" (Level ") &Final_Report[[#This Row],[WCAG 2.1 Conformance Level]] &_xlfn.CONCAT("), ") &IF(Final_Report[[#This Row],[Chrome/JAWS]]="Applicable","Windows_11, Chrome, JAWS, ", " ") &IF(Final_Report[[#This Row],[FF/NVDA]]="Applicable", "Windows_11, Firefox, NVDA, ", " ") &IF(Final_Report[[#This Row],[Chrome/NVDA]]="Applicable", "Windows_11, Chrome, NVDA, ", " ") &IF(Final_Report[[#This Row],[iOS/VO]]="Applicable", "iOS Tablet, VoiceOver, ", " ") &IF(Final_Report[[#This Row],[Mac/Safari/VO]]="Applicable", "macOS_12, Safari, VoiceOver, ", " ") &IF(Final_Report[[#This Row],[Mac/Chrome/VO]]="Applicable", "macOS_12, Chrome, VoiceOver, ", " ") &IF(Final_Report[[#This Row],[Android/Talkback]]="Applicable", "TalkBack, Android Tablet", " ") ) &", " &IF(ISERROR(FIND("iOS 13",INDEX(Keyword[Component Keyword],MATCH(TRUE,INDEX((Keyword[Component Keyword]<>0),0),0)))=FALSE),INDEX(Keyword[Component Keyword],MATCH(TRUE,INDEX((Keyword[Component Keyword]<>0),0),0)),SUBSTITUTE(INDEX(Keyword[Component Keyword],MATCH(TRUE,INDEX((Keyword[Component Keyword]<>0),0),0)),"iOS 13","iOS")),",",REPT(" ",999)),(ROW($AAN$1:INDEX($AAX:$AAX,LEN((Final_Report[[#This Row],[WCAG 2.1 Success Criteria]] &_xlfn.CONCAT(" (Level ") &Final_Report[[#This Row],[WCAG 2.1 Conformance Level]] &_xlfn.CONCAT("), ") &IF(Final_Report[[#This Row],[Chrome/JAWS]]="Applicable","Windows_11, Chrome, JAWS, ", " ") &IF(Final_Report[[#This Row],[FF/NVDA]]="Applicable", "Windows_11, Firefox, NVDA, ", " ") &IF(Final_Report[[#This Row],[Chrome/NVDA]]="Applicable", "Windows_11, Chrome, NVDA, ", " ") &IF(Final_Report[[#This Row],[iOS/VO]]="Applicable", "iOS Tablet, VoiceOver, ", " ") &IF(Final_Report[[#This Row],[Mac/Safari/VO]]="Applicable", "macOS_12, Safari, VoiceOver, ", " ") &IF(Final_Report[[#This Row],[Mac/Chrome/VO]]="Applicable", "macOS_12, Chrome, VoiceOver, ", " ") &IF(Final_Report[[#This Row],[Android/Talkback]]="Applicable", "TalkBack, Android Tablet", " ") ) &", " &IF(ISERROR(FIND("iOS 13",INDEX(Keyword[Component Keyword],MATCH(TRUE,INDEX((Keyword[Component Keyword]<>0),0),0)))=FALSE),INDEX(Keyword[Component Keyword],MATCH(TRUE,INDEX((Keyword[Component Keyword]<>0),0),0)),SUBSTITUTE(INDEX(Keyword[Component Keyword],MATCH(TRUE,INDEX((Keyword[Component Keyword]<>0),0),0)),"iOS 13","iOS")))-LEN(SUBSTITUTE((Final_Report[[#This Row],[WCAG 2.1 Success Criteria]] &_xlfn.CONCAT(" (Level ") &Final_Report[[#This Row],[WCAG 2.1 Conformance Level]] &_xlfn.CONCAT("), ") &IF(Final_Report[[#This Row],[Chrome/JAWS]]="Applicable","Windows_11, Chrome, JAWS, ", " ") &IF(Final_Report[[#This Row],[FF/NVDA]]="Applicable", "Windows_11, Firefox, NVDA, ", " ") &IF(Final_Report[[#This Row],[Chrome/NVDA]]="Applicable", "Windows_11, Chrome, NVDA, ", " ") &IF(Final_Report[[#This Row],[iOS/VO]]="Applicable", "iOS Tablet, VoiceOver, ", " ") &IF(Final_Report[[#This Row],[Mac/Safari/VO]]="Applicable", "macOS_12, Safari, VoiceOver, ", " ") &IF(Final_Report[[#This Row],[Mac/Chrome/VO]]="Applicable", "macOS_12, Chrome, VoiceOver, ", " ") &IF(Final_Report[[#This Row],[Android/Talkback]]="Applicable", "TalkBack, Android Tablet", " ") ) &", " &IF(ISERROR(FIND("iOS 13",INDEX(Keyword[Component Keyword],MATCH(TRUE,INDEX((Keyword[Component Keyword]<>0),0),0)))=FALSE),INDEX(Keyword[Component Keyword],MATCH(TRUE,INDEX((Keyword[Component Keyword]<>0),0),0)),SUBSTITUTE(INDEX(Keyword[Component Keyword],MATCH(TRUE,INDEX((Keyword[Component Keyword]<>0),0),0)),"iOS 13","iOS")),",",""))+1))-1)*999+1,999))))} -> N/A (Level N/A), Windows_11, Chrome, JAWS, Firefox, NVDA, Accessibility, Audit, Marketing, MLM-XL, MLVISION, MyLab, US, VPAT | AM25: {=CONCATENATE(LEFT(AH25, SEARCH(" ", AH25) -1),", ",Labels[Labels])} -> #VALUE! | AN25: =IF(AJ25="Blocker","1 - Critical - showstopper",IF(AJ25="Critical","1 - Critical - showstopper",IF(AJ25="Major","1 - Critical - showstopper",IF(AJ25="Minor","3 - Medium - minor functionality broken",IF(AJ25="Trivial","4 - Low - cosmetic or usability"))))) -> FALSE | AR25: Known issue - ACDS-170037 | BC25: =VLOOKUP('Final Report'!D25,'Issue Variable'!A:N,11,FALSE) -> #N/A
A26: P2, P6 | B26: =VLOOKUP(A26,URL[],2,0) -> #N/A | C26: =VLOOKUP(A26,URL[],3,0) -> #N/A | D26: Content | E26: Content fails to reflow | F26: When reflowing the page on 320x256 dimension content not clearly visible - Its a Global issue | G26: Applicable | H26: Applicable | I26: Applicable | L26: Not Applicable | M26: Not Applicable | P26: naveen.lagishetty | Q26: No QA Needed | S26: Yes | T26: Web: Course Home - Calendar: Content fails to reflow | U26: The content failed to reflow when viewed at 320X256 viewport size. Following are the instances affected: • The "No announcements during the selected timeframe." present in main content area get overlaps with same text. • The header text "AQA_VPAT_Kotler_Principles of Marketing 19e" present in main section area becomes partially unavailable. • The text such as "Kotler/Armstrong/Balasubramanian, Principles of Marketing, 19e" overlaps with decorative image. • Content is not displayed in a single column. This will result in low vision users finding it difficult to access the content when zoomed in. Similar issue found on "Multimedia Library Mainpage" page | V26: =Final_Report[[#This Row],[Issue Description]] -> The content failed to reflow when viewed at 320X256 viewport size. Following are the instances affected: • The "No announcements during the selected timeframe." present in main content area get overlaps with same text. • The header text "AQA_VPAT_Kotler_Principles of Marketing 19e" present in main section area becomes partially unavailable. • The text such as "Kotler/Armstrong/Balasubramanian, Principles of Marketing, 19e" overlaps with decorative image. • Content is not displayed in a single column. This will result in low vision users finding it difficult to access the content when zoomed in. Similar issue found on "Multimedia Library Mainpage" page | X26: =Final_Report[[#This Row],[Code Snippet]] -> 0 | Y26: =IF(Final_Report[[#This Row],[Move to Report]]="Yes",VLOOKUP(E26,IssueVariable[],5,0),"N/A") -> All the content on the page should be available when user zoom in the page at 400%. | Z26: =Final_Report[[#This Row],[Expected Result]] -> All the content on the page should be available when user zoom in the page at 400%. | AA26: =IF(Final_Report[[#This Row],[Move to Report]]="Yes",VLOOKUP(E26,IssueVariable[],6,0),"N/A") -> Low vision users access content by using browser's zoom option turned on. Users have a tendency to zoom in up to 300-400%. Content at high zoom levels gets reflowed and is displayed in a single column. Low vision users find it very helpful to access content displayed in a single column as they do not have to scroll both ways; horizontally and vertically in order to read it. If the web page content fails to reflow when browser zoom is turned on, it becomes very difficult for low vision users to access the content. The content should not get overlapped and should not get cut off when users zoom in at high levels and the content should reflow and displayed in a single column. Additionally, all the content should be available for the users. | AB26: =IF(Final_Report[[#This Row],[Move to Report]]="Yes",VLOOKUP(E26,IssueVariable[],7,0),"N/A") -> Ensure that all the page content is visible when zoomed in. Use relative units to define font and container sizes in CSS to ensure that page's content reflows correctly when zoomed in. In addition, use CSS media queries to display web page content correctly when zoomed in or viewed using different devices, such as mobile phones, tablets etc. | AC26: =Final_Report[[#This Row],[Recommendation]] -> Ensure that all the page content is visible when zoomed in. Use relative units to define font and container sizes in CSS to ensure that page's content reflows correctly when zoomed in. In addition, use CSS media queries to display web page content correctly when zoomed in or viewed using different devices, such as mobile phones, tablets etc. | AD26: URL: https://www.pearsonmylabandmastering.com/northamerica Username: Aqavpat-edu1 Password: AuditPa559338 Course Title: AQA_VPAT_Kotler_Principles of Marketing 19e Course Id: auditor49388 1. Launch the above URL with the given credentials and navigate to the mentioned course | AE26: 2. Navigate to Course Home > Calendar interactive element and activate it. 3. View the page at 320X256 viewport size. | AF26: =Final_Report[[#This Row],[Steps to Reproduce]] -> 2. Navigate to Course Home > Calendar interactive element and activate it. 3. View the page at 320X256 viewport size. | AG26: =IF(Final_Report[[#This Row],[Move to Report]]="Yes",VLOOKUP(E26,IssueVariable[],9,0),"N/A") -> AA | AH26: =IF(Final_Report[[#This Row],[Move to Report]]="Yes",VLOOKUP(E26,IssueVariable[],10,0),"N/A") -> 1.4.10 Reflow | AI26: Marketing_26a, Marketing_26b, Marketing_26c, Marketing_26d | AJ26: Major | AK26: {=Table95[Tested on]} -> Windows: 11 MAC OS: 12 iOS: 15 Android OS: 10 | AL26: {=_xlfn.TEXTJOIN(", ",TRUE,_xlfn.UNIQUE(TRIM(MID(SUBSTITUTE((Final_Report[[#This Row],[WCAG 2.1 Success Criteria]] &_xlfn.CONCAT(" (Level ") &Final_Report[[#This Row],[WCAG 2.1 Conformance Level]] &_xlfn.CONCAT("), ") &IF(Final_Report[[#This Row],[Chrome/JAWS]]="Applicable","Windows_11, Chrome, JAWS, ", " ") &IF(Final_Report[[#This Row],[FF/NVDA]]="Applicable", "Windows_11, Firefox, NVDA, ", " ") &IF(Final_Report[[#This Row],[Chrome/NVDA]]="Applicable", "Windows_11, Chrome, NVDA, ", " ") &IF(Final_Report[[#This Row],[iOS/VO]]="Applicable", "iOS Tablet, VoiceOver, ", " ") &IF(Final_Report[[#This Row],[Mac/Safari/VO]]="Applicable", "macOS_12, Safari, VoiceOver, ", " ") &IF(Final_Report[[#This Row],[Mac/Chrome/VO]]="Applicable", "macOS_12, Chrome, VoiceOver, ", " ") &IF(Final_Report[[#This Row],[Android/Talkback]]="Applicable", "TalkBack, Android Tablet", " ") ) &", " &IF(ISERROR(FIND("iOS 13",INDEX(Keyword[Component Keyword],MATCH(TRUE,INDEX((Keyword[Component Keyword]<>0),0),0)))=FALSE),INDEX(Keyword[Component Keyword],MATCH(TRUE,INDEX((Keyword[Component Keyword]<>0),0),0)),SUBSTITUTE(INDEX(Keyword[Component Keyword],MATCH(TRUE,INDEX((Keyword[Component Keyword]<>0),0),0)),"iOS 13","iOS")),",",REPT(" ",999)),(ROW($AAN$1:INDEX($AAX:$AAX,LEN((Final_Report[[#This Row],[WCAG 2.1 Success Criteria]] &_xlfn.CONCAT(" (Level ") &Final_Report[[#This Row],[WCAG 2.1 Conformance Level]] &_xlfn.CONCAT("), ") &IF(Final_Report[[#This Row],[Chrome/JAWS]]="Applicable","Windows_11, Chrome, JAWS, ", " ") &IF(Final_Report[[#This Row],[FF/NVDA]]="Applicable", "Windows_11, Firefox, NVDA, ", " ") &IF(Final_Report[[#This Row],[Chrome/NVDA]]="Applicable", "Windows_11, Chrome, NVDA, ", " ") &IF(Final_Report[[#This Row],[iOS/VO]]="Applicable", "iOS Tablet, VoiceOver, ", " ") &IF(Final_Report[[#This Row],[Mac/Safari/VO]]="Applicable", "macOS_12, Safari, VoiceOver, ", " ") &IF(Final_Report[[#This Row],[Mac/Chrome/VO]]="Applicable", "macOS_12, Chrome, VoiceOver, ", " ") &IF(Final_Report[[#This Row],[Android/Talkback]]="Applicable", "TalkBack, Android Tablet", " ") ) &", " &IF(ISERROR(FIND("iOS 13",INDEX(Keyword[Component Keyword],MATCH(TRUE,INDEX((Keyword[Component Keyword]<>0),0),0)))=FALSE),INDEX(Keyword[Component Keyword],MATCH(TRUE,INDEX((Keyword[Component Keyword]<>0),0),0)),SUBSTITUTE(INDEX(Keyword[Component Keyword],MATCH(TRUE,INDEX((Keyword[Component Keyword]<>0),0),0)),"iOS 13","iOS")))-LEN(SUBSTITUTE((Final_Report[[#This Row],[WCAG 2.1 Success Criteria]] &_xlfn.CONCAT(" (Level ") &Final_Report[[#This Row],[WCAG 2.1 Conformance Level]] &_xlfn.CONCAT("), ") &IF(Final_Report[[#This Row],[Chrome/JAWS]]="Applicable","Windows_11, Chrome, JAWS, ", " ") &IF(Final_Report[[#This Row],[FF/NVDA]]="Applicable", "Windows_11, Firefox, NVDA, ", " ") &IF(Final_Report[[#This Row],[Chrome/NVDA]]="Applicable", "Windows_11, Chrome, NVDA, ", " ") &IF(Final_Report[[#This Row],[iOS/VO]]="Applicable", "iOS Tablet, VoiceOver, ", " ") &IF(Final_Report[[#This Row],[Mac/Safari/VO]]="Applicable", "macOS_12, Safari, VoiceOver, ", " ") &IF(Final_Report[[#This Row],[Mac/Chrome/VO]]="Applicable", "macOS_12, Chrome, VoiceOver, ", " ") &IF(Final_Report[[#This Row],[Android/Talkback]]="Applicable", "TalkBack, Android Tablet", " ") ) &", " &IF(ISERROR(FIND("iOS 13",INDEX(Keyword[Component Keyword],MATCH(TRUE,INDEX((Keyword[Component Keyword]<>0),0),0)))=FALSE),INDEX(Keyword[Component Keyword],MATCH(TRUE,INDEX((Keyword[Component Keyword]<>0),0),0)),SUBSTITUTE(INDEX(Keyword[Component Keyword],MATCH(TRUE,INDEX((Keyword[Component Keyword]<>0),0),0)),"iOS 13","iOS")),",",""))+1))-1)*999+1,999))))} -> 1.4.10 Reflow (Level AA), Windows_11, Chrome, JAWS, Firefox, NVDA, Accessibility, Audit, Marketing, MLM-XL, MLVISION, MyLab, US, VPAT | AM26: {=CONCATENATE(LEFT(AH26, SEARCH(" ", AH26) -1),", ",Labels[Labels])} -> 1.4.10, Accessibility, Audit, Marketing, MLM-XL, MLVISION, MyLab, US, VPAT | AN26: =IF(AJ26="Blocker","1 - Critical - showstopper",IF(AJ26="Critical","1 - Critical - showstopper",IF(AJ26="Major","1 - Critical - showstopper",IF(AJ26="Minor","3 - Medium - minor functionality broken",IF(AJ26="Trivial","4 - Low - cosmetic or usability"))))) -> 1 - Critical - showstopper | AO26: naveen.lagishetty | AP26: 5 | AQ26: 5 | AS26: 5 | AT26: manisha.prakash | AU26: collapse menu and check for all pages for p2 the overlapping instance and scroll bar pls check in known it is there or not and in Entire Course To Date tab along with above some content is partially unavailable by default also that content is partially available No reflow issue for P4 P8 Known issue | AV26: Detailing | AW26: 5 | AX26: Delete - QA | BC26: =VLOOKUP('Final Report'!D26,'Issue Variable'!A:N,11,FALSE) -> #N/A
A27: P7 | B27: =VLOOKUP(A27,URL[],2,0) -> Print Offers | C27: =VLOOKUP(A27,URL[],3,0) -> 0 | D27: Headings | E27: Inappropriate heading structure | F27: In iFrame heading text suchs as "Purchase a Loose-Leaf Printed Textbook" and "Redeem a Prepaid Print Textbook" heading marked as h3 which is inappropriate | G27: Applicable | H27: Applicable | I27: Applicable | P27: naveen.lagishetty | Q27: No QA Needed | S27: No | T27: =IF(Final_Report[[#This Row],[Move to Report]]="Yes",VLOOKUP(E27,IssueVariable[],3,0),"N/A") -> N/A | U27: =IF(Final_Report[[#This Row],[Move to Report]]="Yes",VLOOKUP(E27,IssueVariable[],4,0),"N/A") -> N/A | V27: =Final_Report[[#This Row],[Issue Description]] -> N/A | X27: =Final_Report[[#This Row],[Code Snippet]] -> 0 | Y27: =IF(Final_Report[[#This Row],[Move to Report]]="Yes",VLOOKUP(E27,IssueVariable[],5,0),"N/A") -> N/A | Z27: =Final_Report[[#This Row],[Expected Result]] -> N/A | AA27: =IF(Final_Report[[#This Row],[Move to Report]]="Yes",VLOOKUP(E27,IssueVariable[],6,0),"N/A") -> N/A | AB27: =IF(Final_Report[[#This Row],[Move to Report]]="Yes",VLOOKUP(E27,IssueVariable[],7,0),"N/A") -> N/A | AC27: =Final_Report[[#This Row],[Recommendation]] -> N/A | AE27: =IF(Final_Report[[#This Row],[Move to Report]]="Yes",VLOOKUP(E27,IssueVariable[],8,0),"N/A") -> N/A | AF27: =Final_Report[[#This Row],[Steps to Reproduce]] -> N/A | AG27: =IF(Final_Report[[#This Row],[Move to Report]]="Yes",VLOOKUP(E27,IssueVariable[],9,0),"N/A") -> N/A | AH27: =IF(Final_Report[[#This Row],[Move to Report]]="Yes",VLOOKUP(E27,IssueVariable[],10,0),"N/A") -> N/A | AK27: {=Table95[Tested on]} -> Windows: 11 MAC OS: 12 iOS: 15 Android OS: 10 | AL27: {=_xlfn.TEXTJOIN(", ",TRUE,_xlfn.UNIQUE(TRIM(MID(SUBSTITUTE((Final_Report[[#This Row],[WCAG 2.1 Success Criteria]] &_xlfn.CONCAT(" (Level ") &Final_Report[[#This Row],[WCAG 2.1 Conformance Level]] &_xlfn.CONCAT("), ") &IF(Final_Report[[#This Row],[Chrome/JAWS]]="Applicable","Windows_11, Chrome, JAWS, ", " ") &IF(Final_Report[[#This Row],[FF/NVDA]]="Applicable", "Windows_11, Firefox, NVDA, ", " ") &IF(Final_Report[[#This Row],[Chrome/NVDA]]="Applicable", "Windows_11, Chrome, NVDA, ", " ") &IF(Final_Report[[#This Row],[iOS/VO]]="Applicable", "iOS Tablet, VoiceOver, ", " ") &IF(Final_Report[[#This Row],[Mac/Safari/VO]]="Applicable", "macOS_12, Safari, VoiceOver, ", " ") &IF(Final_Report[[#This Row],[Mac/Chrome/VO]]="Applicable", "macOS_12, Chrome, VoiceOver, ", " ") &IF(Final_Report[[#This Row],[Android/Talkback]]="Applicable", "TalkBack, Android Tablet", " ") ) &", " &IF(ISERROR(FIND("iOS 13",INDEX(Keyword[Component Keyword],MATCH(TRUE,INDEX((Keyword[Component Keyword]<>0),0),0)))=FALSE),INDEX(Keyword[Component Keyword],MATCH(TRUE,INDEX((Keyword[Component Keyword]<>0),0),0)),SUBSTITUTE(INDEX(Keyword[Component Keyword],MATCH(TRUE,INDEX((Keyword[Component Keyword]<>0),0),0)),"iOS 13","iOS")),",",REPT(" ",999)),(ROW($AAN$1:INDEX($AAX:$AAX,LEN((Final_Report[[#This Row],[WCAG 2.1 Success Criteria]] &_xlfn.CONCAT(" (Level ") &Final_Report[[#This Row],[WCAG 2.1 Conformance Level]] &_xlfn.CONCAT("), ") &IF(Final_Report[[#This Row],[Chrome/JAWS]]="Applicable","Windows_11, Chrome, JAWS, ", " ") &IF(Final_Report[[#This Row],[FF/NVDA]]="Applicable", "Windows_11, Firefox, NVDA, ", " ") &IF(Final_Report[[#This Row],[Chrome/NVDA]]="Applicable", "Windows_11, Chrome, NVDA, ", " ") &IF(Final_Report[[#This Row],[iOS/VO]]="Applicable", "iOS Tablet, VoiceOver, ", " ") &IF(Final_Report[[#This Row],[Mac/Safari/VO]]="Applicable", "macOS_12, Safari, VoiceOver, ", " ") &IF(Final_Report[[#This Row],[Mac/Chrome/VO]]="Applicable", "macOS_12, Chrome, VoiceOver, ", " ") &IF(Final_Report[[#This Row],[Android/Talkback]]="Applicable", "TalkBack, Android Tablet", " ") ) &", " &IF(ISERROR(FIND("iOS 13",INDEX(Keyword[Component Keyword],MATCH(TRUE,INDEX((Keyword[Component Keyword]<>0),0),0)))=FALSE),INDEX(Keyword[Component Keyword],MATCH(TRUE,INDEX((Keyword[Component Keyword]<>0),0),0)),SUBSTITUTE(INDEX(Keyword[Component Keyword],MATCH(TRUE,INDEX((Keyword[Component Keyword]<>0),0),0)),"iOS 13","iOS")))-LEN(SUBSTITUTE((Final_Report[[#This Row],[WCAG 2.1 Success Criteria]] &_xlfn.CONCAT(" (Level ") &Final_Report[[#This Row],[WCAG 2.1 Conformance Level]] &_xlfn.CONCAT("), ") &IF(Final_Report[[#This Row],[Chrome/JAWS]]="Applicable","Windows_11, Chrome, JAWS, ", " ") &IF(Final_Report[[#This Row],[FF/NVDA]]="Applicable", "Windows_11, Firefox, NVDA, ", " ") &IF(Final_Report[[#This Row],[Chrome/NVDA]]="Applicable", "Windows_11, Chrome, NVDA, ", " ") &IF(Final_Report[[#This Row],[iOS/VO]]="Applicable", "iOS Tablet, VoiceOver, ", " ") &IF(Final_Report[[#This Row],[Mac/Safari/VO]]="Applicable", "macOS_12, Safari, VoiceOver, ", " ") &IF(Final_Report[[#This Row],[Mac/Chrome/VO]]="Applicable", "macOS_12, Chrome, VoiceOver, ", " ") &IF(Final_Report[[#This Row],[Android/Talkback]]="Applicable", "TalkBack, Android Tablet", " ") ) &", " &IF(ISERROR(FIND("iOS 13",INDEX(Keyword[Component Keyword],MATCH(TRUE,INDEX((Keyword[Component Keyword]<>0),0),0)))=FALSE),INDEX(Keyword[Component Keyword],MATCH(TRUE,INDEX((Keyword[Component Keyword]<>0),0),0)),SUBSTITUTE(INDEX(Keyword[Component Keyword],MATCH(TRUE,INDEX((Keyword[Component Keyword]<>0),0),0)),"iOS 13","iOS")),",",""))+1))-1)*999+1,999))))} -> N/A (Level N/A), Windows_11, Chrome, JAWS, Firefox, NVDA, Accessibility, Audit, Marketing, MLM-XL, MLVISION, MyLab, US, VPAT | AM27: {=CONCATENATE(LEFT(AH27, SEARCH(" ", AH27) -1),", ",Labels[Labels])} -> #VALUE! | AN27: =IF(AJ27="Blocker","1 - Critical - showstopper",IF(AJ27="Critical","1 - Critical - showstopper",IF(AJ27="Major","1 - Critical - showstopper",IF(AJ27="Minor","3 - Medium - minor functionality broken",IF(AJ27="Trivial","4 - Low - cosmetic or usability"))))) -> FALSE | BC27: =VLOOKUP('Final Report'!D27,'Issue Variable'!A:N,11,FALSE) -> #N/A
A28: P8 | B28: =VLOOKUP(A28,URL[],2,0) -> eTextbook | C28: =VLOOKUP(A28,URL[],3,0) -> 0 | D28: Headings | E28: Inappropriate heading structure | F28: In iFrame heading structure is in appropriate, "Get access to your textbook..." - H1 "anytime, anywhere, any way you want" - H2 "Principles of Marketing" - H2 | G28: Applicable | H28: Applicable | I28: Applicable | J28: Applicable | K28: Applicable | L28: Applicable | M28: Applicable | P28: naveen.lagishetty | Q28: No QA Needed | S28: Yes | T28: Web: eTextbook: Inappropriate heading structure | U28: Heading structure was found to be inappropriate. The texts such as "Get access to your textbook..." is defined as H1 and "anytime, anywhere, any way you want", "Principles of Marketing" is defined as H2 in the main content area. As a result, screen reader users found it difficult to understand the page's content structure. | V28: =Final_Report[[#This Row],[Issue Description]] -> Heading structure was found to be inappropriate. The texts such as "Get access to your textbook..." is defined as H1 and "anytime, anywhere, any way you want", "Principles of Marketing" is defined as H2 in the main content area. As a result, screen reader users found it difficult to understand the page's content structure. | W28: <h1>Get access to your textbook...</h1> <h2>anytime, anywhere, any way you want</h2> <h2><i>Principles of Marketing</i>, 19e</h2> | X28: =Final_Report[[#This Row],[Code Snippet]] -> <h1>Get access to your textbook...</h1> <h2>anytime, anywhere, any way you want</h2> <h2><i>Principles of Marketing</i>, 19e</h2> | Y28: Appropriate heading structure should be used on the page so that screen reader user can understand the structure. Replace <h1> to <h3> and <h2> to <h4>. <h3>Get access to your textbook...</h3> <h4>anytime, anywhere, any way you want</h4> <h4><i>Principles of Marketing</i>, 19e</h4> | Z28: =Final_Report[[#This Row],[Expected Result]] -> Appropriate heading structure should be used on the page so that screen reader user can understand the structure. Replace <h1> to <h3> and <h2> to <h4>. <h3>Get access to your textbook...</h3> <h4>anytime, anywhere, any way you want</h4> <h4><i>Principles of Marketing</i>, 19e</h4> | AA28: =IF(Final_Report[[#This Row],[Move to Report]]="Yes",VLOOKUP(E28,IssueVariable[],6,0),"N/A") -> Headings are used to add structure to the web page. Appropriate heading structure enables screen reader users to understand the page structure. Use headings in the correct sequence; such as h2 should follow h1, h3 should follow h2 and so on. Skipping heading levels will confuse screen reader users as to some information is not being read out to them. Making text appear as headings visually by changing the font size or making the text strong will not be identified as a heading by the screen reader. In the absence of appropriate heading level mark-up, screen reader will treat it as a piece of text and important structure information will not be made available to the users. In addition, screen reader users have a tendency to skim through the page using heading level navigation. Appropriate heading structure enables screen reader users to understand the page structure as well as navigate through the page easily. | AB28: Use heading levels as per specification such as <h1> should be followed by <h2>, <h3> and so on. Even though this is required at WCAG 2.1 at Level AAA, it is recommended that the above issue be addressed as screen reader users rely on headings heavily to understand the page structure. In the above example, define the heading structure as given below: | AC28: =Final_Report[[#This Row],[Recommendation]] -> Use heading levels as per specification such as <h1> should be followed by <h2>, <h3> and so on. Even though this is required at WCAG 2.1 at Level AAA, it is recommended that the above issue be addressed as screen reader users rely on headings heavily to understand the page structure. In the above example, define the heading structure as given below: | AD28: URL: https://www.pearsonmylabandmastering.com/northamerica Username: Aqavpat-edu1 Password: AuditPa559338 Course Title: AQA_VPAT_Kotler_Principles of Marketing 19e Course Id: auditor49388 1. Launch the above URL with the given credentials and navigate to the mentioned course | AE28: 2. Navigate to eTextbook interactive element and activate it. 3. Inspect the text such as "Get access to your textbook...", "anytime, anywhere, any way you want", " Principles of Marketing". | AF28: =Final_Report[[#This Row],[Steps to Reproduce]] -> 2. Navigate to eTextbook interactive element and activate it. 3. Inspect the text such as "Get access to your textbook...", "anytime, anywhere, any way you want", " Principles of Marketing". | AG28: =IF(Final_Report[[#This Row],[Move to Report]]="Yes",VLOOKUP(E28,IssueVariable[],9,0),"N/A") -> AAA | AH28: =IF(Final_Report[[#This Row],[Move to Report]]="Yes",VLOOKUP(E28,IssueVariable[],10,0),"N/A") -> 2.4.10 Section Headings | AI28: Marketing_28a, Marketing_28b | AJ28: Major | AK28: {=Table95[Tested on]} -> Windows: 11 MAC OS: 12 iOS: 15 Android OS: 10 | AL28: {=_xlfn.TEXTJOIN(", ",TRUE,_xlfn.UNIQUE(TRIM(MID(SUBSTITUTE((Final_Report[[#This Row],[WCAG 2.1 Success Criteria]] &_xlfn.CONCAT(" (Level ") &Final_Report[[#This Row],[WCAG 2.1 Conformance Level]] &_xlfn.CONCAT("), ") &IF(Final_Report[[#This Row],[Chrome/JAWS]]="Applicable","Windows_11, Chrome, JAWS, ", " ") &IF(Final_Report[[#This Row],[FF/NVDA]]="Applicable", "Windows_11, Firefox, NVDA, ", " ") &IF(Final_Report[[#This Row],[Chrome/NVDA]]="Applicable", "Windows_11, Chrome, NVDA, ", " ") &IF(Final_Report[[#This Row],[iOS/VO]]="Applicable", "iOS Tablet, VoiceOver, ", " ") &IF(Final_Report[[#This Row],[Mac/Safari/VO]]="Applicable", "macOS_12, Safari, VoiceOver, ", " ") &IF(Final_Report[[#This Row],[Mac/Chrome/VO]]="Applicable", "macOS_12, Chrome, VoiceOver, ", " ") &IF(Final_Report[[#This Row],[Android/Talkback]]="Applicable", "TalkBack, Android Tablet", " ") ) &", " &IF(ISERROR(FIND("iOS 13",INDEX(Keyword[Component Keyword],MATCH(TRUE,INDEX((Keyword[Component Keyword]<>0),0),0)))=FALSE),INDEX(Keyword[Component Keyword],MATCH(TRUE,INDEX((Keyword[Component Keyword]<>0),0),0)),SUBSTITUTE(INDEX(Keyword[Component Keyword],MATCH(TRUE,INDEX((Keyword[Component Keyword]<>0),0),0)),"iOS 13","iOS")),",",REPT(" ",999)),(ROW($AAN$1:INDEX($AAX:$AAX,LEN((Final_Report[[#This Row],[WCAG 2.1 Success Criteria]] &_xlfn.CONCAT(" (Level ") &Final_Report[[#This Row],[WCAG 2.1 Conformance Level]] &_xlfn.CONCAT("), ") &IF(Final_Report[[#This Row],[Chrome/JAWS]]="Applicable","Windows_11, Chrome, JAWS, ", " ") &IF(Final_Report[[#This Row],[FF/NVDA]]="Applicable", "Windows_11, Firefox, NVDA, ", " ") &IF(Final_Report[[#This Row],[Chrome/NVDA]]="Applicable", "Windows_11, Chrome, NVDA, ", " ") &IF(Final_Report[[#This Row],[iOS/VO]]="Applicable", "iOS Tablet, VoiceOver, ", " ") &IF(Final_Report[[#This Row],[Mac/Safari/VO]]="Applicable", "macOS_12, Safari, VoiceOver, ", " ") &IF(Final_Report[[#This Row],[Mac/Chrome/VO]]="Applicable", "macOS_12, Chrome, VoiceOver, ", " ") &IF(Final_Report[[#This Row],[Android/Talkback]]="Applicable", "TalkBack, Android Tablet", " ") ) &", " &IF(ISERROR(FIND("iOS 13",INDEX(Keyword[Component Keyword],MATCH(TRUE,INDEX((Keyword[Component Keyword]<>0),0),0)))=FALSE),INDEX(Keyword[Component Keyword],MATCH(TRUE,INDEX((Keyword[Component Keyword]<>0),0),0)),SUBSTITUTE(INDEX(Keyword[Component Keyword],MATCH(TRUE,INDEX((Keyword[Component Keyword]<>0),0),0)),"iOS 13","iOS")))-LEN(SUBSTITUTE((Final_Report[[#This Row],[WCAG 2.1 Success Criteria]] &_xlfn.CONCAT(" (Level ") &Final_Report[[#This Row],[WCAG 2.1 Conformance Level]] &_xlfn.CONCAT("), ") &IF(Final_Report[[#This Row],[Chrome/JAWS]]="Applicable","Windows_11, Chrome, JAWS, ", " ") &IF(Final_Report[[#This Row],[FF/NVDA]]="Applicable", "Windows_11, Firefox, NVDA, ", " ") &IF(Final_Report[[#This Row],[Chrome/NVDA]]="Applicable", "Windows_11, Chrome, NVDA, ", " ") &IF(Final_Report[[#This Row],[iOS/VO]]="Applicable", "iOS Tablet, VoiceOver, ", " ") &IF(Final_Report[[#This Row],[Mac/Safari/VO]]="Applicable", "macOS_12, Safari, VoiceOver, ", " ") &IF(Final_Report[[#This Row],[Mac/Chrome/VO]]="Applicable", "macOS_12, Chrome, VoiceOver, ", " ") &IF(Final_Report[[#This Row],[Android/Talkback]]="Applicable", "TalkBack, Android Tablet", " ") ) &", " &IF(ISERROR(FIND("iOS 13",INDEX(Keyword[Component Keyword],MATCH(TRUE,INDEX((Keyword[Component Keyword]<>0),0),0)))=FALSE),INDEX(Keyword[Component Keyword],MATCH(TRUE,INDEX((Keyword[Component Keyword]<>0),0),0)),SUBSTITUTE(INDEX(Keyword[Component Keyword],MATCH(TRUE,INDEX((Keyword[Component Keyword]<>0),0),0)),"iOS 13","iOS")),",",""))+1))-1)*999+1,999))))} -> 2.4.10 Section Headings (Level AAA), Windows_11, Chrome, JAWS, Firefox, NVDA, iOS Tablet, VoiceOver, macOS_12, Safari, TalkBack, Android Tablet, Accessibility, Audit, Marketing, MLM-XL, MLVISION, MyLab, US, VPAT | AM28: {=CONCATENATE(LEFT(AH28, SEARCH(" ", AH28) -1),", ",Labels[Labels])} -> 2.4.10, Accessibility, Audit, Marketing, MLM-XL, MLVISION, MyLab, US, VPAT | AN28: =IF(AJ28="Blocker","1 - Critical - showstopper",IF(AJ28="Critical","1 - Critical - showstopper",IF(AJ28="Major","1 - Critical - showstopper",IF(AJ28="Minor","3 - Medium - minor functionality broken",IF(AJ28="Trivial","4 - Low - cosmetic or usability"))))) -> 1 - Critical - showstopper | AO28: naveen.lagishetty | AP28: 5 | AQ28: 5 | AS28: 5 | AT28: manisha.prakash | AU28: ACDS-241469 | AX28: Delete - QA | BC28: =VLOOKUP('Final Report'!D28,'Issue Variable'!A:N,11,FALSE) -> #N/A
